Workbook

Sheet Общее, домены, поддомены

Sheet Результаты аудита
F1: Уровень сложности практики | O1: Инструкция по заполнению описана в репозитории проекта на Github
B2: Модель | C2: Домен | D2: Описание поддомена | E2: Поддомен | F2: 0. Uninitiated | G2: 1. Beginners | H2: 2. Intermediate | I2: 3. Advanced | J2: 4. Experts | K2: % выполнения всех практик кажого ПОДдомена DAF | L2: % выполнения всех практик кажого домена DAF | M2: % выполнения всех практик всего DAF | O2: Уровни Кирилламиды | Q2: % соответствия уровню зрелости по Кирилламиде | R2: Итоговый уровень зрелости Компании (из 7 возможных) по DAF
B3: Технологии | C3: Контроль ИБ артефактов, зависимостей и образов | D3: Контроль использования сторонних компонентов | E3: T-ADI-DEP | F3: =IF(Практики!F3="Неверно","Не реализовывается","Реализовывается") -> Реализовывается | G3: =Практики!H4 -> 0 | H3: =Практики!H9 -> 0 | I3: =Практики!H11 -> 0 | J3: =Практики!H14 -> 0 | K3: =SUM(G3:J3)/4 -> 0 | L3: =AVERAGE(K3:K4) -> 0 | M3: =AVERAGE(K3:K42) -> 0 | O3: 0 | P3: Хаос | Q3: =Кирилламида!B86 -> 0 | R3: =R42 -> 0
D4: Управление артефактами | E4: T-ADI-ART | F4: =IF(Практики!F16="Неверно","Не реализовывается","Реализовывается") -> Реализовывается | G4: =Практики!H17 -> 0 | H4: =Практики!H22 -> 0 | I4: =Практики!H24 -> 0 | J4: =Практики!H26 -> 0 | K4: =SUM(G4:J4)/4 -> 0 | O4: 1 | P4: Минимальный | Q4: =Кирилламида!C86 -> 0
C5: Защита окружения разработки | D5: Защита рабочих мест разработчика | E5: T-DEV-COMP | F5: =IF(Практики!F32="Неверно","Не реализовывается","Реализовывается") -> Реализовывается | G5: =Практики!H33 -> 0 | H5: =Практики!H35 -> 0 | K5: =SUM(G5:H5)/2 -> 0 | L5: =AVERAGE(K5:K10) -> 0 | O5: 2 | P5: Базовый | Q5: =Кирилламида!D86 -> 0
D6: Защита секретов | E6: T-DEV-SM | F6: =IF(Практики!F36="Неверно","Не реализовывается","Реализовывается") -> Реализовывается | G6: =Практики!H37 -> 0 | H6: =Практики!H39 -> 0 | I6: =Практики!H41 -> 0 | J6: =Практики!H43 -> 0 | K6: =SUM(G6:J6)/4 -> 0 | O6: 3 | P6: Повышенный | Q6: =Кирилламида!E86 -> 0
D7: Защита Build-среды | E7: T-DEV-BLD | F7: =IF(Практики!F44="Неверно","Не реализовывается","Реализовывается") -> Реализовывается | G7: =Практики!H45 -> 0 | H7: =Практики!H49 -> 0 | I7: =Практики!H50 -> 0 | J7: =Практики!H53 -> 0 | K7: =SUM(G7:J7)/4 -> 0 | O7: 4 | P7: Продвинутый | Q7: =Кирилламида!F86 -> 0
D8: Защита source code management (SCM) | E8: T-DEV-SCM | F8: =IF(Практики!F54="Неверно","Не реализовывается","Реализовывается") -> Реализовывается | G8: =Практики!H55 -> 0 | H8: =Практики!H62 -> 0 | I8: =Практики!H68 -> 0 | J8: =Практики!H72 -> 0 | K8: =SUM(G8:J8)/4 -> 0 | O8: 5 | P8: Развитый | Q8: =Кирилламида!G86 -> 0
D9: Контроль внесения изменений в исходный код | E9: T-DEV-SRC | F9: =IF(Практики!F75="Неверно","Не реализовывается","Реализовывается") -> Реализовывается | G9: =Практики!H76 -> 0 | H9: =Практики!H81 -> 0 | I9: =Практики!H87 -> 0 | J9: =Практики!H93 -> 0 | K9: =SUM(G9:J9)/4 -> 0 | O9: 6 | P9: Экспертный | Q9: =Кирилламида!H86 -> 0
D10: Защита конвейера сборки | E10: T-DEV-CICD | F10: =IF(Практики!F94="Неверно","Не реализовывается","Реализовывается") -> Реализовывается | G10: =Практики!H95 -> 0 | H10: =Практики!H100 -> 0 | I10: =Практики!H102 -> 0 | J10: =Практики!H103 -> 0 | K10: =SUM(G10:J10)/4 -> 0 | O10: 7 | P10: Космический | Q10: =Кирилламида!I86 -> 0
C11: Инструментальный анализ на наличие дефектов ИБ | D11: Безопасность заказной разработки | E11: T-CODE-SPC | F11: =IF(Практики!F106="Неверно","Не реализовывается","Реализовывается") -> Реализовывается | G11: =Практики!H107 -> 0 | H11: =Практики!H109 -> 0 | I11: =Практики!H113 -> 0 | J11: =Практики!H118 -> 0 | K11: =SUM(G11:J11)/4 -> 0 | L11: =AVERAGE(K11:K16) -> 0
D12: Статический анализ (SAST) | E12: T-CODE-SST | F12: =IF(Практики!F119="Неверно","Не реализовывается","Реализовывается") -> Реализовывается | G12: =Практики!H120 -> 0 | H12: =Практики!H122 -> 0 | I12: =Практики!H126 -> 0 | J12: =Практики!H129 -> 0 | K12: =SUM(G12:J12)/4 -> 0
D13: Композиционный анализ (SCA) | E13: T-CODE-SC | F13: =IF(Практики!F130="Неверно","Не реализовывается","Реализовывается") -> Реализовывается | G13: =Практики!H131 -> 0 | H13: =Практики!H134 -> 0 | I13: =Практики!H139 -> 0 | J13: =Практики!H143 -> 0 | K13: =SUM(G13:J13)/4 -> 0
D14: Анализ образов контейнеров | E14: T-CODE-IMG | F14: =IF(Практики!F144="Неверно","Не реализовывается","Реализовывается") -> Реализовывается | G14: =Практики!H145 -> 0 | H14: =Практики!H148 -> 0 | I14: =Практики!H151 -> 0 | J14: =Практики!H152 -> 0 | K14: =SUM(G14:J14)/4 -> 0
D15: Идентификация секретов | E15: T-CODE-SECDN | F15: =IF(Практики!F154="Неверно","Не реализовывается","Реализовывается") -> Реализовывается | G15: =Практики!H155 -> 0 | H15: =Практики!H159 -> 0 | I15: =Практики!H162 -> 0 | J15: =Практики!H165 -> 0 | K15: =SUM(G15:J15)/4 -> 0
D16: Контроль безопасности Dockerfile’ов | E16: T-CODE-DOCKERFS | F16: =IF(Практики!F166="Неверно","Не реализовывается","Реализовывается") -> Реализовывается | G16: =Практики!H167 -> 0 | H16: =Практики!H169 -> 0 | K16: =SUM(G16:H16)/2 -> 0
C17: Анализ ПО в режиме runtime - Preprod | D17: Динамический анализ приложений (DAST) в PREPROD среде | E17: T-PREPROD-DAST | F17: =IF(Практики!F172="Неверно","Не реализовывается","Реализовывается") -> Реализовывается | G17: =Практики!H173 -> 0 | H17: =Практики!H175 -> 0 | I17: =Практики!H179 -> 0 | J17: =Практики!H183 -> 0 | K17: =SUM(G17:J17)/4 -> 0 | L17: =AVERAGE(K17:K21) -> 0
D18: Тестирование на проникновение перед внедрением приложений в продуктив | E18: T-PREPROD-PENTEST | F18: =IF(Практики!F186="Неверно","Не реализовывается","Реализовывается") -> Реализовывается | G18: =Практики!H187 -> 0 | H18: =Практики!H190 -> 0 | J18: =Практики!H191 -> 0 | K18: =SUM(G18:J18)/3 -> 0
D19: Функциональное ИБ-тестирование | E19: T-PREPROD-SECTEST | F19: =IF(Практики!F192="Неверно","Не реализовывается","Реализовывается") -> Реализовывается | G19: =Практики!H193 -> 0 | H19: =Практики!H194 -> 0 | I19: =Практики!H196 -> 0 | K19: =SUM(G19:I19)/3 -> 0
D20: Контроль безопасности манифестов (k8s, terraform и т.д.) | E20: T-PREPROD-MANSEC | F20: =IF(Практики!F209="Неверно","Не реализовывается","Реализовывается") -> Реализовывается | G20: =Практики!H210 -> 0 | H20: =Практики!H211 -> 0 | K20: =SUM(G20:H20)/2 -> 0
D21: Анализ инфраструктуры PREPROD среды на уязвимости | E21: T-PREPROD-VULN | F21: =IF(Практики!F197="Неверно","Не реализовывается","Реализовывается") -> Реализовывается | G21: =Практики!H198 -> 0 | H21: =Практики!H200 -> 0 | I21: =Практики!H203 -> 0 | J21: =Практики!H207 -> 0 | K21: =SUM(G21:J21)/4 -> 0
C22: Защита ПО и инфраструктуры в режиме runtime | D22: Управление секретами | E22: T-PROD-SM | F22: =IF(Практики!F214="Неверно","Не реализовывается","Реализовывается") -> Реализовывается | G22: =Практики!H215 -> 0 | H22: =Практики!H217 -> 0 | I22: =Практики!H219 -> 0 | J22: =Практики!H222 -> 0 | K22: =SUM(G22:J22)/4 -> 0 | L22: =AVERAGE(K22:K29) -> 0
D23: Динамический анализ приложений (DAST) в продуктивной среде | E23: T-PROD-DAST | F23: =IF(Практики!F233="Неверно","Не реализовывается","Реализовывается") -> Реализовывается | G23: =Практики!H234 -> 0 | H23: =Практики!H237 -> 0 | I23: =Практики!H241 -> 0 | J23: =Практики!H245 -> 0 | K23: =SUM(G23:J23)/4 -> 0
D24: Тестирование на проникновение продуктивной среды | E24: T-PROD-PENTEST | F24: =IF(Практики!F225="Неверно","Не реализовывается","Реализовывается") -> Реализовывается | G24: =Практики!H226 -> 0 | H24: =Практики!H229 -> 0 | I24: =Практики!H230 -> 0 | J24: =Практики!H231 -> 0 | K24: =SUM(G24:J24)/4 -> 0
D25: Управление изменениями инфраструктуры и доступом к ней | E25: T-PROD-ACCESS | F25: =IF(Практики!F248="Неверно","Не реализовывается","Реализовывается") -> Реализовывается | G25: =Практики!H249 -> 0 | H25: =Практики!H254 -> 0 | I25: =Практики!H256 -> 0 | J25: =Практики!H257 -> 0 | K25: =SUM(G25:J25)/4 -> 0
D26: Контроль сетевого трафика (L4-L7) | E26: T-PROD-NETWORK | F26: =IF(Практики!F258="Неверно","Не реализовывается","Реализовывается") -> Реализовывается | G26: =Практики!H259 -> 0 | H26: =Практики!H261 -> 0 | I26: =Практики!H263 -> 0 | K26: =SUM(G26:I26)/3 -> 0
D27: Контроль выполняемых и процессов и их прав доступа | E27: T-PROD-RUN | F27: =IF(Практики!F264="Неверно","Не реализовывается","Реализовывается") -> Реализовывается | G27: =Практики!H265 -> 0 | H27: =Практики!H266 -> 0 | I27: =Практики!H267 -> 0 | K27: =SUM(G27:I27)/3 -> 0
D28: Анализ инфраструктуры PROD среды на уязвимости | E28: T-PROD-VULN | F28: =IF(Практики!F268="Неверно","Не реализовывается","Реализовывается") -> Реализовывается | G28: =Практики!H269 -> 0 | H28: =Практики!H271 -> 0 | I28: =Практики!H274 -> 0 | J28: =Практики!H278 -> 0 | K28: =SUM(G28:J28)/4 -> 0
D29: Анализ событий информационной безопасности | E29: T-PROD-EVENTS | F29: =IF(Практики!F280="Неверно","Не реализовывается","Реализовывается") -> Реализовывается | H29: =Практики!H281 -> 0 | I29: =Практики!H282 -> 0 | K29: =SUM(H29:I29)/2 -> 0
B30: Процессы | C30: Обучение и база знаний | D30: Обучение специалистов | E30: P-EDU-AWR | F30: =IF(Практики!F285="Неверно","Не реализовывается","Реализовывается") -> Реализовывается | G30: =Практики!H286 -> 0 | H30: =Практики!H288 -> 0 | I30: =Практики!H292 -> 0 | J30: =Практики!H294 -> 0 | K30: =SUM(G30:J30)/4 -> 0 | L30: =AVERAGE(K30:K31) -> 0
D31: Управление базой знаний DSO | E31: P-EDU-KB | F31: =IF(Практики!F295="Неверно","Не реализовывается","Реализовывается") -> Реализовывается | G31: =Практики!H296 -> 0 | H31: =Практики!H297 -> 0 | I31: =Практики!H299 -> 0 | J31: =Практики!H302 -> 0 | K31: =SUM(G31:J31)/4 -> 0
C32: Контроль и формирование требований ИБ к ПО | D32: Оценка критичности приложений и моделирование угроз | E32: P-REQ-TM | F32: =IF(Практики!F306="Неверно","Не реализовывается","Реализовывается") -> Реализовывается | G32: =Практики!H307 -> 0 | H32: =Практики!H310 -> 0 | I32: =Практики!H313 -> 0 | J32: =Практики!H316 -> 0 | K32: =SUM(G32:J32)/4 -> 0 | L32: =AVERAGE(K32:K36) -> 0
D33: Определение требований ИБ, предъявляемых к ПО | E33: P-REQ-RD | F33: =IF(Практики!F317="Неверно","Не реализовывается","Реализовывается") -> Реализовывается | G33: =Практики!H318 -> 0 | H33: =Практики!H320 -> 0 | I33: =Практики!H323 -> 0 | J33: =Практики!H326 -> 0 | K33: =SUM(G33:J33)/4 -> 0
D34: Контроль выполнения требований ИБ | E34: P-REQ-CR | F34: =IF(Практики!F327="Неверно","Не реализовывается","Реализовывается") -> Реализовывается | G34: =Практики!H328 -> 0 | H34: =Практики!H329 -> 0 | I34: =Практики!H330 -> 0 | J34: =Практики!H331 -> 0 | K34: =SUM(G34:J34)/4 -> 0 | O34: Порог выполнения ("прохождения") уровня каждого уровня DAF | R34: 0.8
D35: Разработка стандартов конфигураций разрабатываемого ПО | E35: P-REQ-STDR-App | F35: =IF(Практики!F332="Неверно","Не реализовывается","Реализовывается") -> Реализовывается | G35: =Практики!H333 -> 0 | H35: =Практики!H335 -> 0 | I35: =Практики!H336 -> 0 | J35: =Практики!H338 -> 0 | K35: =SUM(G35:J35)/4 -> 0
D36: Разработка стандартов конфигураций для компонентов инфраструктуры | E36: P-REQ-STDR-Infr | F36: =IF(Практики!F339="Неверно","Не реализовывается","Реализовывается") -> Реализовывается | G36: =Практики!H340 -> 0 | H36: =Практики!H342 -> 0 | I36: =Практики!H344 -> 0 | J36: =Практики!H347 -> 0 | K36: =SUM(G36:J36)/4 -> 0 | O36: Согласно методике DAF уровень зрелости присваивается, если выполнено два ОБЯЗАТЕЛЬНЫХ условия: "Выполнено не менее 80% практик уровня Кирилламиды" И (!!!) "все предыдущие уровни зрелости выполнены не менее чем на 80%" Примечание к формулам расчета справа: 1. Сначала определяем закрыт ли каждый из уровней "Хаос" (уровень 0) И "Минимальный" (уровень 1) не менее чем на 80% (ячейкаR37). Если оба закрыты, то присваиваем уровень 1, если нет - уровень 0 2. Затем определяем закрыт ли уровень "Базовый" на 80 и более %. Если да - присваиваем уровень 2, если нет - смотрим значение ячейки R37 3. Затем определяем закрыт ли уровень "Повышенный" на 80 и более %. Если да - присваиваем уровень 3, если нет - смотрим значение ячейки R38 4. итд | R36: =IF(AND(Q3>=R34, Q4>=R34),1,0) -> 0
C37: Управление ИБ дефектами | D37: Обработка дефектов ИБ | E37: P-DEFECT-MNG | F37: =IF(Практики!F350="Неверно","Не реализовывается","Реализовывается") -> Реализовывается | G37: =Практики!H351 -> 0 | H37: =Практики!H352 -> 0 | I37: =Практики!H354 -> 0 | J37: =Практики!H357 -> 0 | K37: =SUM(G37:J37)/4 -> 0 | L37: =AVERAGE(K37:K38) -> 0 | R37: =IF(AND(R36=1,Q5>=R34),2,R36) -> 0
D38: Консолидация дефектов ИБ | E38: P-DEFECT-CNS | F38: =IF(Практики!F358="Неверно","Не реализовывается","Реализовывается") -> Реализовывается | G38: =Практики!H359 -> 0 | H38: =Практики!H361 -> 0 | I38: =Практики!H362 -> 0 | J38: =Практики!H365 -> 0 | K38: =SUM(G38:J38)/4 -> 0 | R38: =IF(AND(R37=2,Q6>=R34),3,R37) -> 0
C39: Оценка эффективности процессов | D39: Управление набором метрик ИБ | E39: P-MET-SET | F39: =IF(Практики!F368="Неверно","Не реализовывается","Реализовывается") -> Реализовывается | H39: =Практики!H369 -> 0 | I39: =Практики!H371 -> 0 | K39: =SUM(H39:I39)/2 -> 0 | L39: =AVERAGE(K39:K40) -> 0 | R39: =IF(AND(R38=3,Q7>=R34),4,R38) -> 0
D40: Контроль исполнения метрик | E40: P-MET-EX | F40: =IF(Практики!F373="Неверно","Не реализовывается","Реализовывается") -> Реализовывается | H40: =Практики!H374 -> 0 | I40: =Практики!H376 -> 0 | J40: =Практики!H379 -> 0 | K40: =SUM(H40:J40)/3 -> 0 | R40: =IF(AND(R39=4,Q8>=R34),5,R39) -> 0
C41: Функциональные роли | D41: Security Champions | E41: P-ROLE-SC | F41: =IF(Практики!F382="Неверно","Не реализовывается","Реализовывается") -> Реализовывается | G41: =Практики!H383 -> 0 | H41: =Практики!H384 -> 0 | I41: =Практики!H386 -> 0 | J41: =Практики!H390 -> 0 | K41: =SUM(G41:J41)/4 -> 0 | L41: =AVERAGE(K41:K42) -> 0 | R41: =IF(AND(R40=5,Q9>=R34),6,R40) -> 0
D42: Разграничение ролей процесса DSO | E42: P-ROLE-RESP | F42: =IF(Практики!F394="Неверно","Не реализовывается","Реализовывается") -> Реализовывается | G42: =Практики!H395 -> 0 | H42: =Практики!H397 -> 0 | I42: =Практики!H401 -> 0 | K42: =SUM(G42:I42)/3 -> 0 | R42: =IF(AND(R41=6,Q10>=R34),7,R41) -> 0

Sheet Практики
B1: Поддомен | C1: ID | D1: Практики и их требования | E1: Область действия практики | F1: Оценка | G1: Уровень сложности практики | H1: Соответствие уровню сложности | I1: % выполнения группы практик | J1: Уровень Кирилламиды | K1: BSIMM v14 | L1: DSOMM | M1: OWASP SAMMv2 | N1: ПЗ ЦБ | O1: ГОСТ Р 56939 | P1: AppSec Table Top (Positive) | Q1: Комментарии
B2: Домен "Контроль ИБ артефактов, зависимостей и образов"
B3: ='Результаты аудита'!D3 -> Контроль использования сторонних компонентов | C3: T-ADI-DEP-0-1 | D3: Управление зависимостями (Dependencies) в исходном коде осуществляется в каком-либо виде | E3: Отдельная команда | F3: Не заполнено | G3: 0 | H3: =(COUNTIF(F3:F3,$F$407))/COUNTA(F3:F3) -> 0 | I3: =SUM(H4:H15)/4 -> 0 | J3: 0 | L3: 4 | M3: SB-B-1
C4: T-ADI-DEP-1-1 | D4: Существуют (формализованы) единые правила, определяющие возможность использования тех или иных зависимостей в коде. Например, есть утвержденный документ, и/или страница в базе знаний, описывающие порядок использования зависимостей в коде. | E4: Отдельная команда | F4: Не заполнено | G4: 1 | H4: =(COUNTIF(F4:F8,$G$409)+(COUNTIF(F4:F8,$G$408)*0.5))/(COUNTA(F4:F8)-COUNTIF(F4:F8,$G$410)) -> 0 | J4: 2 | M4: SB-B-2 | N4: 7.4.2.1 | P4: TP2
C5: T-ADI-DEP-1-2 | D5: Обновление существующих зависимостей выполняется вручную. Например, если возникла необходимость использовать новую версию библиотеки в коде, то ее вручную выгружают и добавляют в проект | E5: Отдельная команда | F5: Не заполнено | J5: 2 | L5: 9 | M5: SB-B-2
C6: T-ADI-DEP-1-3 | D6: Существует (описан, формализован) план реагирования на события ИБ, связанных с зависимостями. | E6: Отдельная команда | F6: Не заполнено | J6: 2 | K6: SR2.7 | N6: 7.4.2.1 | O6: 5.16.2.1 | P6: MI4
C7: T-ADI-DEP-1-4 | D7: Выполняется харденинг (безопасная настройка) файлов конфигураций используемых пакетов open source software - OSS (например, nuget.config, .npmrc, pip.conf, pom.xml, etc.). | E7: Отдельная команда | F7: Не заполнено | J7: 2 | L7: 83 91 56 | M7: EM-A-1 | P7: CNFG1
C8: T-ADI-DEP-1-5 | D8: Зависимости с тэгом "latest" не применяются | E8: Отдельная команда | F8: Не заполнено | J8: 2 | M8: SA-B-1
C9: T-ADI-DEP-2-1 | D9: Разработчики получают и используют OSS компоненты, применяя только стандартизованные (формализованные и утвержденные) методы | E9: Отдельная команда | F9: Не заполнено | G9: 2 | H9: =(COUNTIF(F9:F10,$G$409)+(COUNTIF(F9:F10,$G$408)*0.5))/(COUNTA(F9:F10)-COUNTIF(F9:F10,$G$410)) -> 0 | J9: 3 | K9: SR2.7 | N9: 7.4.2.1, 7.4.3.7 Табл. 5 - Анализ кода, компонентов на соответствие ИБ
C10: T-ADI-DEP-2-2 | D10: Контролируется и регулируется использование новых (моложе 60 дней) и старых (неактуальных, заброшенных, старше 365 дней) OSS. Например, настроен OSS firewall на предупреждение (или запрет) использования OSS, выпущенных\актуализированных более 365 дней назад и менее чем 60 дней | E10: Отдельная команда | F10: Не заполнено | J10: 3 | M10: OM-B-1 OM-B-2 SB-B-2 | N10: 7.4.3.6 Табл. 4 - Проверка соответствия требованиям ИБ стороннего программного обеспечения
C11: T-ADI-DEP-3-1 | D11: Выполняется инвентаризация используемых зависимостей. Например, создан внутренний репозиторий. | E11: Отдельная команда | F11: Не заполнено | G11: 3 | H11: =(COUNTIF(F11:F13,$G$409)+(COUNTIF(F11:F13,$G$408)*0.5))/(COUNTA(F11:F13)-COUNTIF(F11:F13,$G$410)) -> 0 | J11: 4 | K11: SR1.5 | M11: SB-B-1 | N11: 7.4.3.7 Табл. 5 - Анализ кода, компонентов на соответствие ИБ | O11: 5.16.2.2 | P11: SCA5
C12: T-ADI-DEP-3-2 | D12: При выполнении запросов на слияние (PR/MR) предоставляется список всех уязвимостей используемых зависимостей. Это может быть реализовано с помощью SCA решения | E12: Отдельная команда | F12: Не заполнено | J12: 4 | N12: 7.4.3.7 Табл. 5 - Анализ коммерческих и открытых программных модулей на наличие уязвимостей
C13: T-ADI-DEP-3-3 | D13: Выполняется автоматическое обновление используемых зависимостей. Это может быть реализовано с помощью специальных утилит для обновления зависимостей. | E13: Отдельная команда | F13: Не заполнено | J13: 4 | L13: 10
C14: T-ADI-DEP-4-1 | D14: Выполняется верификация цифровой подписи SBOM перед использованием зависимостей в сборке. Это может быть реализовано с помощью SCA решения | E14: Отдельная команда | F14: Не заполнено | G14: 4 | H14: =(COUNTIF(F14:F15,$G$409)+(COUNTIF(F14:F15,$G$408)*0.5))/(COUNTA(F14:F15)-COUNTIF(F14:F15,$G$410)) -> 0 | J14: 6 | P14: SCS1 IA3
C15: T-ADI-DEP-4-2 | D15: Выполняется самостоятельная сборка необходимых зависимостей в доверенной среде | E15: Отдельная команда | F15: Не заполнено | J15: 6
B16: ='Результаты аудита'!D4 -> Управление артефактами | C16: T-ADI-ART-0-1 | D16: Управление артефактами разработки присутствует в каком-либо виде | E16: Отдельная команда | F16: Не заполнено | G16: 0 | H16: =(COUNTIF(F16:F16,$F$407))/COUNTA(F16:F16) -> 0 | I16: =SUM(H17:H29)/4 -> 0 | J16: 0 | M16: SA-B-2
C17: T-ADI-ART-1-1 | D17: Все артефакты разработки хранятся в доверенных registry. Например, используется внутренний реестр. | E17: Отдельная команда | F17: Не заполнено | G17: 1 | H17: =(COUNTIF(F17:F21,$G$409)+(COUNTIF(F17:F21,$G$408)*0.5))/(COUNTA(F17:F21)-COUNTIF(F17:F21,$G$410)) -> 0 | J17: 1 | N17: 7.4.3.3 | O17: 5.13.2.5 | P17: OSS2
C18: T-ADI-ART-1-2 | D18: Строго ограниченный перечень лиц может помещать артефакты в registry. Внутри registry настроены правила разграничения доступа. | E18: Отдельная команда | F18: Не заполнено | J18: 1 | L18: 60 58 57 | O18: 5.13.2.2 | P18: AC2
C19: T-ADI-ART-1-3 | D19: Для аутентификации в registry используются внешние сервисы. Например, выполнена интеграция с LDAP или другим IdM, локальные учетные записи не используются. | E19: Отдельная команда | F19: Не заполнено | J19: 1 | L19: 60 59
C20: T-ADI-ART-1-4 | D20: Отключен анонимный доступ в registry | E20: Отдельная команда | F20: Не заполнено | J20: 1 | P20: AC2 CNFG1
C21: T-ADI-ART-1-5 | D21: Настроен и включен аудит любых изменений конфигурации хранилищ артефактов | E21: Отдельная команда | F21: Не заполнено | J21: 1 | L21: 108 106 101 | P21: CNFG1
C22: T-ADI-ART-2-1 | D22: Разработчики получают артефакты для дальнейшей работы только из внутренних репозиториев | E22: Отдельная команда | F22: Не заполнено | G22: 2 | H22: =(COUNTIF(F22:F23,$G$409)+(COUNTIF(F22:F23,$G$408)*0.5))/(COUNTA(F22:F23)-COUNTIF(F22:F23,$G$410)) -> 0 | J22: 3 | N22: 7.4.3.7 Табл. 5 - Анализ кода, компонентов на соответствие ИБ
C23: T-ADI-ART-2-2 | D23: Для взаимодействия с registry используются webhook с использованием TLS версии не ниже 1.2 | E23: Отдельная команда | F23: Не заполнено | J23: 3
C24: T-ADI-ART-3-1 | D24: Для всех артефактов создается SBOM | E24: Отдельная команда | F24: Не заполнено | G24: 3 | H24: =(COUNTIF(F24:F25,$G$409)+(COUNTIF(F24:F25,$G$408)*0.5))/(COUNTA(F24:F25)-COUNTIF(F24:F25,$G$410)) -> 0 | J24: 4 | K24: SR1.5 SE3.6 | L24: 4 | O24: 5.16.2.2
C25: T-ADI-ART-3-2 | D25: Используется многофакторная аутентификация для доступа к registry | E25: Отдельная команда | F25: Не заполнено | J25: 4 | L25: 60 59
C26: T-ADI-ART-4-1 | D26: Конвейер сборки (build pipeline) подписывает все артефакты, которые он создает | E26: Отдельная команда | F26: Не заполнено | G26: 4 | H26: =(COUNTIF(F26:F29,$G$409)+(COUNTIF(F26:F29,$G$408)*0.5))/(COUNTA(F26:F29)) -> 0 | J26: 5 | K26: SE2.4 | P26: IA3
C27: T-ADI-ART-4-2 | D27: Выполняется шифрование всех артефактов в registry | E27: Отдельная команда | F27: Не заполнено | G27: 4 | J27: 5
C28: T-ADI-ART-4-3 | D28: Выполняется создание цифровых подписей артефактов после проверок безопасности и перед их отправкой в доверенный registry | E28: Отдельная команда | F28: Не заполнено | G28: 4 | J28: 5 | K28: SE2.4 | P28: SCS1 IA3
C29: T-ADI-ART-4-4 | D29: Выполняется создание хэш сумм артефактов перед отправкой их в registry, а также их проверка при сборке | E29: Отдельная команда | F29: Не заполнено | G29: 4 | J29: 5 | N29: 7.4.3.7 Табл. 5 - Обеспечение контроля целостности всего программного кода и размещение доступных механизмов для контроля в соответствующих средах | P29: SCS1 IA3
B31: Домен "Защита окружения разработки"
B32: ='Результаты аудита'!D5 -> Защита рабочих мест разработчика | C32: T-DEV-COMP-0-1 | D32: Применяются практики защиты рабочих мест разработчиков | E32: Отдельная команда | F32: Не заполнено | G32: 0 | H32: =(COUNTIF(F32:F32,$F$407))/COUNTA(F32:F32) -> 0 | I32: =SUM(H33:H35)/2 -> 0 | J32: 0 | N32: 7.4.3.2 | P32: CNFG1 MI1
C33: T-DEV-COMP-1-1 | D33: Утверждены и применяются базовые требования к ПО и настройкам на корпоративных рабочих местах разработчиков. Например, требования к антивирусу, обновлениям ОС, требования к паролям. | E33: Отдельная команда | F33: Не заполнено | G33: 1 | H33: =(COUNTIF(F33:F34,$G$409)+(COUNTIF(F33:F34,$G$408)*0.5))/(COUNTA(F33:F34)-COUNTIF(F33:F34,$G$410)) -> 0 | J33: 1 | N33: 7.4.3.2
C34: T-DEV-COMP-1-2 | D34: Удаленный доступ с некорпоративных (и, соответственно, ненастроенных) устройств к инструментам разработки возможен только для ограниченного (небольшого) числа устройств. | E34: Отдельная команда | F34: Не заполнено | J34: 1 | N34: 7.4.3.2 | P34: AC2 MI1
C35: T-DEV-COMP-2-1 | D35: Удаленный доступ к инструментам разработки возможен либо с корпоративных устройств с использованием MDM, либо через промежуточные\проксирующие системы, например, VDI или PAM. | E35: Отдельная команда | F35: Не заполнено | G35: 2 | H35: =(COUNTIF(F35,$G$409)+(COUNTIF(F35,$G$408)*0.5))/COUNTA(F35) -> 0 | J35: 3 | N35: 7.4.3.2 | P35: MI1
B36: ='Результаты аудита'!D6 -> Защита секретов | C36: T-DEV-SM-0-1 | D36: Существует практика управления секретами | E36: Отдельная команда | F36: Не заполнено | G36: 0 | H36: =(COUNTIF(F36:F36,$F$407))/COUNTA(F36:F36) -> 0 | I36: =SUM(H37:H43)/4 -> 0 | J36: 0 | L36: 7 | M36: SD-B-1 | O36: 5.15.2.2
C37: T-DEV-SM-1-1 | D37: Секреты в среде разработки защищаются встроенными механизмами инструментов разработки, например, CI/CD системы, без применения Secret Management систем. | E37: Отдельная команда | F37: Не заполнено | G37: 1 | H37: =(COUNTIF(F37:F38,$G$409)+(COUNTIF(F37:F38,$G$408)*0.5))/(COUNTA(F37:F38)-COUNTIF(F37:F38,$G$410)) -> 0 | J37: 1 | L37: 7 | M37: SD-B-1
C38: T-DEV-SM-1-2 | D38: Инциденты ИБ, связанные с использованием секретов в среде разработки, обрабатываются службой ИБ совместно с разработчиками. | E38: Отдельная команда | F38: Не заполнено | J38: 1 | K38: CMVM1.1 | M38: IM-A-2 | P38: MI4
C39: T-DEV-SM-2-1 | D39: Секреты окружения разработки хранятся в Secret Management инструменте, например, Hashicorp Vault. | E39: Отдельная команда | F39: Не заполнено | G39: 2 | H39: =(COUNTIF(F39:F40,$G$409)+(COUNTIF(F39:F40,$G$408)*0.5))/(COUNTA(F39:F40)-COUNTIF(F39:F40,$G$410)) -> 0 | J39: 2 | L39: 7 | M39: SD-B-2 | O39: 5.15.2.4 | P39: IA2
C40: T-DEV-SM-2-2 | D40: Разработчики и инженеры обмениваются секретами с помощью инструмента Secret Management, например, Hashicorp Vault | E40: Отдельная команда | F40: Не заполнено | J40: 2 | M40: SD-B-2 | O40: 5.15.2.4
C41: T-DEV-SM-3-1 | D41: Секреты всех сред и инструментов (за исключением рабочих станций разработчиков и подобных adhoc сред) хранятся в SM (например, Vault), количество hardcoded секретов минимально. Случаи использования hardcoded секретов известны команде ИБ и запланирован отказ от их использования | E41: Отдельная команда | F41: Не заполнено | G41: 3 | H41: =(COUNTIF(F41:F42,$G$409)+(COUNTIF(F41:F42,$G$408)*0.5))/(COUNTA(F41:F42)-COUNTIF(F41:F42,$G$410)) -> 0 | J41: 3 | L41: 7 | M41: SD-B-1
C42: T-DEV-SM-3-2 | D42: Сформирована и применяется политика ротации секретов окружений разработки | E42: Отдельная команда | F42: Не заполнено | J42: 3 | M42: SD-B-3 | O42: 5.15.2.1
C43: T-DEV-SM-4-1 | D43: Используются динамические секреты с ограничением доступа для сред | E43: Отдельная команда | F43: Не заполнено | G43: 4 | H43: =(COUNTIF(F43,$G$409)+(COUNTIF(F43,$G$408)*0.5))/COUNTA(F43) -> 0 | J43: 6
B44: ='Результаты аудита'!D7 -> Защита Build-среды | C44: T-DEV-BLD-0-1 | D44: Применяются практики защиты инфраструктуры сборки ПО | E44: Отдельная команда | F44: Не заполнено | G44: 0 | H44: =(COUNTIF(F44:F44,$F$407))/COUNTA(F44:F44) -> 0 | I44: =SUM(H45:H53)/4 -> 0 | J44: 0 | L44: 83 56 | M44: SB-A-1 | N44: 7.4.3.2 | O44: 5.13.2 | P44: CNFG1 SCS2
C45: T-DEV-BLD-1-1 | D45: Доступ к среде сборки (build) (оркестратор, worker-узлы и т.д.) ограничен (настроен RBAC) | E45: Отдельная команда | F45: Не заполнено | G45: 1 | H45: =(COUNTIF(F45:F48,$G$409)+(COUNTIF(F45:F48,$G$408)*0.5))/(COUNTA(F45:F48)-COUNTIF(F45:F48,$G$410)) -> 0 | J45: 2 | L45: 57 58 | N45: 7.4.3.2 | O45: 5.13.2.7 | P45: AC2 MI1
C46: T-DEV-BLD-1-2 | D46: Для всех узлов сборки (build worker) используется подход push (вместо pull) для передачи параметров | E46: Отдельная команда | F46: Не заполнено | J46: 2
C47: T-DEV-BLD-1-3 | D47: Каждый узел сборки (build worker) имеет минимально необходимые сетевые доступы (для связи только с нужными сервисами и только по определенным портам\протоколам) | E47: Отдельная команда | F47: Не заполнено | J47: 2 | M47: SB-A-2 | N47: 7.4.3.2 | O47: 5.13.2.8 | P47: AC1 MI1
C48: T-DEV-BLD-1-4 | D48: Выполняется централизованное хранение журналов (логов) сборки, включающее изменение настроек | E48: Отдельная команда | F48: Не заполнено | J48: 2 | M48: SB-A-3 | O48: 5.13.2.4 | P48: SCS2
C49: T-DEV-BLD-2-1 | D49: Осуществляется мониторинг и реагирование на инциденты для узлов сборки в части потребления вычислительных ресурсов (CPU, RAM, HDD и пр). | E49: Отдельная команда | F49: Не заполнено | G49: 2 | H49: =(COUNTIF(F49,$G$409)+(COUNTIF(F49,$G$408)*0.5))/COUNTA(F49) -> 0 | J49: 3 | K49: CMVM1.1
C50: T-DEV-BLD-3-1 | D50: Каждый узел сборки (build worker) имеет отдельную роль (например, тестирование, компиляция, отправка артефактов), прочие задачи на нем не выполняются | E50: Отдельная команда | F50: Не заполнено | G50: 3 | H50: =(COUNTIF(F50:F52,$G$409)+(COUNTIF(F50:F52,$G$408)*0.5))/(COUNTA(F50:F52)-COUNTIF(F50:F52,$G$410)) -> 0 | J50: 5 | L50: 3 | P50: TP3
C51: T-DEV-BLD-3-2 | D51: Реализована настройка механизмов безопасности для узлов сборки | E51: Отдельная команда | F51: Не заполнено | J51: 5 | L51: 83 56 | M51: SB-A-1 SB-A-2 | N51: 7.4.3.2 | P51: CNFG1
C52: T-DEV-BLD-3-3 | D52: Все настройки узлов сборки (build worker) централизованно хранятся в системе хранения исходного кода | E52: Отдельная команда | F52: Не заполнено | J52: 5
C53: T-DEV-BLD-4-1 | D53: Создание среды сборки (build environment) выполняется автоматизировано (IaC) | E53: Отдельная команда | F53: Не заполнено | G53: 4 | H53: =(COUNTIF(F53,$G$409)+(COUNTIF(F53,$G$408)*0.5))/COUNTA(F53) -> 0 | J53: 6 | L53: 3 | P53: SCS2
B54: ='Результаты аудита'!D8 -> Защита source code management (SCM) | C54: T-DEV-SCM-0-1 | D54: Применяются практики защиты репозитория кода | E54: Отдельная команда | F54: Не заполнено | G54: 0 | H54: =(COUNTIF(F54:F54,$F$407))/COUNTA(F54:F54) -> 0 | I54: =SUM(H55:H74)/4 -> 0 | J54: 0 | L54: 57 | N54: 7.4.3.2, 7.4.3.3
C55: T-DEV-SCM-1-1 | D55: Создавать и удалять репозитории могут только определенные пользователи (например, настроен RBAC) | E55: Отдельная команда | F55: Не заполнено | G55: 1 | H55: =(COUNTIF(F55:F61,$G$409)+(COUNTIF(F55:F61,$G$408)*0.5))/(COUNTA(F55:F61)-COUNTIF(F55:F61,$G$410)) -> 0 | J55: 2 | L55: 57 | N55: 7.4.3.3 | O55: 5.14.2.2 | P55: AC2
C56: T-DEV-SCM-1-2 | D56: Удалять issues могут только определенные пользователи (например, настроен RBAC) | E56: Отдельная команда | F56: Не заполнено | J56: 2 | N56: 7.4.3.3 | P56: AC2
C57: T-DEV-SCM-1-3 | D57: Создавать teams/groups могут только определенные пользователи (например, настроен RBAC) | E57: Отдельная команда | F57: Не заполнено | J57: 2 | N57: 7.4.3.3 | O57: 5.14.2.2 | P57: AC2
C58: T-DEV-SCM-1-4 | D58: Количество администраторов SCM ограничено и регулярно проверяется | E58: Отдельная команда | F58: Не заполнено | J58: 2 | N58: 7.4.3.3
C59: T-DEV-SCM-1-5 | D59: Управление доступом к системе контроля версий осуществляется с использованием ролевой модели, созданной на основе принципа минимальных привилегий. Модель регулирует как минимум: - Возможности по созданию репозиториев - Возможности по удалению репозиториев - Возможности по изменению видимости репозиториев | E59: Отдельная команда | F59: Не заполнено | J59: 2 | N59: 7.4.3.3 | O59: 5.14.2.2
C60: T-DEV-SCM-1-6 | D60: Непривилегированным пользователям доступно создание только приватных репозиториев | E60: Отдельная команда | F60: Не заполнено | J60: 2 | N60: 7.4.3.3 | O60: 5.14.2.2 | P60: AC2
C61: T-DEV-SCM-1-7 | D61: При установке любых приложений и дополнений в Source code management системах (SCM) запрашивается одобрение (approval) администратора | E61: Отдельная команда | F61: Не заполнено | J61: 2 | N61: 7.4.3.3
C62: T-DEV-SCM-2-1 | D62: У всех копий (forks) кода включен аудит, а также назначен ответственный | E62: Отдельная команда | F62: Не заполнено | G62: 2 | H62: =(COUNTIF(F62:F67,$G$409)+(COUNTIF(F62:F67,$G$408)*0.5))/(COUNTA(F62:F67)-COUNTIF(F62:F67,$G$410)) -> 0 | J62: 3 | N62: 7.4.3.3
C63: T-DEV-SCM-2-2 | D63: Регулярно осуществляется анализ и удаление неактивных пользователей из проекта | E63: Отдельная команда | F63: Не заполнено | J63: 3 | N63: 7.4.3.3
C64: T-DEV-SCM-2-3 | D64: Почтовые уведомления могут направляться только на доверенные (проверенные) домены | E64: Отдельная команда | F64: Не заполнено | J64: 3 | N64: 7.4.3.3
C65: T-DEV-SCM-2-4 | D65: Неактивные (ненужные) приложения (applications, плагины или дополнения) удаляются из SCM системы | E65: Отдельная команда | F65: Не заполнено | J65: 3 | M65: OM-B-1
C66: T-DEV-SCM-2-5 | D66: Для каждого репозитория по умолчанию установлены минимальные привилегии пользователей | E66: Отдельная команда | F66: Не заполнено | J66: 3 | M66: SA-A-1 | N66: 7.4.3.3
C67: T-DEV-SCM-2-6 | D67: Для добавления нового пользователя в SCM используются только корпоративные email | E67: Отдельная команда | F67: Не заполнено | J67: 3 | N67: 7.4.3.3
C68: T-DEV-SCM-3-1 | D68: Все изменения видимости проекта отслеживаются | E68: Отдельная команда | F68: Не заполнено | G68: 3 | H68: =(COUNTIF(F68:F71,$G$409)+(COUNTIF(F68:F71,$G$408)*0.5))/(COUNTA(F68:F71)-COUNTIF(F68:F71,$G$410)) -> 0 | J68: 4 | N68: 7.4.3.3
C69: T-DEV-SCM-3-2 | D69: Осуществляется идентификация неиспользуемых репозиториев и их архивирование | E69: Отдельная команда | F69: Не заполнено | J69: 4
C70: T-DEV-SCM-3-3 | D70: Доступ к SCM осуществляется с использованием многофакторной аутентификации | E70: Отдельная команда | F70: Не заполнено | J70: 4 | L70: 59 60 | N70: 7.4.3.3
C71: T-DEV-SCM-3-4 | D71: Доступ к SCM осуществляется только с разрешенных IP-адресов | E71: Отдельная команда | F71: Не заполнено | J71: 4 | N71: 7.4.3.3 | P71: AC1
C72: T-DEV-SCM-4-1 | D72: Проводится анализ кода на наличие аномалий, релевантных организации (например, commit содержит слишком значительные изменения объемов кода или в commit'ов слишком много в определенный промежуток времени) | E72: Отдельная команда | F72: Не заполнено | G72: 4 | H72: =(COUNTIF(F72:F74,$G$409)+(COUNTIF(F72:F74,$G$408)*0.5))/(COUNTA(F72:F74)-COUNTIF(F72:F74,$G$410)) -> 0 | J72: 6 | N72: 7.4.3.3 | P72: MI4
C73: T-DEV-SCM-4-2 | D73: Доступ разработчиков к репозиторию осуществляется с использованием сертификатов, созданных только с использованием внутреннего CA (центр сертификации) компании (а не самоподписанные сертификаты) в качестве дополнительного фактора аутентификации | E73: Отдельная команда | F73: Не заполнено | J73: 6 | N73: 7.4.3.3
C74: T-DEV-SCM-4-3 | D74: Автоматизированный харденинг настроек проектов в SCM через API или dev. platform eng. с сравнением состояния | E74: Отдельная команда | F74: Не заполнено | J74: 6
B75: ='Результаты аудита'!D9 -> Контроль внесения изменений в исходный код | C75: T-DEV-SRC-0-1 | D75: Применяются практики контроля внесения изменений в исходный код | E75: Отдельная команда | F75: Не заполнено | G75: 0 | H75: =(COUNTIF(F75:F75,$F$407))/COUNTA(F75:F75) -> 0 | I75: =SUM(H76:H93)/4 -> 0 | J75: 0 | L75: 79 | M75: RT-A-3 | N75: 7.4.2.1, 7.4.3.7 | O75: 5.5.2.3
C76: T-DEV-SRC-1-1 | D76: Все изменения в исходном коде отслеживаются с использованием системы контроля версий (SCM) | E76: Отдельная команда | F76: Не заполнено | G76: 1 | H76: =(COUNTIF(F76:F80,$G$409)+(COUNTIF(F76:F80,$G$408)*0.5))/(COUNTA(F76:F80)-COUNTIF(F76:F80,$G$410)) -> 0 | J76: 1 | N76: 7.4.2.1, 7.4.3.7 | O76: 5.5.2.3, 5.5.2.5 | P76: GF1
C77: T-DEV-SRC-1-2 | D77: Круг согласования запроса на слияние исходного кода начинается заново при внесении новых предложений по изменению | E77: Отдельная команда | F77: Не заполнено | J77: 1 | N77: 7.4.2.1, 7.4.3.7 | P77: GF1
C78: T-DEV-SRC-1-3 | D78: Разработчики не обладают правами "dismiss code change review", позволяющими обходить стандартную процедуру проверки кода | E78: Отдельная команда | F78: Не заполнено | J78: 1 | N78: 7.4.2.1, 7.4.3.7 | P78: AC2
C79: T-DEV-SRC-1-4 | D79: Для всех репозиториев включена опция linear history. В качестве вариантов merge доступны только squash и rebase merge | E79: Отдельная команда | F79: Не заполнено | J79: 1
C80: T-DEV-SRC-1-5 | D80: Используется защита веток (branch protection) | E80: Отдельная команда | F80: Не заполнено | J80: 1
C81: T-DEV-SRC-2-1 | D81: Осуществляется регулярный анализ и удаление неиспользуемых веток (branches) | E81: Отдельная команда | F81: Не заполнено | G81: 2 | H81: =(COUNTIF(F81:F86,$G$409)+(COUNTIF(F81:F86,$G$408)*0.5))/(COUNTA(F81:F86)-COUNTIF(F81:F86,$G$410)) -> 0 | J81: 3
C82: T-DEV-SRC-2-2 | D82: Запрос на слияние (PR/MR) реализуется только при успешном прохождении всех проверок | E82: Отдельная команда | F82: Не заполнено | J82: 3 | K82: ST3.6 | L82: 68
C83: T-DEV-SRC-2-3 | D83: Все открытые ветки (branches) обновляются перед отправкой запросов на слияние | E83: Отдельная команда | F83: Не заполнено | J83: 3
C84: T-DEV-SRC-2-4 | D84: Слияние изменений в исходном коде разрешены только в случае отсутствия открытых комментариев и обсуждений | E84: Отдельная команда | F84: Не заполнено | J84: 3
C85: T-DEV-SRC-2-5 | D85: Для каждого изменения исходного кода есть соответствующий тикет в системе управления заданиями (task management system, например, jira) | E85: Отдельная команда | F85: Не заполнено | J85: 3
C86: T-DEV-SRC-2-6 | D86: Правила защиты, применяемые к веткам (branch protection rules), применяются в том числе к УЗ администраторов | E86: Отдельная команда | F86: Не заполнено | J86: 3 | L86: 65
C87: T-DEV-SRC-3-1 | D87: Для наиболее важных файлов определены и назначены Code Owners | E87: Отдельная команда | F87: Не заполнено | G87: 3 | H87: =(COUNTIF(F87:F92,$G$409)+(COUNTIF(F87:F92,$G$408)*0.5))/(COUNTA(F87:F92)-COUNTIF(F87:F92,$G$410)) -> 0 | J87: 4
C88: T-DEV-SRC-3-2 | D88: Code Owners согласовывают изменения файлов, которые им "принадлежат" | E88: Отдельная команда | F88: Не заполнено | J88: 4 | N88: 7.4.2.1, 7.4.3.7
C89: T-DEV-SRC-3-3 | D89: Только подписанные commits (signed commit) допускаются к запросам на слияние (MR/PR) (особенно в main-ветку) | E89: Отдельная команда | F89: Не заполнено | J89: 4 | K89: SE2.4 | N89: 7.4.3.7 Табл. 5 - Обеспечение контроля целостности всего программного кода и размещение доступных механизмов для контроля в соответствующих средах | O89: 5.14.2.3
C90: T-DEV-SRC-3-4 | D90: Каждое изменение в исходном коде (запрос на слияние (MR/PR)) согласовывается как минимум двумя аутентифицированными пользователями | E90: Отдельная команда | F90: Не заполнено | J90: 4 | N90: 7.4.2.1, 7.4.3.7
C91: T-DEV-SRC-3-5 | D91: Осуществляется контроль за удалением защищенных веток (protected branch) | E91: Отдельная команда | F91: Не заполнено | J91: 4
C92: T-DEV-SRC-3-6 | D92: Осуществляется контроль за тем, как сканеры безопасности (SAST,SCA,Secrets) игнорируют "skip/ignore scan" inline комментарии и ignore файлы (.aiignore, .gitleaksignore и т.д.) | E92: Отдельная команда | F92: Не заполнено | J92: 4 | L92: 68
C93: T-DEV-SRC-4-1 | D93: Для всех репозиториев функция "force push" доступна только для владельца | E93: Отдельная команда | F93: Не заполнено | G93: 4 | H93: =(COUNTIF(F93,$G$409)+(COUNTIF(F93,$G$408)*0.5))/COUNTA(F93) -> 0 | J93: 6 | L93: 63
B94: ='Результаты аудита'!D10 -> Защита конвейера сборки | C94: T-DEV-CICD-0-1 | D94: Применяются практики защиты конвейера сборки ПО | E94: Отдельная команда | F94: Не заполнено | G94: 0 | H94: =(COUNTIF(F94:F94,$F$407))/COUNTA(F94:F94) -> 0 | I94: =SUM(H95:H103)/4 -> 0 | J94: 0 | L94: 83 56 | M94: SB-A-1 | N94: 7.4.3.3 | P94: AC2 MI1
C95: T-DEV-CICD-1-1 | D95: Доступ к конвейеру сборки ограничен (настроен RBAC) | E95: Отдельная команда | F95: Не заполнено | G95: 1 | H95: =(COUNTIF(F95:F99,$G$409)+(COUNTIF(F95:F99,$G$408)*0.5))/(COUNTA(F95:F99)-COUNTIF(F95:F99,$G$410)) -> 0 | J95: 1 | N95: 7.4.3.3 | O95: 5.13.2.7 | P95: SCS2
C96: T-DEV-CICD-1-2 | D96: Выполняется централизованное хранение журналов событий конвейеров сборки | E96: Отдельная команда | F96: Не заполнено | J96: 1 | O96: 5.13.2.4
C97: T-DEV-CICD-1-3 | D97: Используется подход "CICD as a code" при создании конвейера разработки | E97: Отдельная команда | F97: Не заполнено | J97: 1 | K97: SM3.4
C98: T-DEV-CICD-1-4 | D98: Используется защита тегов (protected tags) | E98: Отдельная команда | F98: Не заполнено | J98: 1
C99: T-DEV-CICD-1-5 | D99: Запрет использования обхода запуска пайплайна на коммит [skip ci] pre-commit хуками | E99: Отдельная команда | F99: Не заполнено | J99: 1
C100: T-DEV-CICD-2-1 | D100: Для каждого этапа сборки строго определены входные и выходные параметры и результаты | E100: Отдельная команда | F100: Не заполнено | G100: 2 | H100: =(COUNTIF(F100:F101,$G$409)+(COUNTIF(F100:F101,$G$408)*0.5))/(COUNTA(F100:F101)-COUNTIF(F100:F101,$G$410)) -> 0 | J100: 3 | O100: 5.13.2.2
C101: T-DEV-CICD-2-2 | D101: Изменение конфигурационных файлов CI\CD (конвейеров сборки) непрерывно отслеживается | E101: Отдельная команда | F101: Не заполнено | J101: 3 | N101: 7.4.3.3
...

Sheet Кирилламида
A1: Уровни зрелости. Расположение групп практик
B2: 0. Хаос | C2: 1. Минимальный | D2: 2. Базовый | E2: 3. Повышенный | F2: 4. Продвинутый | G2: 5. Развитый | H2: 6. Экспертный | I2: 7. Космический
A3: ='Результаты аудита'!E3 -> T-ADI-DEP | B3: T-ADI-DEP-0 | D3: T-ADI-DEP-1 | E3: T-ADI-DEP-2 | F3: T-ADI-DEP-3 | H3: T-ADI-DEP-4
A4: ='Результаты аудита'!E4 -> T-ADI-ART | B4: T-ADI-ART-0 | C4: T-ADI-ART-1 | E4: T-ADI-ART-2 | F4: T-ADI-ART-3 | G4: T-ADI-ART-4
A5: ='Результаты аудита'!E5 -> T-DEV-COMP | B5: T-DEV-COMP-0 | C5: T-DEV-COMP-1 | E5: T-DEV-COMP-2
A6: ='Результаты аудита'!E6 -> T-DEV-SM | B6: T-DEV-SM-0 | C6: T-DEV-SM-1 | D6: T-DEV-SM-2 | E6: T-DEV-SM-3 | H6: T-DEV-SM-4
A7: ='Результаты аудита'!E7 -> T-DEV-BLD | B7: T-DEV-BLD-0 | D7: T-DEV-BLD-1 | E7: T-DEV-BLD-2 | G7: T-DEV-BLD-3 | H7: T-DEV-BLD-4
A8: ='Результаты аудита'!E8 -> T-DEV-SCM | B8: T-DEV-SCM-0 | D8: T-DEV-SCM-1 | E8: T-DEV-SCM-2 | F8: T-DEV-SCM-3 | H8: T-DEV-SCM-4
A9: ='Результаты аудита'!E9 -> T-DEV-SRC | B9: T-DEV-SRC-0 | C9: T-DEV-SRC-1 | E9: T-DEV-SRC-2 | F9: T-DEV-SRC-3 | H9: T-DEV-SRC-4
A10: ='Результаты аудита'!E10 -> T-DEV-CICD | B10: T-DEV-CICD-0 | C10: T-DEV-CICD-1 | E10: T-DEV-CICD-2 | F10: T-DEV-CICD-3 | G10: T-DEV-CICD-4
A11: ='Результаты аудита'!E11 -> T-CODE-SPC | B11: T-CODE-SPC-0 | D11: T-CODE-SPC-1 | F11: T-CODE-SPC-2 | G11: T-CODE-SPC-3 | I11: T-CODE-SPC-4
A12: ='Результаты аудита'!E12 -> T-CODE-SST | B12: T-CODE-SST-0 | D12: T-CODE-SST-1 | E12: T-CODE-SST-2 | F12: T-CODE-SST-3 | I12: T-CODE-SST-4
A13: ='Результаты аудита'!E13 -> T-CODE-SC | B13: T-CODE-SC-0 | C13: T-CODE-SC-1 | D13: T-CODE-SC-2 | F13: T-CODE-SC-3 | H13: T-CODE-SC-4
A14: ='Результаты аудита'!E14 -> T-CODE-IMG | B14: T-CODE-IMG-0 | C14: T-CODE-IMG-1 | D14: T-CODE-IMG-2 | E14: T-CODE-IMG-3 | F14: T-CODE-IMG-4
A15: ='Результаты аудита'!E15 -> T-CODE-SECDN | B15: T-CODE-SECDN-0 | C15: T-CODE-SECDN-1 | D15: T-CODE-SECDN-2 | E15: T-CODE-SECDN-3 | G15: T-CODE-SECDN-4
A16: ='Результаты аудита'!E16 -> T-CODE-DOCKERFS | B16: T-CODE-DOCKERFS-0 | C16: T-CODE-DOCKERFS-1 | D16: T-CODE-DOCKERFS-2
A17: ='Результаты аудита'!E17 -> T-PREPROD-DAST | B17: T-PREPROD-DAST-0 | E17: T-PREPROD-DAST-1 | F17: T-PREPROD-DAST-2 | G17: T-PREPROD-DAST-3 | H17: T-PREPROD-DAST-4
A18: ='Результаты аудита'!E18 -> T-PREPROD-PENTEST | B18: T-PREPROD-PENTEST-0 | C18: T-PREPROD-PENTEST-1 | D18: T-PREPROD-PENTEST-2 | H18: T-PREPROD-PENTEST-4
A19: ='Результаты аудита'!E21 -> T-PREPROD-VULN | B19: T-PREPROD-VULN-0 | D19: T-PREPROD-VULN-1 | F19: T-PREPROD-VULN-2 | G19: T-PREPROD-VULN-3 | I19: T-PREPROD-VULN-4
A20: ='Результаты аудита'!E19 -> T-PREPROD-SECTEST | B20: T-PREPROD-SECTEST-0 | C20: T-PREPROD-SECTEST-1 | D20: T-PREPROD-SECTEST-2 | H20: T-PREPROD-SECTEST-3
A21: ='Результаты аудита'!E20 -> T-PREPROD-MANSEC | B21: T-PREPROD-MANSEC-0 | D21: T-PREPROD-MANSEC-1 | E21: T-PREPROD-MANSEC-2
A22: ='Результаты аудита'!E22 -> T-PROD-SM | B22: T-PROD-SM-0 | C22: T-PROD-SM-1 | D22: T-PROD-SM-2 | E22: T-PROD-SM-3 | G22: T-PROD-SM-4
A23: ='Результаты аудита'!E23 -> T-PROD-DAST | B23: T-PROD-DAST-0 | F23: T-PROD-DAST-1 | G23: T-PROD-DAST-2 | H23: T-PROD-DAST-3 | I23: T-PROD-DAST-4
A24: ='Результаты аудита'!E24 -> T-PROD-PENTEST | B24: T-PROD-PENTEST-0 | D24: T-PROD-PENTEST-1 | E24: T-PROD-PENTEST-2 | F24: T-PROD-PENTEST-3 | I24: T-PROD-PENTEST-4
A25: ='Результаты аудита'!E25 -> T-PROD-ACCESS | B25: T-PROD-ACCESS-0 | C25: T-PROD-ACCESS-1 | E25: T-PROD-ACCESS-2 | F25: T-PROD-ACCESS-3 | I25: T-PROD-ACCESS-4
A26: ='Результаты аудита'!E26 -> T-PROD-NETWORK | B26: T-PROD-NETWORK-0 | C26: T-PROD-NETWORK-1 | D26: T-PROD-NETWORK-2 | E26: T-PROD-NETWORK-3
A27: ='Результаты аудита'!E27 -> T-PROD-RUN | B27: T-PROD-RUN-0 | D27: T-PROD-RUN-1 | E27: T-PROD-RUN-2 | G27: T-PROD-RUN-3
A28: ='Результаты аудита'!E28 -> T-PROD-VULN | B28: T-PROD-VULN-0 | C28: T-PROD-VULN-1 | D28: T-PROD-VULN-2 | E28: T-PROD-VULN-3 | G28: T-PROD-VULN-4
A29: ='Результаты аудита'!E29 -> T-PROD-EVENTS | B29: T-PROD-EVENTS-0 | D29: T-PROD-EVENTS-2 | E29: T-PROD-EVENTS-3
A30: ='Результаты аудита'!E30 -> P-EDU-AWR | B30: P-EDU-AWR-0 | C30: P-EDU-AWR-1 | E30: P-EDU-AWR-2 | G30: P-EDU-AWR-3 | H30: P-EDU-AWR-4
A31: ='Результаты аудита'!E31 -> P-EDU-KB | B31: P-EDU-KB-0 | C31: P-EDU-KB-1 | E31: P-EDU-KB-2 | F31: P-EDU-KB-3 | G31: P-EDU-KB-4
A32: ='Результаты аудита'!E32 -> P-REQ-TM | B32: P-REQ-TM-0 | D32: P-REQ-TM-1 | E32: P-REQ-TM-2 | F32: P-REQ-TM-3 | G32: P-REQ-TM-4
A33: ='Результаты аудита'!E33 -> P-REQ-RD | B33: P-REQ-RD-0 | C33: P-REQ-RD-1 | D33: P-REQ-RD-2 | F33: P-REQ-RD-3 | H33: P-REQ-RD-4
A34: ='Результаты аудита'!E34 -> P-REQ-CR | B34: P-REQ-CR-0 | C34: P-REQ-CR-1 | D34: P-REQ-CR-2 | G34: P-REQ-CR-3 | H34: P-REQ-CR-4
A35: ='Результаты аудита'!E35 -> P-REQ-STDR-App | B35: P-REQ-STDR-App-0 | E35: P-REQ-STDR-App-1 | F35: P-REQ-STDR-App-2 | G35: P-REQ-STDR-App-3 | H35: P-REQ-STDR-App-4
A36: ='Результаты аудита'!E36 -> P-REQ-STDR-Infr | B36: P-REQ-STDR-Infr-0 | C36: P-REQ-STDR-Infr-1 | D36: P-REQ-STDR-Infr-2 | E36: P-REQ-STDR-Infr-3 | G36: P-REQ-STDR-Infr-4
A37: ='Результаты аудита'!E37 -> P-DEFECT-MNG | B37: P-DEFECT-MNG-0 | C37: P-DEFECT-MNG-1 | D37: P-DEFECT-MNG-2 | E37: P-DEFECT-MNG-3 | I37: P-DEFECT-MNG-4
A38: ='Результаты аудита'!E38 -> P-DEFECT-CNS | B38: P-DEFECT-CNS-0 | E38: P-DEFECT-CNS-1 | F38: P-DEFECT-CNS-2 | G38: P-DEFECT-CNS-3 | H38: P-DEFECT-CNS-4
A39: ='Результаты аудита'!E39 -> P-MET-SET | B39: P-MET-SET-0 | E39: P-MET-SET-2 | F39: P-MET-SET-3
A40: ='Результаты аудита'!E40 -> P-MET-EX | B40: P-MET-EX-0 | E40: P-MET-EX-2 | F40: P-MET-EX-3 | H40: P-MET-EX-4
A41: ='Результаты аудита'!E41 -> P-ROLE-SC | B41: P-ROLE-SC-0 | C41: P-ROLE-SC-1 | E41: P-ROLE-SC-2 | F41: P-ROLE-SC-3 | I41: P-ROLE-SC-4
A42: ='Результаты аудита'!E42 -> P-ROLE-RESP | B42: P-ROLE-RESP-0 | C42: P-ROLE-RESP-1 | E42: P-ROLE-RESP-2 | F42: P-ROLE-RESP-3
A44: Уровни зрелости. Процент выполнения групп практик и соответствие уровням зрелости Кирилламиды
B45: 0. Хаос | C45: 1. Минимальный | D45: 2. Базовый | E45: 3. Повышенный | F45: 4. Продвинутый | G45: 5. Развитый | H45: 6. Экспертный | I45: 7. Космический
A46: ='Результаты аудита'!E3 -> T-ADI-DEP | B46: =Практики!H3 -> 0 | D46: =Практики!H4 -> 0 | E46: =Практики!H9 -> 0 | F46: =Практики!H11 -> 0 | H46: =Практики!H14 -> 0
A47: ='Результаты аудита'!E4 -> T-ADI-ART | B47: =Практики!H16 -> 0 | C47: =Практики!H17 -> 0 | E47: =Практики!H22 -> 0 | F47: =Практики!H24 -> 0 | G47: =Практики!H26 -> 0
A48: ='Результаты аудита'!E5 -> T-DEV-COMP | B48: =Практики!H32 -> 0 | C48: =Практики!H33 -> 0 | E48: =Практики!H35 -> 0
A49: ='Результаты аудита'!E6 -> T-DEV-SM | B49: =Практики!H36 -> 0 | C49: =Практики!H37 -> 0 | D49: =Практики!H39 -> 0 | E49: =Практики!H41 -> 0 | H49: =Практики!H43 -> 0
A50: ='Результаты аудита'!E7 -> T-DEV-BLD | B50: =Практики!H44 -> 0 | D50: =Практики!H45 -> 0 | E50: =Практики!H49 -> 0 | G50: =Практики!H50 -> 0 | H50: =Практики!H53 -> 0
A51: ='Результаты аудита'!E8 -> T-DEV-SCM | B51: =Практики!H54 -> 0 | D51: =Практики!H55 -> 0 | E51: =Практики!H62 -> 0 | F51: =Практики!H68 -> 0 | H51: =Практики!H72 -> 0
A52: ='Результаты аудита'!E9 -> T-DEV-SRC | B52: =Практики!H75 -> 0 | C52: =Практики!H76 -> 0 | E52: =Практики!H81 -> 0 | F52: =Практики!H87 -> 0 | H52: =Практики!H93 -> 0
A53: ='Результаты аудита'!E10 -> T-DEV-CICD | B53: =Практики!H94 -> 0 | C53: =Практики!H95 -> 0 | E53: =Практики!H100 -> 0 | F53: =Практики!H102 -> 0 | G53: =Практики!H103 -> 0
A54: ='Результаты аудита'!E11 -> T-CODE-SPC | B54: =Практики!H106 -> 0 | D54: =Практики!H107 -> 0 | F54: =Практики!H109 -> 0 | G54: =Практики!H113 -> 0 | I54: =Практики!H118 -> 0
A55: ='Результаты аудита'!E12 -> T-CODE-SST | B55: =Практики!H119 -> 0 | D55: =Практики!H120 -> 0 | E55: =Практики!H122 -> 0 | F55: =Практики!H126 -> 0 | I55: =Практики!H129 -> 0
A56: ='Результаты аудита'!E13 -> T-CODE-SC | B56: =Практики!H130 -> 0 | C56: =Практики!H131 -> 0 | D56: =Практики!H134 -> 0 | F56: =Практики!H139 -> 0 | H56: =Практики!H143 -> 0
A57: ='Результаты аудита'!E14 -> T-CODE-IMG | B57: =Практики!H144 -> 0 | C57: =Практики!H145 -> 0 | D57: =Практики!H148 -> 0 | E57: =Практики!H151 -> 0 | F57: {=Практики!H152:H153} -> 0
A58: ='Результаты аудита'!E15 -> T-CODE-SECDN | B58: =Практики!H154 -> 0 | C58: =Практики!H155 -> 0 | D58: =Практики!H159 -> 0 | E58: =Практики!H162 -> 0 | F58: 0 | G58: =Практики!H165 -> 0
A59: ='Результаты аудита'!E16 -> T-CODE-DOCKERFS | B59: =Практики!H166 -> 0 | C59: =Практики!H167 -> 0 | D59: =Практики!H169 -> 0
A60: ='Результаты аудита'!E17 -> T-PREPROD-DAST | B60: =Практики!H172 -> 0 | E60: =Практики!H173 -> 0 | F60: =Практики!H175 -> 0 | G60: =Практики!H179 -> 0 | H60: =Практики!H183 -> 0
A61: ='Результаты аудита'!E18 -> T-PREPROD-PENTEST | B61: =Практики!H186 -> 0 | C61: =Практики!H187 -> 0 | D61: =Практики!H190 -> 0 | H61: =Практики!H191 -> 0
A62: ='Результаты аудита'!E19 -> T-PREPROD-SECTEST | B62: =Практики!H192 -> 0 | D62: =Практики!H198 -> 0 | F62: =Практики!H200 -> 0 | G62: =Практики!H203 -> 0 | I62: =Практики!H207 -> 0
A63: ='Результаты аудита'!E20 -> T-PREPROD-MANSEC | B63: =Практики!H209 -> 0 | C63: =Практики!H193 -> 0 | D63: =Практики!H194 -> 0 | H63: =Практики!H196 -> 0
A64: ='Результаты аудита'!E21 -> T-PREPROD-VULN | B64: =Практики!H197 -> 0 | D64: =Практики!H210 -> 0 | E64: =Практики!H211 -> 0
A65: ='Результаты аудита'!E22 -> T-PROD-SM | B65: =Практики!H214 -> 0 | C65: =Практики!H215 -> 0 | D65: =Практики!H217 -> 0 | E65: =Практики!H219 -> 0 | G65: =Практики!H222 -> 0
A66: ='Результаты аудита'!E23 -> T-PROD-DAST | B66: =Практики!H233 -> 0 | F66: =Практики!H234 -> 0 | G66: =Практики!H237 -> 0 | H66: =Практики!H241 -> 0 | I66: =Практики!H245 -> 0
A67: ='Результаты аудита'!E24 -> T-PROD-PENTEST | B67: =Практики!H225 -> 0 | D67: =Практики!H226 -> 0 | E67: =Практики!H229 -> 0 | F67: =Практики!H230 -> 0 | I67: =Практики!H231 -> 0
A68: ='Результаты аудита'!E25 -> T-PROD-ACCESS | B68: =Практики!H248 -> 0 | C68: =Практики!H249 -> 0 | E68: =Практики!H254 -> 0 | F68: =Практики!H256 -> 0 | I68: =Практики!H257 -> 0
A69: ='Результаты аудита'!E26 -> T-PROD-NETWORK | B69: =Практики!H258 -> 0 | C69: =Практики!H259 -> 0 | D69: =Практики!H261 -> 0 | E69: =Практики!H263 -> 0
A70: ='Результаты аудита'!E27 -> T-PROD-RUN | B70: =Практики!H264 -> 0 | D70: =Практики!H265 -> 0 | E70: =Практики!H266 -> 0 | G70: =Практики!H267 -> 0
A71: ='Результаты аудита'!E28 -> T-PROD-VULN | B71: =Практики!H268 -> 0 | C71: =Практики!H269 -> 0 | D71: =Практики!H271 -> 0 | E71: =Практики!H274 -> 0 | G71: =Практики!H278 -> 0
A72: ='Результаты аудита'!E29 -> T-PROD-EVENTS | B72: =Практики!H280 -> 0 | D72: =Практики!H281 -> 0 | E72: =Практики!H282 -> 0
A73: ='Результаты аудита'!E30 -> P-EDU-AWR | B73: =Практики!H285 -> 0 | C73: =Практики!H286 -> 0 | E73: =Практики!H288 -> 0 | G73: =Практики!H292 -> 0 | H73: =Практики!H294 -> 0
A74: ='Результаты аудита'!E31 -> P-EDU-KB | B74: =Практики!H295 -> 0 | C74: =Практики!H296 -> 0 | E74: =Практики!H297 -> 0 | F74: =Практики!H299 -> 0 | G74: =Практики!H302 -> 0
A75: ='Результаты аудита'!E32 -> P-REQ-TM | B75: =Практики!H306 -> 0 | D75: =Практики!H307 -> 0 | E75: =Практики!H310 -> 0 | F75: =Практики!H313 -> 0 | G75: =Практики!H316 -> 0
A76: ='Результаты аудита'!E33 -> P-REQ-RD | B76: =Практики!H317 -> 0 | C76: =Практики!H318 -> 0 | D76: =Практики!H320 -> 0 | F76: =Практики!H323 -> 0 | H76: =Практики!H326 -> 0
A77: ='Результаты аудита'!E34 -> P-REQ-CR | B77: =Практики!H327 -> 0 | C77: =Практики!H328 -> 0 | D77: =Практики!H329 -> 0 | G77: =Практики!H330 -> 0 | H77: =Практики!H331 -> 0
A78: ='Результаты аудита'!E35 -> P-REQ-STDR-App | B78: =Практики!H332 -> 0 | E78: =Практики!H333 -> 0 | F78: =Практики!H335 -> 0 | G78: =Практики!H336 -> 0 | H78: =Практики!H338 -> 0
A79: ='Результаты аудита'!E36 -> P-REQ-STDR-Infr | B79: =Практики!H339 -> 0 | C79: =Практики!H340 -> 0 | D79: =Практики!H342 -> 0 | E79: =Практики!H344 -> 0 | G79: =Практики!H347 -> 0
A80: ='Результаты аудита'!E37 -> P-DEFECT-MNG | B80: =Практики!H350 -> 0 | C80: =Практики!H351 -> 0 | D80: =Практики!H352 -> 0 | E80: =Практики!H354 -> 0 | I80: =Практики!H357 -> 0
A81: ='Результаты аудита'!E38 -> P-DEFECT-CNS | B81: =Практики!H358 -> 0 | E81: =Практики!H359 -> 0 | F81: =Практики!H361 -> 0 | G81: =Практики!H362 -> 0 | H81: =Практики!H365 -> 0
A82: ='Результаты аудита'!E39 -> P-MET-SET | B82: =Практики!H368 -> 0 | E82: =Практики!H369 -> 0 | F82: =Практики!H371 -> 0
A83: ='Результаты аудита'!E40 -> P-MET-EX | B83: =Практики!H373 -> 0 | E83: =Практики!H374 -> 0 | F83: =Практики!H376 -> 0 | H83: =Практики!H379 -> 0
A84: ='Результаты аудита'!E41 -> P-ROLE-SC | B84: =Практики!H382 -> 0 | C84: =Практики!H383 -> 0 | E84: =Практики!H384 -> 0 | F84: =Практики!H386 -> 0 | I84: =Практики!H390 -> 0
A85: ='Результаты аудита'!E42 -> P-ROLE-RESP | B85: =Практики!H394 -> 0 | C85: =Практики!H395 -> 0 | E85: =Практики!H397 -> 0 | F85: =Практики!H401 -> 0
A86: Итого | B86: =AVERAGE(B46:B85) -> 0 | C86: =AVERAGE(C46:C85) -> 0 | D86: =AVERAGE(D46:D85) -> 0 | E86: =AVERAGE(E46:E85) -> 0 | F86: =AVERAGE(F46:F85) -> 0 | G86: =AVERAGE(G46:G85) -> 0 | H86: =AVERAGE(H46:H85) -> 0 | I86: =AVERAGE(I46:I85) -> 0

Sheet miniRoadmap
A1: Модель | B1: Домены и поддомены | C1: 202х | G1: 202х+1 | K1: 202х+2
C2: Q1 | D2: Q2 | E2: Q3 | F2: Q4 | G2: Q1 | H2: Q2 | I2: Q3 | J2: Q4 | K2: Q1 | L2: Q2 | M2: Q3 | N2: Q4
A3: Технологии | B3: ='Результаты аудита'!D3 -> Контроль использования сторонних компонентов | E3: Внедрение решения OSA\SCA
B4: ='Результаты аудита'!D4 -> Управление артефактами
B5: ='Результаты аудита'!D5 -> Защита рабочих мест разработчика | I5: Внедрение и настройка решения класса XDR
B6: ='Результаты аудита'!D6 -> Защита секретов | G6: Внедрение средство управления секретами (HashiCorp Vault )
B7: ='Результаты аудита'!D7 -> Защита Build-среды | C7: Харденинг узлов сборки , настройка мониторинга, сетевых доступов к workers и пр.
B8: ='Результаты аудита'!D8 -> Защита source code management (SCM) | C8: Харденинг SCM
B9: ='Результаты аудита'!D9 -> Контроль внесения изменений в исходный код | C9: Харденинг SCM, настройка RBAC
B10: ='Результаты аудита'!D10 -> Защита конвейера сборки | C10: Харденинг СI\CD, настройка RBAC, настройка и анализ логов pipeline и пр.
B11: ='Результаты аудита'!D11 -> Безопасность заказной разработки | E11: Формирование Регламента приемки заказной разработки и настройка инструментов анализа SBOM
B12: ='Результаты аудита'!D12 -> Статический анализ (SAST) | E12: Внедрение решения SAST
B13: ='Результаты аудита'!D13 -> Композиционный анализ (SCA) | E13: Внедрение решения OSA\SCA
B14: ='Результаты аудита'!D14 -> Анализ образов контейнеров | D14: Внедрить анализ образов контейнеров и защиту runtime для всех команд , настроить контроль конфигураций
B15: ='Результаты аудита'!D15 -> Идентификация секретов | E15: Внедрить решение Secret detection
B16: ='Результаты аудита'!D16 -> Контроль безопасности Dockerfile’ов | D16: Внедрить инструмент анализа dockerfile'ов
B17: ='Результаты аудита'!D17 -> Динамический анализ приложений (DAST) в PREPROD среде | G17: Внедрить решение класса DAST
B18: ='Результаты аудита'!D18 -> Тестирование на проникновение перед внедрением приложений в продуктив | G18: Формализация и проведение тестирований на проникновение при приемочных испытаниях ПО
B19: ='Результаты аудита'!D19 -> Функциональное ИБ-тестирование | E19: Внедрить практики автотестов, выполняющих проверки по ИБ
B20: ='Результаты аудита'!D20 -> Контроль безопасности манифестов (k8s, terraform и т.д.) | D20: Внедрить анализ образов контейнеров и защиту runtime для всех команд
B21: ='Результаты аудита'!D21 -> Анализ инфраструктуры PREPROD среды на уязвимости
B22: ='Результаты аудита'!D22 -> Управление секретами | G22: Внедрить средство управления секретами (Hashicorp vault)
B23: ='Результаты аудита'!D23 -> Динамический анализ приложений (DAST) в продуктивной среде
B24: ='Результаты аудита'!D24 -> Тестирование на проникновение продуктивной среды | C24: Выполнить сегментацию сети, настроить минимальные сетевые доступы к k8s
B25: ='Результаты аудита'!D25 -> Управление изменениями инфраструктуры и доступом к ней | C25: Выполнить сегментацию сети, настроить минимальные сетевые доступы к k8s | E25: Внедрение решения Container security. | J25: Настройка admission policy
B26: ='Результаты аудита'!D26 -> Контроль сетевого трафика (L4-L7) | E26: Внедрение решения Container security. | J26: Настройка admission policy
B27: ='Результаты аудита'!D27 -> Контроль выполняемых и процессов и их прав доступа | E27: Внедрение решения Container security.
B28: ='Результаты аудита'!D28 -> Анализ инфраструктуры PROD среды на уязвимости
B29: ='Результаты аудита'!D29 -> Анализ событий информационной безопасности | F29: После внедрения решения Container Security создать правила корреляции от него в SIEM
A30: Процессы | B30: ='Результаты аудита'!D30 -> Обучение специалистов | E30: Разработать план обучения специалистов, соглсасование плана обучений
B31: ='Результаты аудита'!D31 -> Управление базой знаний DSO | E31: Назначение ответственных за БЗ и регламентация процессов управления БЗ
B32: ='Результаты аудита'!D32 -> Оценка критичности приложений и моделирование угроз | I32: Разработать методику моделирования угроз ИБ
B33: ='Результаты аудита'!D33 -> Определение требований ИБ, предъявляемых к ПО | F33: 1.Разработать положение по безопасной разработке ПО 2.Разработать регламент безопасной разработки ПО
B34: ='Результаты аудита'!D34 -> Контроль выполнения требований ИБ
B35: ='Результаты аудита'!D35 -> Разработка стандартов конфигураций разрабатываемого ПО | I35: Разработка стандарта
B36: ='Результаты аудита'!D36 -> Разработка стандартов конфигураций для компонентов инфраструктуры | H36: Разработка стандарта
B37: ='Результаты аудита'!D37 -> Обработка дефектов ИБ | D37: Разработать регламент управления уязвимостями
B38: ='Результаты аудита'!D38 -> Консолидация дефектов ИБ | D38: Разработать регламент управления уязвимостями | G38: Внедрить ресурс хранения отчетов тестирований безопасности
B39: ='Результаты аудита'!D39 -> Управление набором метрик ИБ
B40: ='Результаты аудита'!D40 -> Контроль исполнения метрик
B41: ='Результаты аудита'!D41 -> Security Champions | G41: Для каждой команды определить специалиста с ролью Security Champion
B42: ='Результаты аудита'!D42 -> Разграничение ролей процесса DSO | F42: Разработка регламента с разграничением ролей

Sheet Документы для процессов DSO
A1: Предполагаемый базовый перечень и состав документов
A2: Название документа | B2: Предполагаемое содержания (разделы) документа | C2: Примечание
A3: Отчет по результатам проведения оценки зрелости процессов безопасной разработки по фреймворку DAF
B4: Описание текущих процессов разработки ПО;
B5: Перечень сильных/слабых сторон и возможностей для улучшения/развития;
B6: Рекомендации по встраиванию практик безопасной разработки на каждом из этапов разработки ПО.
A7: Проект документа «Положение по безопасной разработке программного обеспечения»
B8: 1 Общие положения
B9: 1.1 Назначение и область действия документа
B10: 1.2 Нормативные документы, на основе которых составлен настоящий документ
B11: 2 Описание процессов безопасной разработки ПО
B12: 2.1 Основные принципы безопасной разработки ПО
B13: 2.2 Описание жизненного цикла безопасной разработки ПО
B14: 2.3 Функциональные роли участников безопасной разработки ПО
B15: 3 Требования ИБ на различных этапах жизненного цикла разработки ПО
B16: 3.1 Общие требования ИБ
B17: 3.2 Требования к этапу планирования функционала ПО
B18: 3.3 Требования к этапу проектирования ПО
B19: 3.4 Требования к этапу разработки ПО
... B25: 4 Контроль и ответственность за выполнение требований настоящего документа
A26: Проект документа «Регламент процесса безопасной разработки ПО»
B27: 1 Общие положения
B28: 1.1 Назначение и область действия документа
B29: 1.2 Нормативные документы, на основе которых составлен настоящий документ
B30: 2 Функциональные роли процесса безопасной разработки ПО
B31: 2.1 Перечень функциональных ролей, участвующих в безопасной разработки ПО
B32: 2.2 Описание и задачи функциональных ролей, участвующих в безопасной разработки ПО
B33: 3 Жизненный цикл безопасной разработки ПО
B34: 3.1 Полный жизненный цикл безопасной разработки ПО
B35: 3.2 Изменение/доработка ПО с точки зрения информационной безопасности
B36: 4 Процессы безопасной разработки ПО
B37: 4.1 Обучение работников в части безопасной разработки ПО
B38: 4.2 Анализ применимости базовых требований ИБ к ПО
... B54: 4.18 Процесс обеспечения безопасности ПО на этапе вывода из эксплуатации
A55: Проект документа «Регламент управления дефектами, идентифицированными в процессе разработки ПО»
B56: 1 Общие положения
B57: 1.1 Назначение и область действия документа
B58: 1.2 Нормативные документы, на основе которых составлен настоящий документ
B59: 2 Общие положения
B60: 2.1 Сроки и правила устранения выявленных уязвимостей в разрабатываемом ПО
B61: 3 Обязанности и ответственность участников процесса управления дефектами, идентифицированными в процессе разработки ПО
B62: 4 Общая схема процесса управления дефектами ИБ в разрабатываемом ПО
B63: Приложение 1. Матрица разграничения обязанностей (RACI-матрица) для общего процесса управления дефектами в разрабатываемом ПО
A64: Проект документа «Использования контрольных точек информационной безопасности (Quality Gates) в процессе разработки ПО»
B65: 1. Определение QUALITY GATES (QG)
B66: 2. Цели и задачи применения QG
B67: 3. Этапы и среды, которые предполагают использование QG
B68: 4. Описание встраивания QG в процессы разработки ПО
B69: 4.1. Этапы внедрения QG в процесс безопасной разработки ПО
B70: 4.2. Описание QG
B71: 4.3. Встраивание QG (внедрение)
B72: 4.3.1. Требования к конвейеру
B73: 4.3.2. План встраивания нового QG
B74: 4.3.3. Точки встраивания (этапы и среды) QG
B75: 4.3.4. Генерация метрик для функционировани QG
B76: 4.3.5. Оценка и учет результатов работы QG
... B87: 6.3.3. Метрики анализа образов контейнеров (Container security)
A88: Проект документа «Стандарт информационной безопасности средств контейнеризации и сред контейнерной оркестрации»
B89: 1 Общие положения
B90: 1.1 Назначение и область действия документа
B91: 1.2 Нормативные документы, на основе которых составлен настоящий документ
B92: 2. Защита элементов ИТ-инфраструктуры, используемой для запуска контейнеров без использования оркестратора
B93: 2.1. Требования по ИБ к ОС для узлов, на которых запускаются контейнеры
B94: 2.2. Требования по ИБ к среде контейнеризации
B95: 3. Защита элементов ИТ-инфраструктуры, используемой для запуска контейнеров с использованием оркестратора
B96: 3.1. Требования по ИБ к ОС узлам оркестратора
B97: 3.2. Требования по ИБ к средствам контейнеризации, используемых средами контейнерной оркестрации
B98: 3.3 Требования по ИБ к средам контейнерной оркестрации
B99: 3.4 Рекомендации по мониторингу и выявлению инцидентов ИБ. Сценарии выявления инцидентов информационной безопасности для сред контейнерной оркестрации и контейнеризации.
B100: 4. Защита образов контейнеров
... B111: 5.2. Требования к автоматизации проверок
A112: Проект документа «Стандарт по безопасной разработке ПО»
B113: 1 Общие положения
B114: 1.1 Назначение и область действия документа
B115: 1.2 Нормативные документы, на основе которых составлен настоящий документ
B116: 2.Основные принципы DevSecOps
B117: 3.Проектирование и разработка (design and code)
B118: 3.1.Общие требования ИБ к разрабатываемому ПО
B119: 3.1.1.Аутентификация
B120: 3.1.2.Контроль доступа
B121: 3.1.3.Контроль потоков данных
B122: 3.1.4.Защита данных при хранении, использовании и передаче
B123: 3.1.5.Контроль ввода-вывода данных
B124: 3.1.6.Контроль загружаемых файлов
... B174: 7.1.Метрики оценки эффективности
A175: Проект документа «Регламент управления компонентами с открытым исходным кодом»
B176: 1 Общие положения
B177: 1.1 Назначение и область действия документа
B178: 1.2 Нормативные документы, на основе которых составлен настоящий документ
B179: 2 Контроль и ответственность
B180: 3 Процесс управления компонентами с открытым исходным кодом
B181: 3.1 Общее описание процесса управления компонентами с открытым исходным кодом
B182: 3.2 Участники процесса управления компонентами с открытым исходным кодом
B183: 3.3 Процедуры управления компонентами с открытым исходным кодом
B184: 3.3.1.1 Процедура добавления компонента во внутренний репозиторий
B185: 3.3.1.2 Процедура модификации доступа к внутреннему репозиторию
B186: 3.3.1.3 Процедура обновления используемых компонентов
A187: Проект документа «Регламент управления секретами»
B188: 1 Общие положения
B189: 1.1 Назначение и область действия документа
...

Sheet FTE AppSec
B1: Язык разработки | C1: Коэффициент сложности | D1: Используемый фреймворк | E1: Коэф. сложности для фреймворка | F1: Тип приложения | G1: Коэффициент сложности приложения | H1: Количество строк кода ВСЕГО (в тысячах) | I1: СРЕДНЕЕ количество ИЗМЕНЯЕМЫХ каждый релиз строк код (в тысячах) | J1: Частота релизов (кол-во раз в год) | K1: Это приложение сканирует SAST? | L1: Это приложение сканирует DAST? | M1: Это приложение сканирует OSA\SCA? | N1: Образы контейнеров этого приложения анализируются? | O1: РЕЗУЛЬТАТ: Затрачиваемое время на анализ результатов AppSec'ом, часов в год | V1: Да
A2: Приложение 1 | B2: TypeScript | C2: =IFERROR(VLOOKUP(B2,Таблица1[#All],2,FALSE),"-") -> 1.1 | F2: веб-приложение | G2: =VLOOKUP(F2,Таблица3[#All],2,FALSE) -> 1 | H2: 300 | I2: 1 | J2: 24 | K2: Да | L2: Да | M2: Да | N2: Да | O2: =$R$8*I2*(IF(K2="Да",1,0)*$R$9+IF(L2="Да",1,0)*$R$10+IF(M2="Да",1,0)*$R$11+IF(N2="Да",1,0)*$R$12)*J2*IF($R$3="Да",0.5,1)+$R$8*H2*(IF(K2="Да",1,0)*$R$9+IF(L2="Да",1,0)*$R$10+IF(M2="Да",1,0)*$R$11+IF(N2="Да",1,0)*$R$12)*IF($R$3="Да",0.5,1) -> 206.145 | Q2: Итого сколько нужно AppSec'ов (FTE) | R2: Есть и используется ли в компании ASOC? | V2: Нет
A3: Приложение 2 | B3: C# | C3: =IFERROR(VLOOKUP(B3,Таблица1[#All],2,FALSE),"-") -> 1.6 | F3: мобильное приложение | G3: =VLOOKUP(F3,Таблица3[#All],2,FALSE) -> 1.6 | H3: 200 | I3: 1 | J3: 20 | K3: Да | L3: Да | M3: Да | N3: Да | O3: =$R$8*I3*(IF(K3="Да",1,0)*$R$9+IF(L3="Да",1,0)*$R$10+IF(M3="Да",1,0)*$R$11+IF(N3="Да",1,0)*$R$12)*J3*IF($R$3="Да",0.5,1)+$R$8*H3*(IF(K3="Да",1,0)*$R$9+IF(L3="Да",1,0)*$R$10+IF(M3="Да",1,0)*$R$11+IF(N3="Да",1,0)*$R$12)*IF($R$3="Да",0.5,1) -> 139.975 | Q3: =(SUM(O2:O301)+R13+R6+R7)*V5/V4 -> 1.7484659 | R3: Да
A4: Приложение 3 | B4: Kotlin | C4: =IFERROR(VLOOKUP(B4,Таблица1[#All],2,FALSE),"-") -> 1.1 | F4: веб-приложение | G4: =IFERROR(VLOOKUP(F4,Таблица3[#All],2,FALSE),"-") -> 1 | H4: 250 | I4: 1 | J4: 12 | K4: Да | L4: Да | M4: Да | N4: Да | O4: =$R$8*I4*(IF(K4="Да",1,0)*$R$9+IF(L4="Да",1,0)*$R$10+IF(M4="Да",1,0)*$R$11+IF(N4="Да",1,0)*$R$12)*J4*IF($R$3="Да",0.5,1)+$R$8*H4*(IF(K4="Да",1,0)*$R$9+IF(L4="Да",1,0)*$R$10+IF(M4="Да",1,0)*$R$11+IF(N4="Да",1,0)*$R$12)*IF($R$3="Да",0.5,1) -> 166.6975 | U4: Количество рабочих часов в году | V4: =8*247 -> 1976
A5: Приложение 4 | B5: Python | C5: =IFERROR(VLOOKUP(B5,Таблица1[#All],2,FALSE),"-") -> 1 | F5: веб-приложение | G5: =IFERROR(VLOOKUP(F5,Таблица3[#All],2,FALSE),"-") -> 1 | H5: 400 | I5: 2 | J5: 24 | K5: Да | L5: Да | M5: Да | N5: Да | O5: =$R$8*I5*(IF(K5="Да",1,0)*$R$9+IF(L5="Да",1,0)*$R$10+IF(M5="Да",1,0)*$R$11+IF(N5="Да",1,0)*$R$12)*J5*IF($R$3="Да",0.5,1)+$R$8*H5*(IF(K5="Да",1,0)*$R$9+IF(L5="Да",1,0)*$R$10+IF(M5="Да",1,0)*$R$11+IF(N5="Да",1,0)*$R$12)*IF($R$3="Да",0.5,1) -> 285.04 | Q5: Ограничения | U5: Коэффициент расчета FTE (отпуски, болезни и прочее) | V5: 1.1
A6: Приложение 5 | B6: Solidity | C6: =IFERROR(VLOOKUP(B6,Таблица1[#All],2,FALSE),"-") -> 1.1 | F6: веб-приложение | G6: =IFERROR(VLOOKUP(F6,Таблица3[#All],2,FALSE),"-") -> 1 | H6: 400 | I6: 1 | J6: 12 | K6: Да | L6: Да | M6: Да | N6: Да | O6: =$R$8*I6*(IF(K6="Да",1,0)*$R$9+IF(L6="Да",1,0)*$R$10+IF(M6="Да",1,0)*$R$11+IF(N6="Да",1,0)*$R$12)*J6*IF($R$3="Да",0.5,1)+$R$8*H6*(IF(K6="Да",1,0)*$R$9+IF(L6="Да",1,0)*$R$10+IF(M6="Да",1,0)*$R$11+IF(N6="Да",1,0)*$R$12)*IF($R$3="Да",0.5,1) -> 262.135 | Q6: Постановка и контроль задач на устранения найденных в приложениях уязвимостях силами AppSec-инеженера, часов | R6: =SUM(I2:I301)*SUM(J2:J301)*0.001*12 -> 37.488
A7: Приложение 6 | B7: Kotlin | C7: =IFERROR(VLOOKUP(B7,Таблица1[#All],2,FALSE),"-") -> 1.1 | F7: мобильное приложение | G7: =IFERROR(VLOOKUP(F7,Таблица3[#All],2,FALSE),"-") -> 1.6 | H7: 200 | I7: 1 | J7: 36 | K7: Да | L7: Да | M7: Да | N7: Да | O7: =$R$8*I7*(IF(K7="Да",1,0)*$R$9+IF(L7="Да",1,0)*$R$10+IF(M7="Да",1,0)*$R$11+IF(N7="Да",1,0)*$R$12)*J7*IF($R$3="Да",0.5,1)+$R$8*H7*(IF(K7="Да",1,0)*$R$9+IF(L7="Да",1,0)*$R$10+IF(M7="Да",1,0)*$R$11+IF(N7="Да",1,0)*$R$12)*IF($R$3="Да",0.5,1) -> 150.155 | Q7: Консультации команд разработки силами AppSec-инженера по верифицированным уязвимостям, часов | R7: =COUNTA(B2:B301)*12 -> 144
A8: Приложение 7 | B8: Perl | C8: =IFERROR(VLOOKUP(B8,Таблица1[#All],2,FALSE),"-") -> 1.1 | F8: веб-приложение | G8: =IFERROR(VLOOKUP(F8,Таблица3[#All],2,FALSE),"-") -> 1 | H8: 100 | I8: 0.5 | J8: 12 | K8: Да | L8: Да | M8: Да | N8: Да | O8: =$R$8*I8*(IF(K8="Да",1,0)*$R$9+IF(L8="Да",1,0)*$R$10+IF(M8="Да",1,0)*$R$11+IF(N8="Да",1,0)*$R$12)*J8*IF($R$3="Да",0.5,1)+$R$8*H8*(IF(K8="Да",1,0)*$R$9+IF(L8="Да",1,0)*$R$10+IF(M8="Да",1,0)*$R$11+IF(N8="Да",1,0)*$R$12)*IF($R$3="Да",0.5,1) -> 67.4425 | Q8: СРЕДНЕЕ время обработки 1-го найденного дефекта\уязвимости, часов | R8: 0.05
A9: Приложение 8 | B9: Java | C9: =IFERROR(VLOOKUP(B9,Таблица1[#All],2,FALSE),"-") -> 1.1 | F9: веб-приложение | G9: =IFERROR(VLOOKUP(F9,Таблица3[#All],2,FALSE),"-") -> 1 | H9: 800 | I9: 1 | J9: 24 | K9: Да | L9: Да | M9: Да | N9: Да | O9: =$R$8*I9*(IF(K9="Да",1,0)*$R$9+IF(L9="Да",1,0)*$R$10+IF(M9="Да",1,0)*$R$11+IF(N9="Да",1,0)*$R$12)*J9*IF($R$3="Да",0.5,1)+$R$8*H9*(IF(K9="Да",1,0)*$R$9+IF(L9="Да",1,0)*$R$10+IF(M9="Да",1,0)*$R$11+IF(N9="Да",1,0)*$R$12)*IF($R$3="Да",0.5,1) -> 524.27 | Q9: SAST. СРЕДНЕЕ количество дефектов на 1000 строк кода | R9: 5
A10: Приложение 9 | B10: JavaScript | C10: =IFERROR(VLOOKUP(B10,Таблица1[#All],2,FALSE),"-") -> 1.1 | F10: веб-приложение | G10: =IFERROR(VLOOKUP(F10,Таблица3[#All],2,FALSE),"-") -> 1 | H10: 300 | I10: 1 | J10: 36 | K10: Да | L10: Да | M10: Да | N10: Да | O10: =$R$8*I10*(IF(K10="Да",1,0)*$R$9+IF(L10="Да",1,0)*$R$10+IF(M10="Да",1,0)*$R$11+IF(N10="Да",1,0)*$R$12)*J10*IF($R$3="Да",0.5,1)+$R$8*H10*(IF(K10="Да",1,0)*$R$9+IF(L10="Да",1,0)*$R$10+IF(M10="Да",1,0)*$R$11+IF(N10="Да",1,0)*$R$12)*IF($R$3="Да",0.5,1) -> 213.78 | Q10: DAST. СРЕДНЕЕ количество дефектов на 1000 строк кода | R10: 0.25
A11: Приложение 10 | B11: PHP | C11: =IFERROR(VLOOKUP(B11,Таблица1[#All],2,FALSE),"-") -> 1 | F11: веб-приложение | G11: =IFERROR(VLOOKUP(F11,Таблица3[#All],2,FALSE),"-") -> 1 | H11: 400 | I11: 1 | J11: 36 | K11: Да | L11: Да | M11: Да | N11: Да | O11: =$R$8*I11*(IF(K11="Да",1,0)*$R$9+IF(L11="Да",1,0)*$R$10+IF(M11="Да",1,0)*$R$11+IF(N11="Да",1,0)*$R$12)*J11*IF($R$3="Да",0.5,1)+$R$8*H11*(IF(K11="Да",1,0)*$R$9+IF(L11="Да",1,0)*$R$10+IF(M11="Да",1,0)*$R$11+IF(N11="Да",1,0)*$R$12)*IF($R$3="Да",0.5,1) -> 277.405 | Q11: SCA. СРЕДНЕЕ количество open source проектов, используемых в разработке | R11: 20
A12: Приложение 11 | B12: Python | C12: =IFERROR(VLOOKUP(B12,Таблица1[#All],2,FALSE),"-") -> 1 | F12: веб-приложение | G12: =IFERROR(VLOOKUP(F12,Таблица3[#All],2,FALSE),"-") -> 1 | H12: 52 | I12: 0.25 | J12: 36 | K12: Да | L12: Да | M12: Да | N12: Да | O12: =$R$8*I12*(IF(K12="Да",1,0)*$R$9+IF(L12="Да",1,0)*$R$10+IF(M12="Да",1,0)*$R$11+IF(N12="Да",1,0)*$R$12)*J12*IF($R$3="Да",0.5,1)+$R$8*H12*(IF(K12="Да",1,0)*$R$9+IF(L12="Да",1,0)*$R$10+IF(M12="Да",1,0)*$R$11+IF(N12="Да",1,0)*$R$12)*IF($R$3="Да",0.5,1) -> 38.81125 | Q12: Container Analisys. СРЕДНЕЕ количество дефектов на 1 анализируемый образ | R12: 0.2
A13: Приложение 12 | B13: Python | C13: =IFERROR(VLOOKUP(B13,Таблица1[#All],2,FALSE),"-") -> 1 | F13: веб-приложение | G13: =IFERROR(VLOOKUP(F13,Таблица3[#All],2,FALSE),"-") -> 1 | H13: 78 | I13: 0.25 | J13: 12 | K13: Да | L13: Да | M13: Да | N13: Да | O13: =$R$8*I13*(IF(K13="Да",1,0)*$R$9+IF(L13="Да",1,0)*$R$10+IF(M13="Да",1,0)*$R$11+IF(N13="Да",1,0)*$R$12)*J13*IF($R$3="Да",0.5,1)+$R$8*H13*(IF(K13="Да",1,0)*$R$9+IF(L13="Да",1,0)*$R$10+IF(M13="Да",1,0)*$R$11+IF(N13="Да",1,0)*$R$12)*IF($R$3="Да",0.5,1) -> 51.53625 | Q13: Разработка ЕЖЕМЕСЯЧНЫХ отчетов по анализу ВСЕХ приложений (часов в год) | R13: =COUNTA(B2:B301)*4*12 -> 576
A14: Приложение 13 | C14: =IFERROR(VLOOKUP(B14,Таблица1[#All],2,FALSE),"-") -> - | G14: =IFERROR(VLOOKUP(F14,Таблица3[#All],2,FALSE),"-") -> - | H14: 0 | J14: 0 | K14: Нет | L14: Нет | M14: Нет | N14: Нет | O14: =$R$8*I14*(IF(K14="Да",1,0)*$R$9+IF(L14="Да",1,0)*$R$10+IF(M14="Да",1,0)*$R$11+IF(N14="Да",1,0)*$R$12)*J14*IF($R$3="Да",0.5,1)+$R$8*H14*(IF(K14="Да",1,0)*$R$9+IF(L14="Да",1,0)*$R$10+IF(M14="Да",1,0)*$R$11+IF(N14="Да",1,0)*$R$12)*IF($R$3="Да",0.5,1) -> 0
A15: Приложение 14 | C15: =IFERROR(VLOOKUP(B15,Таблица1[#All],2,FALSE),"-") -> - | G15: =IFERROR(VLOOKUP(F15,Таблица3[#All],2,FALSE),"-") -> - | H15: 0 | J15: 0 | K15: Нет | L15: Нет | M15: Нет | N15: Нет | O15: =$R$8*I15*(IF(K15="Да",1,0)*$R$9+IF(L15="Да",1,0)*$R$10+IF(M15="Да",1,0)*$R$11+IF(N15="Да",1,0)*$R$12)*J15*IF($R$3="Да",0.5,1)+$R$8*H15*(IF(K15="Да",1,0)*$R$9+IF(L15="Да",1,0)*$R$10+IF(M15="Да",1,0)*$R$11+IF(N15="Да",1,0)*$R$12)*IF($R$3="Да",0.5,1) -> 0 | Q15: Тип приложения | R15: Сложность динамического анализа (от 1 до 2)
A16: Приложение 15 | C16: =IFERROR(VLOOKUP(B16,Таблица1[#All],2,FALSE),"-") -> - | G16: =IFERROR(VLOOKUP(F16,Таблица3[#All],2,FALSE),"-") -> - | H16: 0 | J16: 0 | K16: Нет | L16: Нет | M16: Нет | N16: Нет | O16: =$R$8*I16*(IF(K16="Да",1,0)*$R$9+IF(L16="Да",1,0)*$R$10+IF(M16="Да",1,0)*$R$11+IF(N16="Да",1,0)*$R$12)*J16*IF($R$3="Да",0.5,1)+$R$8*H16*(IF(K16="Да",1,0)*$R$9+IF(L16="Да",1,0)*$R$10+IF(M16="Да",1,0)*$R$11+IF(N16="Да",1,0)*$R$12)*IF($R$3="Да",0.5,1) -> 0 | Q16: веб-приложение | R16: 1
A17: Приложение 16 | C17: =IFERROR(VLOOKUP(B17,Таблица1[#All],2,FALSE),"-") -> - | G17: =IFERROR(VLOOKUP(F17,Таблица3[#All],2,FALSE),"-") -> - | H17: 0 | J17: 0 | K17: Нет | L17: Нет | M17: Нет | N17: Нет | O17: =$R$8*I17*(IF(K17="Да",1,0)*$R$9+IF(L17="Да",1,0)*$R$10+IF(M17="Да",1,0)*$R$11+IF(N17="Да",1,0)*$R$12)*J17*IF($R$3="Да",0.5,1)+$R$8*H17*(IF(K17="Да",1,0)*$R$9+IF(L17="Да",1,0)*$R$10+IF(M17="Да",1,0)*$R$11+IF(N17="Да",1,0)*$R$12)*IF($R$3="Да",0.5,1) -> 0 | Q17: мобильное приложение | R17: 1.6
A18: Приложение 17 | C18: =IFERROR(VLOOKUP(B18,Таблица1[#All],2,FALSE),"-") -> - | G18: =IFERROR(VLOOKUP(F18,Таблица3[#All],2,FALSE),"-") -> - | H18: 0 | J18: 0 | K18: Нет | L18: Нет | M18: Нет | N18: Нет | O18: =$R$8*I18*(IF(K18="Да",1,0)*$R$9+IF(L18="Да",1,0)*$R$10+IF(M18="Да",1,0)*$R$11+IF(N18="Да",1,0)*$R$12)*J18*IF($R$3="Да",0.5,1)+$R$8*H18*(IF(K18="Да",1,0)*$R$9+IF(L18="Да",1,0)*$R$10+IF(M18="Да",1,0)*$R$11+IF(N18="Да",1,0)*$R$12)*IF($R$3="Да",0.5,1) -> 0 | Q18: толстое приложение | R18: 1.9
A19: Приложение 18 | C19: =IFERROR(VLOOKUP(B19,Таблица1[#All],2,FALSE),"-") -> - | G19: =IFERROR(VLOOKUP(F19,Таблица3[#All],2,FALSE),"-") -> - | H19: 0 | J19: 0 | K19: Нет | L19: Нет | M19: Нет | N19: Нет | O19: =$R$8*I19*(IF(K19="Да",1,0)*$R$9+IF(L19="Да",1,0)*$R$10+IF(M19="Да",1,0)*$R$11+IF(N19="Да",1,0)*$R$12)*J19*IF($R$3="Да",0.5,1)+$R$8*H19*(IF(K19="Да",1,0)*$R$9+IF(L19="Да",1,0)*$R$10+IF(M19="Да",1,0)*$R$11+IF(N19="Да",1,0)*$R$12)*IF($R$3="Да",0.5,1) -> 0
A20: Приложение 19 | C20: =IFERROR(VLOOKUP(B20,Таблица1[#All],2,FALSE),"-") -> - | G20: =IFERROR(VLOOKUP(F20,Таблица3[#All],2,FALSE),"-") -> - | H20: 0 | J20: 0 | K20: Нет | L20: Нет | M20: Нет | N20: Нет | O20: =$R$8*I20*(IF(K20="Да",1,0)*$R$9+IF(L20="Да",1,0)*$R$10+IF(M20="Да",1,0)*$R$11+IF(N20="Да",1,0)*$R$12)*J20*IF($R$3="Да",0.5,1)+$R$8*H20*(IF(K20="Да",1,0)*$R$9+IF(L20="Да",1,0)*$R$10+IF(M20="Да",1,0)*$R$11+IF(N20="Да",1,0)*$R$12)*IF($R$3="Да",0.5,1) -> 0
A21: Приложение 20 | C21: =IFERROR(VLOOKUP(B21,Таблица1[#All],2,FALSE),"-") -> - | G21: =IFERROR(VLOOKUP(F21,Таблица3[#All],2,FALSE),"-") -> - | H21: 0 | J21: 0 | K21: Нет | L21: Нет | M21: Нет | N21: Нет | O21: =$R$8*I21*(IF(K21="Да",1,0)*$R$9+IF(L21="Да",1,0)*$R$10+IF(M21="Да",1,0)*$R$11+IF(N21="Да",1,0)*$R$12)*J21*IF($R$3="Да",0.5,1)+$R$8*H21*(IF(K21="Да",1,0)*$R$9+IF(L21="Да",1,0)*$R$10+IF(M21="Да",1,0)*$R$11+IF(N21="Да",1,0)*$R$12)*IF($R$3="Да",0.5,1) -> 0 | Q21: ЯП | R21: коэф. Сложности (от 1 до 2) | S21: Группы знаний | T21: Примечание
A22: Приложение 21 | C22: =IFERROR(VLOOKUP(B22,Таблица1[#All],2,FALSE),"-") -> - | G22: =IFERROR(VLOOKUP(F22,Таблица3[#All],2,FALSE),"-") -> - | H22: 0 | J22: 0 | K22: Нет | L22: Нет | M22: Нет | N22: Нет | O22: =$R$8*I22*(IF(K22="Да",1,0)*$R$9+IF(L22="Да",1,0)*$R$10+IF(M22="Да",1,0)*$R$11+IF(N22="Да",1,0)*$R$12)*J22*IF($R$3="Да",0.5,1)+$R$8*H22*(IF(K22="Да",1,0)*$R$9+IF(L22="Да",1,0)*$R$10+IF(M22="Да",1,0)*$R$11+IF(N22="Да",1,0)*$R$12)*IF($R$3="Да",0.5,1) -> 0 | Q22: ABAP | R22: 2 | S22: 5 | T22: 5 - мутные языки
A23: Приложение 22 | C23: =IFERROR(VLOOKUP(B23,Таблица1[#All],2,FALSE),"-") -> - | G23: =IFERROR(VLOOKUP(F23,Таблица3[#All],2,FALSE),"-") -> - | H23: 0 | J23: 0 | K23: Нет | L23: Нет | M23: Нет | N23: Нет | O23: =$R$8*I23*(IF(K23="Да",1,0)*$R$9+IF(L23="Да",1,0)*$R$10+IF(M23="Да",1,0)*$R$11+IF(N23="Да",1,0)*$R$12)*J23*IF($R$3="Да",0.5,1)+$R$8*H23*(IF(K23="Да",1,0)*$R$9+IF(L23="Да",1,0)*$R$10+IF(M23="Да",1,0)*$R$11+IF(N23="Да",1,0)*$R$12)*IF($R$3="Да",0.5,1) -> 0 | Q23: Apex | R23: 1.5 | S23: 5 | T23: 5 - мутные языки
A24: Приложение 23 | C24: =IFERROR(VLOOKUP(B24,Таблица1[#All],2,FALSE),"-") -> - | G24: =IFERROR(VLOOKUP(F24,Таблица3[#All],2,FALSE),"-") -> - | H24: 0 | J24: 0 | K24: Нет | L24: Нет | M24: Нет | N24: Нет | O24: =$R$8*I24*(IF(K24="Да",1,0)*$R$9+IF(L24="Да",1,0)*$R$10+IF(M24="Да",1,0)*$R$11+IF(N24="Да",1,0)*$R$12)*J24*IF($R$3="Да",0.5,1)+$R$8*H24*(IF(K24="Да",1,0)*$R$9+IF(L24="Да",1,0)*$R$10+IF(M24="Да",1,0)*$R$11+IF(N24="Да",1,0)*$R$12)*IF($R$3="Да",0.5,1) -> 0 | Q24: C# | R24: 1.6 | S24: 2 | T24: 2 - бэкенд
A25: Приложение 24 | C25: =IFERROR(VLOOKUP(B25,Таблица1[#All],2,FALSE),"-") -> - | G25: =IFERROR(VLOOKUP(F25,Таблица3[#All],2,FALSE),"-") -> - | H25: 0 | J25: 0 | K25: Нет | L25: Нет | M25: Нет | N25: Нет | O25: =$R$8*I25*(IF(K25="Да",1,0)*$R$9+IF(L25="Да",1,0)*$R$10+IF(M25="Да",1,0)*$R$11+IF(N25="Да",1,0)*$R$12)*J25*IF($R$3="Да",0.5,1)+$R$8*H25*(IF(K25="Да",1,0)*$R$9+IF(L25="Да",1,0)*$R$10+IF(M25="Да",1,0)*$R$11+IF(N25="Да",1,0)*$R$12)*IF($R$3="Да",0.5,1) -> 0 | Q25: C/C++ | R25: 1.8 | S25: 2 | T25: 2 - бэкенд
A26: Приложение 25 | C26: =IFERROR(VLOOKUP(B26,Таблица1[#All],2,FALSE),"-") -> - | G26: =IFERROR(VLOOKUP(F26,Таблица3[#All],2,FALSE),"-") -> - | H26: 0 | J26: 0 | K26: Нет | L26: Нет | M26: Нет | N26: Нет | O26: =$R$8*I26*(IF(K26="Да",1,0)*$R$9+IF(L26="Да",1,0)*$R$10+IF(M26="Да",1,0)*$R$11+IF(N26="Да",1,0)*$R$12)*J26*IF($R$3="Да",0.5,1)+$R$8*H26*(IF(K26="Да",1,0)*$R$9+IF(L26="Да",1,0)*$R$10+IF(M26="Да",1,0)*$R$11+IF(N26="Да",1,0)*$R$12)*IF($R$3="Да",0.5,1) -> 0 | Q26: COBOL | R26: 2 | S26: 5 | T26: 5 - мутные языки
A27: Приложение 26 | C27: =IFERROR(VLOOKUP(B27,Таблица1[#All],2,FALSE),"-") -> - | G27: =IFERROR(VLOOKUP(F27,Таблица3[#All],2,FALSE),"-") -> - | H27: 0 | J27: 0 | K27: Нет | L27: Нет | M27: Нет | N27: Нет | O27: =$R$8*I27*(IF(K27="Да",1,0)*$R$9+IF(L27="Да",1,0)*$R$10+IF(M27="Да",1,0)*$R$11+IF(N27="Да",1,0)*$R$12)*J27*IF($R$3="Да",0.5,1)+$R$8*H27*(IF(K27="Да",1,0)*$R$9+IF(L27="Да",1,0)*$R$10+IF(M27="Да",1,0)*$R$11+IF(N27="Да",1,0)*$R$12)*IF($R$3="Да",0.5,1) -> 0 | Q27: Dart | R27: 1.1 | S27: 4 | T27: 4 - мобильная разработка
A28: Приложение 27 | C28: =IFERROR(VLOOKUP(B28,Таблица1[#All],2,FALSE),"-") -> - | G28: =IFERROR(VLOOKUP(F28,Таблица3[#All],2,FALSE),"-") -> - | H28: 0 | J28: 0 | K28: Нет | L28: Нет | M28: Нет | N28: Нет | O28: =$R$8*I28*(IF(K28="Да",1,0)*$R$9+IF(L28="Да",1,0)*$R$10+IF(M28="Да",1,0)*$R$11+IF(N28="Да",1,0)*$R$12)*J28*IF($R$3="Да",0.5,1)+$R$8*H28*(IF(K28="Да",1,0)*$R$9+IF(L28="Да",1,0)*$R$10+IF(M28="Да",1,0)*$R$11+IF(N28="Да",1,0)*$R$12)*IF($R$3="Да",0.5,1) -> 0 | Q28: Delphi | R28: 1 | S28: 2 | T28: 2 - бэкенд
A29: Приложение 28 | C29: =IFERROR(VLOOKUP(B29,Таблица1[#All],2,FALSE),"-") -> - | G29: =IFERROR(VLOOKUP(F29,Таблица3[#All],2,FALSE),"-") -> - | H29: 0 | J29: 0 | K29: Нет | L29: Нет | M29: Нет | N29: Нет | O29: =$R$8*I29*(IF(K29="Да",1,0)*$R$9+IF(L29="Да",1,0)*$R$10+IF(M29="Да",1,0)*$R$11+IF(N29="Да",1,0)*$R$12)*J29*IF($R$3="Да",0.5,1)+$R$8*H29*(IF(K29="Да",1,0)*$R$9+IF(L29="Да",1,0)*$R$10+IF(M29="Да",1,0)*$R$11+IF(N29="Да",1,0)*$R$12)*IF($R$3="Да",0.5,1) -> 0 | Q29: Groovy | R29: 1.1 | S29: 1 | T29: 1 - компилируемые языки
A30: Приложение 29 | C30: =IFERROR(VLOOKUP(B30,Таблица1[#All],2,FALSE),"-") -> - | G30: =IFERROR(VLOOKUP(F30,Таблица3[#All],2,FALSE),"-") -> - | H30: 0 | J30: 0 | K30: Нет | L30: Нет | M30: Нет | N30: Нет | O30: =$R$8*I30*(IF(K30="Да",1,0)*$R$9+IF(L30="Да",1,0)*$R$10+IF(M30="Да",1,0)*$R$11+IF(N30="Да",1,0)*$R$12)*J30*IF($R$3="Да",0.5,1)+$R$8*H30*(IF(K30="Да",1,0)*$R$9+IF(L30="Да",1,0)*$R$10+IF(M30="Да",1,0)*$R$11+IF(N30="Да",1,0)*$R$12)*IF($R$3="Да",0.5,1) -> 0 | Q30: HTML | R30: 1 | S30: 3 | T30: 3 - бэкенд
A31: Приложение 30 | C31: =IFERROR(VLOOKUP(B31,Таблица1[#All],2,FALSE),"-") -> - | G31: =IFERROR(VLOOKUP(F31,Таблица3[#All],2,FALSE),"-") -> - | H31: 0 | J31: 0 | K31: Нет | L31: Нет | M31: Нет | N31: Нет | O31: =$R$8*I31*(IF(K31="Да",1,0)*$R$9+IF(L31="Да",1,0)*$R$10+IF(M31="Да",1,0)*$R$11+IF(N31="Да",1,0)*$R$12)*J31*IF($R$3="Да",0.5,1)+$R$8*H31*(IF(K31="Да",1,0)*$R$9+IF(L31="Да",1,0)*$R$10+IF(M31="Да",1,0)*$R$11+IF(N31="Да",1,0)*$R$12)*IF($R$3="Да",0.5,1) -> 0 | Q31: Kotlin | R31: 1.1 | S31: 1 или 4 | T31: 4 - мобильная разработка
A32: Приложение 31 | C32: =IFERROR(VLOOKUP(B32,Таблица1[#All],2,FALSE),"-") -> - | G32: =IFERROR(VLOOKUP(F32,Таблица3[#All],2,FALSE),"-") -> - | H32: 0 | J32: 0 | K32: Нет | L32: Нет | M32: Нет | N32: Нет | O32: =$R$8*I32*(IF(K32="Да",1,0)*$R$9+IF(L32="Да",1,0)*$R$10+IF(M32="Да",1,0)*$R$11+IF(N32="Да",1,0)*$R$12)*J32*IF($R$3="Да",0.5,1)+$R$8*H32*(IF(K32="Да",1,0)*$R$9+IF(L32="Да",1,0)*$R$10+IF(M32="Да",1,0)*$R$11+IF(N32="Да",1,0)*$R$12)*IF($R$3="Да",0.5,1) -> 0 | Q32: Java | R32: 1.1 | S32: 1 | T32: 1 - компилируемые языки
A33: Приложение 32 | C33: =IFERROR(VLOOKUP(B33,Таблица1[#All],2,FALSE),"-") -> - | G33: =IFERROR(VLOOKUP(F33,Таблица3[#All],2,FALSE),"-") -> - | H33: 0 | J33: 0 | K33: Нет | L33: Нет | M33: Нет | N33: Нет | O33: =$R$8*I33*(IF(K33="Да",1,0)*$R$9+IF(L33="Да",1,0)*$R$10+IF(M33="Да",1,0)*$R$11+IF(N33="Да",1,0)*$R$12)*J33*IF($R$3="Да",0.5,1)+$R$8*H33*(IF(K33="Да",1,0)*$R$9+IF(L33="Да",1,0)*$R$10+IF(M33="Да",1,0)*$R$11+IF(N33="Да",1,0)*$R$12)*IF($R$3="Да",0.5,1) -> 0 | Q33: JavaScript | R33: 1.1 | S33: 3 | T33: 3 - бэкенд
A34: Приложение 33 | C34: =IFERROR(VLOOKUP(B34,Таблица1[#All],2,FALSE),"-") -> - | G34: =IFERROR(VLOOKUP(F34,Таблица3[#All],2,FALSE),"-") -> - | H34: 0 | J34: 0 | K34: Нет | L34: Нет | M34: Нет | N34: Нет | O34: =$R$8*I34*(IF(K34="Да",1,0)*$R$9+IF(L34="Да",1,0)*$R$10+IF(M34="Да",1,0)*$R$11+IF(N34="Да",1,0)*$R$12)*J34*IF($R$3="Да",0.5,1)+$R$8*H34*(IF(K34="Да",1,0)*$R$9+IF(L34="Да",1,0)*$R$10+IF(M34="Да",1,0)*$R$11+IF(N34="Да",1,0)*$R$12)*IF($R$3="Да",0.5,1) -> 0 | Q34: LotusScript | R34: 1.1 | S34: 1 | T34: 1 - компилируемые языки
A35: Приложение 34 | C35: =IFERROR(VLOOKUP(B35,Таблица1[#All],2,FALSE),"-") -> - | G35: =IFERROR(VLOOKUP(F35,Таблица3[#All],2,FALSE),"-") -> - | H35: 0 | J35: 0 | K35: Нет | L35: Нет | M35: Нет | N35: Нет | O35: =$R$8*I35*(IF(K35="Да",1,0)*$R$9+IF(L35="Да",1,0)*$R$10+IF(M35="Да",1,0)*$R$11+IF(N35="Да",1,0)*$R$12)*J35*IF($R$3="Да",0.5,1)+$R$8*H35*(IF(K35="Да",1,0)*$R$9+IF(L35="Да",1,0)*$R$10+IF(M35="Да",1,0)*$R$11+IF(N35="Да",1,0)*$R$12)*IF($R$3="Да",0.5,1) -> 0 | Q35: Objective-C | R35: 1 | S35: 2 | T35: 2 - бэкенд
A36: Приложение 35 | C36: =IFERROR(VLOOKUP(B36,Таблица1[#All],2,FALSE),"-") -> - | G36: =IFERROR(VLOOKUP(F36,Таблица3[#All],2,FALSE),"-") -> - | H36: 0 | J36: 0 | K36: Нет | L36: Нет | M36: Нет | N36: Нет | O36: =$R$8*I36*(IF(K36="Да",1,0)*$R$9+IF(L36="Да",1,0)*$R$10+IF(M36="Да",1,0)*$R$11+IF(N36="Да",1,0)*$R$12)*J36*IF($R$3="Да",0.5,1)+$R$8*H36*(IF(K36="Да",1,0)*$R$9+IF(L36="Да",1,0)*$R$10+IF(M36="Да",1,0)*$R$11+IF(N36="Да",1,0)*$R$12)*IF($R$3="Да",0.5,1) -> 0 | Q36: Pascal | R36: 1 | S36: 2 | T36: 2 - бэкенд
A37: Приложение 36 | C37: =IFERROR(VLOOKUP(B37,Таблица1[#All],2,FALSE),"-") -> - | G37: =IFERROR(VLOOKUP(F37,Таблица3[#All],2,FALSE),"-") -> - | H37: 0 | J37: 0 | K37: Нет | L37: Нет | M37: Нет | N37: Нет | O37: =$R$8*I37*(IF(K37="Да",1,0)*$R$9+IF(L37="Да",1,0)*$R$10+IF(M37="Да",1,0)*$R$11+IF(N37="Да",1,0)*$R$12)*J37*IF($R$3="Да",0.5,1)+$R$8*H37*(IF(K37="Да",1,0)*$R$9+IF(L37="Да",1,0)*$R$10+IF(M37="Да",1,0)*$R$11+IF(N37="Да",1,0)*$R$12)*IF($R$3="Да",0.5,1) -> 0 | Q37: PHP | R37: 1 | S37: 3 | T37: 3 - бэкенд
A38: Приложение 37 | C38: =IFERROR(VLOOKUP(B38,Таблица1[#All],2,FALSE),"-") -> - | G38: =IFERROR(VLOOKUP(F38,Таблица3[#All],2,FALSE),"-") -> - | H38: 0 | J38: 0 | K38: Нет | L38: Нет | M38: Нет | N38: Нет | O38: =$R$8*I38*(IF(K38="Да",1,0)*$R$9+IF(L38="Да",1,0)*$R$10+IF(M38="Да",1,0)*$R$11+IF(N38="Да",1,0)*$R$12)*J38*IF($R$3="Да",0.5,1)+$R$8*H38*(IF(K38="Да",1,0)*$R$9+IF(L38="Да",1,0)*$R$10+IF(M38="Да",1,0)*$R$11+IF(N38="Да",1,0)*$R$12)*IF($R$3="Да",0.5,1) -> 0 | Q38: PL/SQL | R38: 1.1 | S38: 2 или 3 | T38: 2 - бэкенд, 3 - тоже бэкенд
A39: Приложение 38 | C39: =IFERROR(VLOOKUP(B39,Таблица1[#All],2,FALSE),"-") -> - | G39: =IFERROR(VLOOKUP(F39,Таблица3[#All],2,FALSE),"-") -> - | H39: 0 | J39: 0 | K39: Нет | L39: Нет | M39: Нет | N39: Нет | O39: =$R$8*I39*(IF(K39="Да",1,0)*$R$9+IF(L39="Да",1,0)*$R$10+IF(M39="Да",1,0)*$R$11+IF(N39="Да",1,0)*$R$12)*J39*IF($R$3="Да",0.5,1)+$R$8*H39*(IF(K39="Да",1,0)*$R$9+IF(L39="Да",1,0)*$R$10+IF(M39="Да",1,0)*$R$11+IF(N39="Да",1,0)*$R$12)*IF($R$3="Да",0.5,1) -> 0 | Q39: Perl | R39: 1.1 | S39: 3 | T39: 3 - бэкенд
A40: Приложение 39 | C40: =IFERROR(VLOOKUP(B40,Таблица1[#All],2,FALSE),"-") -> - | G40: =IFERROR(VLOOKUP(F40,Таблица3[#All],2,FALSE),"-") -> - | H40: 0 | J40: 0 | K40: Нет | L40: Нет | M40: Нет | N40: Нет | O40: =$R$8*I40*(IF(K40="Да",1,0)*$R$9+IF(L40="Да",1,0)*$R$10+IF(M40="Да",1,0)*$R$11+IF(N40="Да",1,0)*$R$12)*J40*IF($R$3="Да",0.5,1)+$R$8*H40*(IF(K40="Да",1,0)*$R$9+IF(L40="Да",1,0)*$R$10+IF(M40="Да",1,0)*$R$11+IF(N40="Да",1,0)*$R$12)*IF($R$3="Да",0.5,1) -> 0 | Q40: Ruby | R40: 1.1 | S40: 1 | T40: 1 - компилируемые языки
A41: Приложение 40 | C41: =IFERROR(VLOOKUP(B41,Таблица1[#All],2,FALSE),"-") -> - | G41: =IFERROR(VLOOKUP(F41,Таблица3[#All],2,FALSE),"-") -> - | H41: 0 | J41: 0 | K41: Нет | L41: Нет | M41: Нет | N41: Нет | O41: =$R$8*I41*(IF(K41="Да",1,0)*$R$9+IF(L41="Да",1,0)*$R$10+IF(M41="Да",1,0)*$R$11+IF(N41="Да",1,0)*$R$12)*J41*IF($R$3="Да",0.5,1)+$R$8*H41*(IF(K41="Да",1,0)*$R$9+IF(L41="Да",1,0)*$R$10+IF(M41="Да",1,0)*$R$11+IF(N41="Да",1,0)*$R$12)*IF($R$3="Да",0.5,1) -> 0 | Q41: Rust | R41: 1.3 | S41: 1 | T41: 1 - компилируемые языки
A42: Приложение 41 | C42: =IFERROR(VLOOKUP(B42,Таблица1[#All],2,FALSE),"-") -> - | G42: =IFERROR(VLOOKUP(F42,Таблица3[#All],2,FALSE),"-") -> - | H42: 0 | J42: 0 | K42: Нет | L42: Нет | M42: Нет | N42: Нет | O42: =$R$8*I42*(IF(K42="Да",1,0)*$R$9+IF(L42="Да",1,0)*$R$10+IF(M42="Да",1,0)*$R$11+IF(N42="Да",1,0)*$R$12)*J42*IF($R$3="Да",0.5,1)+$R$8*H42*(IF(K42="Да",1,0)*$R$9+IF(L42="Да",1,0)*$R$10+IF(M42="Да",1,0)*$R$11+IF(N42="Да",1,0)*$R$12)*IF($R$3="Да",0.5,1) -> 0 | Q42: Scala | R42: 1.3 | S42: 1 | T42: 1 - компилируемые языки
A43: Приложение 42 | C43: =IFERROR(VLOOKUP(B43,Таблица1[#All],2,FALSE),"-") -> - | G43: =IFERROR(VLOOKUP(F43,Таблица3[#All],2,FALSE),"-") -> - | H43: 0 | J43: 0 | K43: Нет | L43: Нет | M43: Нет | N43: Нет | O43: =$R$8*I43*(IF(K43="Да",1,0)*$R$9+IF(L43="Да",1,0)*$R$10+IF(M43="Да",1,0)*$R$11+IF(N43="Да",1,0)*$R$12)*J43*IF($R$3="Да",0.5,1)+$R$8*H43*(IF(K43="Да",1,0)*$R$9+IF(L43="Да",1,0)*$R$10+IF(M43="Да",1,0)*$R$11+IF(N43="Да",1,0)*$R$12)*IF($R$3="Да",0.5,1) -> 0 | Q43: Solidity | R43: 1.1 | S43: 5 | T43: 5 - мутные языки
A44: Приложение 43 | C44: =IFERROR(VLOOKUP(B44,Таблица1[#All],2,FALSE),"-") -> - | G44: =IFERROR(VLOOKUP(F44,Таблица3[#All],2,FALSE),"-") -> - | H44: 0 | J44: 0 | K44: Нет | L44: Нет | M44: Нет | N44: Нет | O44: =$R$8*I44*(IF(K44="Да",1,0)*$R$9+IF(L44="Да",1,0)*$R$10+IF(M44="Да",1,0)*$R$11+IF(N44="Да",1,0)*$R$12)*J44*IF($R$3="Да",0.5,1)+$R$8*H44*(IF(K44="Да",1,0)*$R$9+IF(L44="Да",1,0)*$R$10+IF(M44="Да",1,0)*$R$11+IF(N44="Да",1,0)*$R$12)*IF($R$3="Да",0.5,1) -> 0 | Q44: Swift | R44: 1.1 | S44: 4 | T44: 4 - мобильная разработка
A45: Приложение 44 | C45: =IFERROR(VLOOKUP(B45,Таблица1[#All],2,FALSE),"-") -> - | G45: =IFERROR(VLOOKUP(F45,Таблица3[#All],2,FALSE),"-") -> - | H45: 0 | J45: 0 | K45: Нет | L45: Нет | M45: Нет | N45: Нет | O45: =$R$8*I45*(IF(K45="Да",1,0)*$R$9+IF(L45="Да",1,0)*$R$10+IF(M45="Да",1,0)*$R$11+IF(N45="Да",1,0)*$R$12)*J45*IF($R$3="Да",0.5,1)+$R$8*H45*(IF(K45="Да",1,0)*$R$9+IF(L45="Да",1,0)*$R$10+IF(M45="Да",1,0)*$R$11+IF(N45="Да",1,0)*$R$12)*IF($R$3="Да",0.5,1) -> 0 | Q45: T-SQL | R45: 1.1 | S45: 2 или 3 | T45: 2 - бэкенд, 3 - тоже бэкенд
A46: Приложение 45 | C46: =IFERROR(VLOOKUP(B46,Таблица1[#All],2,FALSE),"-") -> - | G46: =IFERROR(VLOOKUP(F46,Таблица3[#All],2,FALSE),"-") -> - | H46: 0 | J46: 0 | K46: Нет | L46: Нет | M46: Нет | N46: Нет | O46: =$R$8*I46*(IF(K46="Да",1,0)*$R$9+IF(L46="Да",1,0)*$R$10+IF(M46="Да",1,0)*$R$11+IF(N46="Да",1,0)*$R$12)*J46*IF($R$3="Да",0.5,1)+$R$8*H46*(IF(K46="Да",1,0)*$R$9+IF(L46="Да",1,0)*$R$10+IF(M46="Да",1,0)*$R$11+IF(N46="Да",1,0)*$R$12)*IF($R$3="Да",0.5,1) -> 0 | Q46: TypeScript | R46: 1.1 | S46: 3 | T46: 3 - бэкенд
A47: Приложение 46 | C47: =IFERROR(VLOOKUP(B47,Таблица1[#All],2,FALSE),"-") -> - | G47: =IFERROR(VLOOKUP(F47,Таблица3[#All],2,FALSE),"-") -> - | H47: 0 | J47: 0 | K47: Нет | L47: Нет | M47: Нет | N47: Нет | O47: =$R$8*I47*(IF(K47="Да",1,0)*$R$9+IF(L47="Да",1,0)*$R$10+IF(M47="Да",1,0)*$R$11+IF(N47="Да",1,0)*$R$12)*J47*IF($R$3="Да",0.5,1)+$R$8*H47*(IF(K47="Да",1,0)*$R$9+IF(L47="Да",1,0)*$R$10+IF(M47="Да",1,0)*$R$11+IF(N47="Да",1,0)*$R$12)*IF($R$3="Да",0.5,1) -> 0 | Q47: VB.NET | R47: 1.1 | S47: 1 | T47: 1 - компилируемые языки
A48: Приложение 47 | C48: =IFERROR(VLOOKUP(B48,Таблица1[#All],2,FALSE),"-") -> - | G48: =IFERROR(VLOOKUP(F48,Таблица3[#All],2,FALSE),"-") -> - | H48: 0 | J48: 0 | K48: Нет | L48: Нет | M48: Нет | N48: Нет | O48: =$R$8*I48*(IF(K48="Да",1,0)*$R$9+IF(L48="Да",1,0)*$R$10+IF(M48="Да",1,0)*$R$11+IF(N48="Да",1,0)*$R$12)*J48*IF($R$3="Да",0.5,1)+$R$8*H48*(IF(K48="Да",1,0)*$R$9+IF(L48="Да",1,0)*$R$10+IF(M48="Да",1,0)*$R$11+IF(N48="Да",1,0)*$R$12)*IF($R$3="Да",0.5,1) -> 0 | Q48: VBA | R48: 1.1 | S48: 1 | T48: 1 - компилируемые языки
A49: Приложение 48 | C49: =IFERROR(VLOOKUP(B49,Таблица1[#All],2,FALSE),"-") -> - | G49: =IFERROR(VLOOKUP(F49,Таблица3[#All],2,FALSE),"-") -> - | H49: 0 | J49: 0 | K49: Нет | L49: Нет | M49: Нет | N49: Нет | O49: =$R$8*I49*(IF(K49="Да",1,0)*$R$9+IF(L49="Да",1,0)*$R$10+IF(M49="Да",1,0)*$R$11+IF(N49="Да",1,0)*$R$12)*J49*IF($R$3="Да",0.5,1)+$R$8*H49*(IF(K49="Да",1,0)*$R$9+IF(L49="Да",1,0)*$R$10+IF(M49="Да",1,0)*$R$11+IF(N49="Да",1,0)*$R$12)*IF($R$3="Да",0.5,1) -> 0 | Q49: VBScript | R49: 1.1 | S49: 1 | T49: 1 - компилируемые языки
A50: Приложение 49 | C50: =IFERROR(VLOOKUP(B50,Таблица1[#All],2,FALSE),"-") -> - | G50: =IFERROR(VLOOKUP(F50,Таблица3[#All],2,FALSE),"-") -> - | H50: 0 | J50: 0 | K50: Нет | L50: Нет | M50: Нет | N50: Нет | O50: =$R$8*I50*(IF(K50="Да",1,0)*$R$9+IF(L50="Да",1,0)*$R$10+IF(M50="Да",1,0)*$R$11+IF(N50="Да",1,0)*$R$12)*J50*IF($R$3="Да",0.5,1)+$R$8*H50*(IF(K50="Да",1,0)*$R$9+IF(L50="Да",1,0)*$R$10+IF(M50="Да",1,0)*$R$11+IF(N50="Да",1,0)*$R$12)*IF($R$3="Да",0.5,1) -> 0 | Q50: Visual Basic 6 | R50: 1.1 | S50: 1 | T50: 1 - компилируемые языки
A51: Приложение 50 | C51: =IFERROR(VLOOKUP(B51,Таблица1[#All],2,FALSE),"-") -> - | G51: =IFERROR(VLOOKUP(F51,Таблица3[#All],2,FALSE),"-") -> - | H51: 0 | J51: 0 | K51: Нет | L51: Нет | M51: Нет | N51: Нет | O51: =$R$8*I51*(IF(K51="Да",1,0)*$R$9+IF(L51="Да",1,0)*$R$10+IF(M51="Да",1,0)*$R$11+IF(N51="Да",1,0)*$R$12)*J51*IF($R$3="Да",0.5,1)+$R$8*H51*(IF(K51="Да",1,0)*$R$9+IF(L51="Да",1,0)*$R$10+IF(M51="Да",1,0)*$R$11+IF(N51="Да",1,0)*$R$12)*IF($R$3="Да",0.5,1) -> 0 | Q51: Vyper | R51: 1.3 | S51: 5 | T51: 5 - мутные языки
A52: Приложение 51 | C52: =IFERROR(VLOOKUP(B52,Таблица1[#All],2,FALSE),"-") -> - | G52: =IFERROR(VLOOKUP(F52,Таблица3[#All],2,FALSE),"-") -> - | H52: 0 | J52: 0 | K52: Нет | L52: Нет | M52: Нет | N52: Нет | O52: =$R$8*I52*(IF(K52="Да",1,0)*$R$9+IF(L52="Да",1,0)*$R$10+IF(M52="Да",1,0)*$R$11+IF(N52="Да",1,0)*$R$12)*J52*IF($R$3="Да",0.5,1)+$R$8*H52*(IF(K52="Да",1,0)*$R$9+IF(L52="Да",1,0)*$R$10+IF(M52="Да",1,0)*$R$11+IF(N52="Да",1,0)*$R$12)*IF($R$3="Да",0.5,1) -> 0 | Q52: 1C | R52: 1.3 | S52: 5 | T52: 5 - мутные языки
A53: Приложение 52 | C53: =IFERROR(VLOOKUP(B53,Таблица1[#All],2,FALSE),"-") -> - | G53: =IFERROR(VLOOKUP(F53,Таблица3[#All],2,FALSE),"-") -> - | H53: 0 | J53: 0 | K53: Нет | L53: Нет | M53: Нет | N53: Нет | O53: =$R$8*I53*(IF(K53="Да",1,0)*$R$9+IF(L53="Да",1,0)*$R$10+IF(M53="Да",1,0)*$R$11+IF(N53="Да",1,0)*$R$12)*J53*IF($R$3="Да",0.5,1)+$R$8*H53*(IF(K53="Да",1,0)*$R$9+IF(L53="Да",1,0)*$R$10+IF(M53="Да",1,0)*$R$11+IF(N53="Да",1,0)*$R$12)*IF($R$3="Да",0.5,1) -> 0 | Q53: react | R53: 1 | S53: 3 | T53: 3 - бэкенд
A54: Приложение 53 | C54: =IFERROR(VLOOKUP(B54,Таблица1[#All],2,FALSE),"-") -> - | G54: =IFERROR(VLOOKUP(F54,Таблица3[#All],2,FALSE),"-") -> - | H54: 0 | J54: 0 | K54: Нет | L54: Нет | M54: Нет | N54: Нет | O54: =$R$8*I54*(IF(K54="Да",1,0)*$R$9+IF(L54="Да",1,0)*$R$10+IF(M54="Да",1,0)*$R$11+IF(N54="Да",1,0)*$R$12)*J54*IF($R$3="Да",0.5,1)+$R$8*H54*(IF(K54="Да",1,0)*$R$9+IF(L54="Да",1,0)*$R$10+IF(M54="Да",1,0)*$R$11+IF(N54="Да",1,0)*$R$12)*IF($R$3="Да",0.5,1) -> 0 | Q54: Golang | R54: 1 | S54: 2 | T54: 2 - бэкенд
A55: Приложение 54 | C55: =IFERROR(VLOOKUP(B55,Таблица1[#All],2,FALSE),"-") -> - | G55: =IFERROR(VLOOKUP(F55,Таблица3[#All],2,FALSE),"-") -> - | H55: 0 | J55: 0 | K55: Нет | L55: Нет | M55: Нет | N55: Нет | O55: =$R$8*I55*(IF(K55="Да",1,0)*$R$9+IF(L55="Да",1,0)*$R$10+IF(M55="Да",1,0)*$R$11+IF(N55="Да",1,0)*$R$12)*J55*IF($R$3="Да",0.5,1)+$R$8*H55*(IF(K55="Да",1,0)*$R$9+IF(L55="Да",1,0)*$R$10+IF(M55="Да",1,0)*$R$11+IF(N55="Да",1,0)*$R$12)*IF($R$3="Да",0.5,1) -> 0 | Q55: Python | R55: 1 | S55: 3 | T55: 3 - бэкенд
A56: Приложение 55 | C56: =IFERROR(VLOOKUP(B56,Таблица1[#All],2,FALSE),"-") -> - | G56: =IFERROR(VLOOKUP(F56,Таблица3[#All],2,FALSE),"-") -> - | H56: 0 | J56: 0 | K56: Нет | L56: Нет | M56: Нет | N56: Нет | O56: =$R$8*I56*(IF(K56="Да",1,0)*$R$9+IF(L56="Да",1,0)*$R$10+IF(M56="Да",1,0)*$R$11+IF(N56="Да",1,0)*$R$12)*J56*IF($R$3="Да",0.5,1)+$R$8*H56*(IF(K56="Да",1,0)*$R$9+IF(L56="Да",1,0)*$R$10+IF(M56="Да",1,0)*$R$11+IF(N56="Да",1,0)*$R$12)*IF($R$3="Да",0.5,1) -> 0
A57: Приложение 56 | C57: =IFERROR(VLOOKUP(B57,Таблица1[#All],2,FALSE),"-") -> - | G57: =IFERROR(VLOOKUP(F57,Таблица3[#All],2,FALSE),"-") -> - | H57: 0 | J57: 0 | K57: Нет | L57: Нет | M57: Нет | N57: Нет | O57: =$R$8*I57*(IF(K57="Да",1,0)*$R$9+IF(L57="Да",1,0)*$R$10+IF(M57="Да",1,0)*$R$11+IF(N57="Да",1,0)*$R$12)*J57*IF($R$3="Да",0.5,1)+$R$8*H57*(IF(K57="Да",1,0)*$R$9+IF(L57="Да",1,0)*$R$10+IF(M57="Да",1,0)*$R$11+IF(N57="Да",1,0)*$R$12)*IF($R$3="Да",0.5,1) -> 0
A58: Приложение 57 | C58: =IFERROR(VLOOKUP(B58,Таблица1[#All],2,FALSE),"-") -> - | G58: =IFERROR(VLOOKUP(F58,Таблица3[#All],2,FALSE),"-") -> - | H58: 0 | J58: 0 | K58: Нет | L58: Нет | M58: Нет | N58: Нет | O58: =$R$8*I58*(IF(K58="Да",1,0)*$R$9+IF(L58="Да",1,0)*$R$10+IF(M58="Да",1,0)*$R$11+IF(N58="Да",1,0)*$R$12)*J58*IF($R$3="Да",0.5,1)+$R$8*H58*(IF(K58="Да",1,0)*$R$9+IF(L58="Да",1,0)*$R$10+IF(M58="Да",1,0)*$R$11+IF(N58="Да",1,0)*$R$12)*IF($R$3="Да",0.5,1) -> 0
A59: Приложение 58 | C59: =IFERROR(VLOOKUP(B59,Таблица1[#All],2,FALSE),"-") -> - | G59: =IFERROR(VLOOKUP(F59,Таблица3[#All],2,FALSE),"-") -> - | H59: 0 | J59: 0 | K59: Нет | L59: Нет | M59: Нет | N59: Нет | O59: =$R$8*I59*(IF(K59="Да",1,0)*$R$9+IF(L59="Да",1,0)*$R$10+IF(M59="Да",1,0)*$R$11+IF(N59="Да",1,0)*$R$12)*J59*IF($R$3="Да",0.5,1)+$R$8*H59*(IF(K59="Да",1,0)*$R$9+IF(L59="Да",1,0)*$R$10+IF(M59="Да",1,0)*$R$11+IF(N59="Да",1,0)*$R$12)*IF($R$3="Да",0.5,1) -> 0
A60: Приложение 59 | C60: =IFERROR(VLOOKUP(B60,Таблица1[#All],2,FALSE),"-") -> - | G60: =IFERROR(VLOOKUP(F60,Таблица3[#All],2,FALSE),"-") -> - | H60: 0 | J60: 0 | K60: Нет | L60: Нет | M60: Нет | N60: Нет | O60: =$R$8*I60*(IF(K60="Да",1,0)*$R$9+IF(L60="Да",1,0)*$R$10+IF(M60="Да",1,0)*$R$11+IF(N60="Да",1,0)*$R$12)*J60*IF($R$3="Да",0.5,1)+$R$8*H60*(IF(K60="Да",1,0)*$R$9+IF(L60="Да",1,0)*$R$10+IF(M60="Да",1,0)*$R$11+IF(N60="Да",1,0)*$R$12)*IF($R$3="Да",0.5,1) -> 0
A61: Приложение 60 | C61: =IFERROR(VLOOKUP(B61,Таблица1[#All],2,FALSE),"-") -> - | G61: =IFERROR(VLOOKUP(F61,Таблица3[#All],2,FALSE),"-") -> - | H61: 0 | J61: 0 | K61: Нет | L61: Нет | M61: Нет | N61: Нет | O61: =$R$8*I61*(IF(K61="Да",1,0)*$R$9+IF(L61="Да",1,0)*$R$10+IF(M61="Да",1,0)*$R$11+IF(N61="Да",1,0)*$R$12)*J61*IF($R$3="Да",0.5,1)+$R$8*H61*(IF(K61="Да",1,0)*$R$9+IF(L61="Да",1,0)*$R$10+IF(M61="Да",1,0)*$R$11+IF(N61="Да",1,0)*$R$12)*IF($R$3="Да",0.5,1) -> 0
A62: Приложение 61 | C62: =IFERROR(VLOOKUP(B62,Таблица1[#All],2,FALSE),"-") -> - | G62: =IFERROR(VLOOKUP(F62,Таблица3[#All],2,FALSE),"-") -> - | H62: 0 | J62: 0 | K62: Нет | L62: Нет | M62: Нет | N62: Нет | O62: =$R$8*I62*(IF(K62="Да",1,0)*$R$9+IF(L62="Да",1,0)*$R$10+IF(M62="Да",1,0)*$R$11+IF(N62="Да",1,0)*$R$12)*J62*IF($R$3="Да",0.5,1)+$R$8*H62*(IF(K62="Да",1,0)*$R$9+IF(L62="Да",1,0)*$R$10+IF(M62="Да",1,0)*$R$11+IF(N62="Да",1,0)*$R$12)*IF($R$3="Да",0.5,1) -> 0
A63: Приложение 62 | C63: =IFERROR(VLOOKUP(B63,Таблица1[#All],2,FALSE),"-") -> - | G63: =IFERROR(VLOOKUP(F63,Таблица3[#All],2,FALSE),"-") -> - | H63: 0 | J63: 0 | K63: Нет | L63: Нет | M63: Нет | N63: Нет | O63: =$R$8*I63*(IF(K63="Да",1,0)*$R$9+IF(L63="Да",1,0)*$R$10+IF(M63="Да",1,0)*$R$11+IF(N63="Да",1,0)*$R$12)*J63*IF($R$3="Да",0.5,1)+$R$8*H63*(IF(K63="Да",1,0)*$R$9+IF(L63="Да",1,0)*$R$10+IF(M63="Да",1,0)*$R$11+IF(N63="Да",1,0)*$R$12)*IF($R$3="Да",0.5,1) -> 0
A64: Приложение 63 | C64: =IFERROR(VLOOKUP(B64,Таблица1[#All],2,FALSE),"-") -> - | G64: =IFERROR(VLOOKUP(F64,Таблица3[#All],2,FALSE),"-") -> - | H64: 0 | J64: 0 | K64: Нет | L64: Нет | M64: Нет | N64: Нет | O64: =$R$8*I64*(IF(K64="Да",1,0)*$R$9+IF(L64="Да",1,0)*$R$10+IF(M64="Да",1,0)*$R$11+IF(N64="Да",1,0)*$R$12)*J64*IF($R$3="Да",0.5,1)+$R$8*H64*(IF(K64="Да",1,0)*$R$9+IF(L64="Да",1,0)*$R$10+IF(M64="Да",1,0)*$R$11+IF(N64="Да",1,0)*$R$12)*IF($R$3="Да",0.5,1) -> 0
A65: Приложение 64 | C65: =IFERROR(VLOOKUP(B65,Таблица1[#All],2,FALSE),"-") -> - | G65: =IFERROR(VLOOKUP(F65,Таблица3[#All],2,FALSE),"-") -> - | H65: 0 | J65: 0 | K65: Нет | L65: Нет | M65: Нет | N65: Нет | O65: =$R$8*I65*(IF(K65="Да",1,0)*$R$9+IF(L65="Да",1,0)*$R$10+IF(M65="Да",1,0)*$R$11+IF(N65="Да",1,0)*$R$12)*J65*IF($R$3="Да",0.5,1)+$R$8*H65*(IF(K65="Да",1,0)*$R$9+IF(L65="Да",1,0)*$R$10+IF(M65="Да",1,0)*$R$11+IF(N65="Да",1,0)*$R$12)*IF($R$3="Да",0.5,1) -> 0
A66: Приложение 65 | C66: =IFERROR(VLOOKUP(B66,Таблица1[#All],2,FALSE),"-") -> - | G66: =IFERROR(VLOOKUP(F66,Таблица3[#All],2,FALSE),"-") -> - | H66: 0 | J66: 0 | K66: Нет | L66: Нет | M66: Нет | N66: Нет | O66: =$R$8*I66*(IF(K66="Да",1,0)*$R$9+IF(L66="Да",1,0)*$R$10+IF(M66="Да",1,0)*$R$11+IF(N66="Да",1,0)*$R$12)*J66*IF($R$3="Да",0.5,1)+$R$8*H66*(IF(K66="Да",1,0)*$R$9+IF(L66="Да",1,0)*$R$10+IF(M66="Да",1,0)*$R$11+IF(N66="Да",1,0)*$R$12)*IF($R$3="Да",0.5,1) -> 0
A67: Приложение 66 | C67: =IFERROR(VLOOKUP(B67,Таблица1[#All],2,FALSE),"-") -> - | G67: =IFERROR(VLOOKUP(F67,Таблица3[#All],2,FALSE),"-") -> - | H67: 0 | J67: 0 | K67: Нет | L67: Нет | M67: Нет | N67: Нет | O67: =$R$8*I67*(IF(K67="Да",1,0)*$R$9+IF(L67="Да",1,0)*$R$10+IF(M67="Да",1,0)*$R$11+IF(N67="Да",1,0)*$R$12)*J67*IF($R$3="Да",0.5,1)+$R$8*H67*(IF(K67="Да",1,0)*$R$9+IF(L67="Да",1,0)*$R$10+IF(M67="Да",1,0)*$R$11+IF(N67="Да",1,0)*$R$12)*IF($R$3="Да",0.5,1) -> 0
... A301: Приложение 300 | C301: =IFERROR(VLOOKUP(B301,Таблица1[#All],2,FALSE),"-") -> - | G301: =IFERROR(VLOOKUP(F301,Таблица3[#All],2,FALSE),"-") -> - | H301: 0 | J301: 0 | K301: Нет | L301: Нет | M301: Нет | N301: Нет | O301: =$R$8*I301*(IF(K301="Да",1,0)*$R$9+IF(L301="Да",1,0)*$R$10+IF(M301="Да",1,0)*$R$11+IF(N301="Да",1,0)*$R$12)*J301*IF($R$3="Да",0.5,1)+$R$8*H301*(IF(K301="Да",1,0)*$R$9+IF(L301="Да",1,0)*$R$10+IF(M301="Да",1,0)*$R$11+IF(N301="Да",1,0)*$R$12)*IF($R$3="Да",0.5,1) -> 0

Sheet Расчет FTE DSO
A1: Задача | B1: Единица измерения | C1: Норма времени (в часах) | D1: Периодичность выполнения | E1: Выполняется несколько раз в неделю | F1: Выполняется несколько раз в месяц | G1: Выполняется несколько раз в квартал | H1: Итого в год, часов
A2: ПРИМЕР!
A3: Container security
A4: 1. Контроль корректности текущих настроек и конфигурации | J4: Параметр | K4: Значение
A5: - Контроль корректности настроек | B5: Одна операция | C5: 0.5 | D5: 5 | E5: X | H5: =IF(E5="X",C5*D5*48, IF(F5="X", C5*D5*12, IF(G5="X",C5*D5*4))) -> 120 | J5: Часов в неделе | K5: 40
A6: - Корректировка настроек при необходимости | B6: Одна операция | C6: 2 | D6: 1 | F6: X | H6: =IF(E6="X",C6*D6*48, IF(F6="X", C6*D6*12, IF(G6="X",C6*D6*4))) -> 24 | J6: Недель в месяце | K6: 4
A7: 2. Предоставление доступа к Container security | J7: Часов в месяце | K7: =K5*K6 -> 160
A8: - Предоставление доступа | B8: Одна операция | C8: 0.25 | D8: 3 | F8: X | H8: =IF(E8="X",C8*D8*48, IF(F8="X", C8*D8*12, IF(G8="X",C8*D8*4))) -> 9 | J8: Месяцев в квартале | K8: 3
A9: - Актуализация прав доступа | B9: Одна операция | C9: 2 | D9: 1 | F9: X | H9: =IF(E9="X",C9*D9*48, IF(F9="X", C9*D9*12, IF(G9="X",C9*D9*4))) -> 24 | J9: Часов в квартале | K9: =K7*K8 -> 480
A10: 3. Настройка подписки на события в кластере Kubernetes | B10: Одна операция | C10: 2 | D10: 2 | F10: X | H10: =IF(E10="X",C10*D10*48, IF(F10="X", C10*D10*12, IF(G10="X",C10*D10*4))) -> 48 | J10: Кварталов в году | K10: 4
A11: 4. Настройка параметров обучения политики | B11: Одна операция | C11: 2 | D11: 4 | G11: X | H11: =IF(E11="X",C11*D11*48, IF(F11="X", C11*D11*12, IF(G11="X",C11*D11*4))) -> 32 | J11: Часов в году | K11: =K10*K9 -> 1920
A12: 5. Анализ событий аудита | B12: Одна операция | C12: 1 | D12: 5 | E12: X | H12: =IF(E12="X",C12*D12*48, IF(F12="X", C12*D12*12, IF(G12="X",C12*D12*4))) -> 240
A13: 6. Подготовка отчетов | B13: Единоразовый анализ событий аудита | C13: 1 | D13: 4 | F13: X | H13: =IF(E13="X",C13*D13*48, IF(F13="X", C13*D13*12, IF(G13="X",C13*D13*4))) -> 48 | J13: Коэффициент расчета FTE | K13: 1.1 | L13: Отпуски, болезни и прочее
A14: 7. Контроль соответствия узлов кластера лучшим практикам CIS | J14: Часов для одного FTE в год | K14: =247*8 -> 1976 | L14: 247 рабочих дней в году
A15: - Контроль настроек и постановка задачи на исправление | B15: Одна консультация | C15: 1 | D15: 2 | F15: X | H15: =IF(E15="X",C15*D15*48, IF(F15="X", C15*D15*12, IF(G15="X",C15*D15*4))) -> 24 | J15: Итого FTE нужно | K15: =SUM(H26,H41,H56,H69,H81,H96,H111,H118,H126) -> 3.3092611 | L15: Всегда нужно округлять в бОльшую сторону
A16: - Корректировка Ansible playbook для исправления | B16: Одна операция | C16: 4 | D16: 2 | G16: X | H16: =IF(E16="X",C16*D16*48, IF(F16="X", C16*D16*12, IF(G16="X",C16*D16*4))) -> 32
A17: 8. Обновление ПО | B17: Одна консультация | C17: 4 | D17: 1 | G17: X | H17: =IF(E17="X",C17*D17*48, IF(F17="X", C17*D17*12, IF(G17="X",C17*D17*4))) -> 16
A18: 9. Масштабирование решения | B18: Одна консультация | C18: 0.5 | D18: 2 | G18: X | H18: =IF(E18="X",C18*D18*48, IF(F18="X", C18*D18*12, IF(G18="X",C18*D18*4))) -> 4
A19: 10. Контроль резервного копирования
A20: - Проверка резервной копии в СРК | B20: Одна операция | C20: 0.25 | D20: 5 | E20: X | H20: =IF(E20="X",C20*D20*48, IF(F20="X", C20*D20*12, IF(G20="X",C20*D20*4))) -> 60
A21: - Проверка возможности восстановления из РК | B21: Одна операция | C21: 2 | D21: 1 | G21: X | H21: =IF(E21="X",C21*D21*48, IF(F21="X", C21*D21*12, IF(G21="X",C21*D21*4))) -> 8
A22: 11. Актуализация прав доступа настроенных в кластерах Kubernetes (RBAC) | B22: Одна операция | C22: 3 | D22: 1 | F22: X | H22: =IF(E22="X",C22*D22*48, IF(F22="X", C22*D22*12, IF(G22="X",C22*D22*4))) -> 36
A23: 12. Актуализация и анализ сетевых политик | B23: Одна операция | C23: 4 | D23: 2 | F23: X | H23: =IF(E23="X",C23*D23*48, IF(F23="X", C23*D23*12, IF(G23="X",C23*D23*4))) -> 96
A24: Итого (Ч) для Container security: | H24: =SUM(H5:H6,H8:H23) -> 821
A25: Итого (Ч-Д) для Container security: | H25: =H24/8 -> 102.625
A26: Итого (FTE) для Container security: | H26: =(H24/K14)*1.1 -> 0.45703441
A27: KeyCloak
A28: 1. Контроль корректности текущих настроек и конфигурации
A29: - Контроль корректности настроек | B29: Одна операция | C29: 0.25 | D29: 5 | E29: X | H29: =IF(E29="X",C29*D29*48, IF(F29="X", C29*D29*48, IF(G29="X",C29*D29*12))) -> 60
A30: - Корректировка настроек при необходимости | B30: Одна операция | C30: 2 | D30: 2 | G30: X | H30: =IF(E30="X",C30*D30*48, IF(F30="X", C30*D30*48, IF(G30="X",C30*D30*12))) -> 48
A31: 2. Предоставление доступа к ресурсам кластера Kubernetes | B31: Одна операция | C31: 1 | D31: 3 | F31: X | H31: =IF(E31="X",C31*D31*48, IF(F31="X", C31*D31*12, IF(G31="X",C31*D31*4))) -> 36
A32: 3. Контроль резервного копирования
A33: - Проверка наличия резервных копий и их целостности | B33: Контроль создания РК | C33: 0.25 | D33: 5 | E33: X | H33: =IF(E33="X",C33*D33*48, IF(F33="X", C33*D33*12, IF(G33="X",C33*D33*4))) -> 60
A34: - Проверка возможности восстановления из РК | B34: Восстановление из РК | C34: 3 | D34: 2 | G34: X | H34: =IF(E34="X",C34*D34*48, IF(F34="X", C34*D34*12, IF(G34="X",C34*D34*4))) -> 24
A35: 4. Создание отчетов | B35: Один отчет | C35: 1.5 | D35: 1 | F35: X | H35: =IF(E35="X",C35*D35*48, IF(F35="X", C35*D35*12, IF(G35="X",C35*D35*4))) -> 18
A36: 5. Обновление ПО | B36: Одна консультация | C36: 4 | D36: 1 | G36: X | H36: =IF(E36="X",C36*D36*48, IF(F36="X", C36*D36*12, IF(G36="X",C36*D36*4))) -> 16
A37: 6. Анализ событий аудита | B37: Одна операция | C37: 0.5 | D37: 5 | E37: X | H37: =IF(E37="X",C37*D37*48, IF(F37="X", C37*D37*12, IF(G37="X",C37*D37*4))) -> 120
A38: 7. Масштабирование системы | B38: Одна консультация | C38: 0.5 | D38: 2 | G38: X | H38: =IF(E38="X",C38*D38*48, IF(F38="X", C38*D38*12, IF(G38="X",C38*D38*4))) -> 4
A39: Итого (Ч) для KeyCloak: | H39: =SUM(H29:H30,H31:H31,H33:H38) -> 386
A40: Итого (Ч-Д) для KeyCloak: | H40: =H39/8 -> 48.25
A41: Итого (FTE) для KeyCloak: | H41: =H39/K14 -> 0.19534413
A42: Kyverno
A43: 1. Контроль корректности текущих настроек и конфигурации
A44: - Контроль корректности настроек | B44: Одна операция | C44: 0.5 | D44: 5 | E44: X | H44: =IF(E44="X",C44*D44*48, IF(F44="X", C44*D44*48, IF(G44="X",C44*D44*12))) -> 120
A45: - Корректировка настроек при необходимости | B45: Одна операция | C45: 2 | D45: 3 | G45: X | H45: =IF(E45="X",C45*D45*48, IF(F45="X", C45*D45*48, IF(G45="X",C45*D45*12))) -> 72
A46: 2. Проверка корректности резервного копирования | B46: Контроль создания РК | C46: 0.25 | D46: 5 | E46: X | H46: =IF(E46="X",C46*D46*48, IF(F46="X", C46*D46*12, IF(G46="X",C46*D46*4))) -> 60
A47: 3. Создание отчетов | B47: Один отчет | C47: 1.5 | D47: 1 | F47: X | H47: =IF(E47="X",C47*D47*48, IF(F47="X", C47*D47*12, IF(G47="X",C47*D47*4))) -> 18
A48: 4. Настройка политик
A49: - Добавление новой политики | B49: Добавление одной политики | C49: 3 | D49: 3 | G49: X | H49: =IF(E49="X",C49*D49*48, IF(F49="X", C49*D49*12, IF(G49="X",C49*D49*4))) -> 36
A50: - Внесение изменений в существующие политики | B50: Актуализация одной политики | C50: 3 | D50: 1 | F50: X | H50: =IF(F50="X",C50*D50*48, IF(E50="X", C50*D50*12, IF(G50="X",C50*D50*4))) -> 144
A51: 5. Масштабирование | B51: Одна консультация | C51: 0.5 | D51: 2 | G51: X | H51: =IF(E51="X",C51*D51*48, IF(F51="X", C51*D51*12, IF(G51="X",C51*D51*4))) -> 4
A52: 6. Обновление ПО | B52: Одна консультация | C52: 4 | D52: 1 | G52: X | H52: =IF(E52="X",C52*D52*48, IF(F52="X", C52*D52*12, IF(G52="X",C52*D52*4))) -> 16
A53: 7. Контроль целостности контейнеров | B53: Актуализация одной политики | C53: 1 | D53: 1 | G53: X | H53: =IF(E53="X",C53*D53*48, IF(F53="X", C53*D53*12, IF(G53="X",C53*D53*4))) -> 4
A54: Итого (Ч) для Kyverno: | H54: =SUM(H44:H47,H49:H53) -> 474
A55: Итого (Ч-Д) для Kyverno: | H55: =H54/8 -> 59.25
A56: Итого (FTE) для Kyverno: | H56: =H54/K14 -> 0.23987854
A57: Cilium
A58: 1. Контроль корректности текущих настроек и конфигурации
A59: - Контроль корректности настроек | B59: Одна операция | C59: 0.25 | D59: 5 | E59: X | H59: =IF(E59="X",C59*D59*48, IF(F59="X", C59*D59*48, IF(G59="X",C59*D59*12))) -> 60
A60: - Корректировка настроек при необходимости | B60: Одна операция | C60: 2 | D60: 1 | G60: X | H60: =IF(E60="X",C60*D60*48, IF(F60="X", C60*D60*48, IF(G60="X",C60*D60*12))) -> 24
A61: 2. Проверка корректности резервного копирования | B61: Контроль создания РК | C61: 0.25 | D61: 5 | E61: X | H61: =IF(E61="X",C61*D61*48, IF(F61="X", C61*D61*12, IF(G61="X",C61*D61*4))) -> 60
A62: 3. Внесение изменений в настройки политик
A63: - Добавление новой политики | B63: Добавление одной политики | C63: 2 | D63: 2 | F63: X | H63: =IF(E63="X",C63*D63*48, IF(F63="X", C63*D63*48, IF(G63="X",C63*D63*12))) -> 192
A64: - Внесение изменений в существующие политики | B64: Актуализация одной сетевой политики | C64: 2 | D64: 2 | F64: X | H64: =IF(E64="X",C64*D64*48, IF(F64="X", C64*D64*48, IF(G64="X",C64*D64*12))) -> 192
A65: 4. Масштабирование | B65: Одна консультация | C65: 2 | D65: 1 | G65: X | H65: =IF(E65="X",C65*D65*48, IF(F65="X", C65*D65*48, IF(G65="X",C65*D65*12))) -> 24
A66: 5. Обновление ПО | B66: Одна консультация | C66: 3 | D66: 1 | G66: X | H66: =IF(E66="X",C66*D66*48, IF(F66="X", C66*D66*48, IF(G66="X",C66*D66*12))) -> 36
A67: Итого (Ч) для Cilium: | H67: =SUM(H59:H61,H63:H66) -> 588
A68: Итого (Ч-Д) для Cilium: | H68: =H67/8 -> 73.5
A69: Итого (FTE) для Cilium: | H69: =H67/K14 -> 0.29757085
A70: Политики аудита Kubernetes
A71: 1. Контроль корректности текущих настроек и конфигурации
A72: - Контроль корректности настроек | B72: Одна операция | C72: 0.25 | D72: 5 | E72: X | H72: =IF(E72="X",C72*D72*48, IF(F72="X", C72*D72*48, IF(G72="X",C72*D72*12))) -> 60
A73: - Корректировка настроек при необходимости | B73: Одна операция | C73: 2 | D73: 1 | G73: X | H73: =IF(E73="X",C73*D73*48, IF(F73="X", C73*D73*48, IF(G73="X",C73*D73*12))) -> 24
A74: 2. Проверка корректности резервного копирования | B74: Контроль создания РК | C74: 0.25 | D74: 2 | F74: X | H74: =IF(E74="X",C74*D74*48, IF(F74="X", C74*D74*48, IF(G74="X",C74*D74*12))) -> 24
A75: 3. Внесение изменений в настройки политик | B75: Актуализация политики аудита | C75: 2 | D75: 2 | F75: X | H75: =IF(E75="X",C75*D75*48, IF(F75="X", C75*D75*48, IF(G75="X",C75*D75*12))) -> 192
A76: 4. Масштабирование | B76: Одна консультация | C76: 0.5 | D76: 1 | G76: X | H76: =IF(E76="X",C76*D76*48, IF(F76="X", C76*D76*48, IF(G76="X",C76*D76*12))) -> 6
A77: 5. Анализ событий аудита | B77: Одна операция | C77: 1 | D77: 5 | E77: X | H77: =IF(E77="X",C77*D77*48, IF(F77="X", C77*D77*48, IF(G77="X",C77*D77*12))) -> 240
A78: 6. Подготовка отчетов | B78: Один отчет | C78: 1 | D78: 1 | F78: X | H78: =IF(E78="X",C78*D78*48, IF(F78="X", C78*D78*48, IF(G78="X",C78*D78*12))) -> 48
A79: Итого (Ч) для политик аудита Kubernetes: | H79: =SUM(H71:H74,H75:H78) -> 594
A80: Итого (Ч-Д) для политик аудита Kubernetes: | H80: =H79/8 -> 74.25
A81: Итого (FTE) для политик аудита Kubernetes: | H81: =H79/K14 -> 0.30060729
A82: Falco
A83: 1. Контроль корректности текущих настроек и конфигурации
A84: - Контроль корректности настроек | B84: Одна операция | C84: 1 | D84: 5 | E84: X | H84: =IF(E84="X",C84*D84*48, IF(F84="X", C84*D84*48, IF(G84="X",C84*D84*12))) -> 240
A85: - Корректировка настроек при необходимости | B85: Одна операция | C85: 2 | D85: 2 | F85: X | H85: =IF(E85="X",C85*D85*48, IF(F85="X", C85*D85*48, IF(G85="X",C85*D85*12))) -> 192
A86: 2. Внесение изменений в настройки политик
A87: - Добавление новой политики | B87: Добавление одной политики | C87: 2 | D87: 2 | F87: X | H87: =IF(E87="X",C87*D87*48, IF(F87="X", C87*D87*48, IF(G87="X",C87*D87*12))) -> 192
A88: - Внесение изменений в существующие политики | B88: Актуализация политики Falco | C88: 2 | D88: 8 | F88: X | H88: =IF(E88="X",C88*D88*48, IF(F88="X", C88*D88*48, IF(G88="X",C88*D88*12))) -> 768
A89: 3. Проверка корректности резервного копирования | B89: Одна операция | C89: 0.25 | D89: 2 | F89: X | H89: =IF(E89="X",C89*D89*48, IF(F89="X", C89*D89*48, IF(G89="X",C89*D89*12))) -> 24
A90: 4. Масштабирование | B90: Одна консультация | C90: 1 | D90: 2 | G90: X | H90: =IF(E90="X",C90*D90*48, IF(F90="X", C90*D90*48, IF(G90="X",C90*D90*12))) -> 24
A91: 5. Обновление | B91: Одна консультация | C91: 8 | D91: 1 | G91: X | H91: =IF(E91="X",C91*D91*48, IF(F91="X", C91*D91*48, IF(G91="X",C91*D91*12))) -> 96
A92: 6. Анализ событий аудита | B92: Одна операция | C92: 1 | D92: 5 | E92: X | H92: =IF(E92="X",C92*D92*48, IF(F92="X", C92*D92*48, IF(G92="X",C92*D92*12))) -> 240
A93: 7. Подготовка отчетов | B93: Один отчет | C93: 1 | D93: 1 | F93: X | H93: =IF(E93="X",C93*D93*48, IF(F93="X", C93*D93*48, IF(G93="X",C93*D93*12))) -> 48
A94: Итого (Ч) для политик аудита Falco: | H94: =SUM(H84:H85,H87:H88,H89:H93) -> 1824
A95: Итого (Ч-Д) для политик аудита Falco: | H95: =H94/8 -> 228
A96: Итого (FTE) для политик аудита Falco: | H96: =H94/K14 -> 0.92307692
A97: OPA
A98: 1. Контроль корректности текущих настроек и конфигурации
A99: - Контроль корректности настроек | B99: Одна операция | C99: 2 | D99: 5 | E99: X | H99: =IF(E99="X",C99*D99*48, IF(F99="X", C99*D99*48, IF(G99="X",C99*D99*12))) -> 480
A100: - Корректировка настроек при необходимости | B100: Одна операция | C100: 2 | D100: 2 | F100: X | H100: =IF(E100="X",C100*D100*48, IF(F100="X", C100*D100*48, IF(G100="X",C100*D100*12))) -> 192
...

Sheet PT TableTop_mapping
A1: Стадия | B1: Процесс | C1: Практика | D1: Задача | E1: ID | F1: Требования из DAF | G1: Выполнение по DAF | H1: Подсчет требований | I1: Комментарий | L1: Замаплено | M1: Всего требований | N1: % Маппинга на DAF
A2: PreStageSDL | B2: Планирование | C2: Стратегия SSDL | D2: Определение текущего и целевого состояния | E2: SSDL1 | L2: =COUNTA(H2:H238) -> 74 | M2: =COUNTA(E2:E238) -> 96 | N2: =(L2/M2)*100 -> 77.083333
D3: Определение перечня внедряемых практик | E3: SSDL2
D4: Разработка дорожной карты | E4: SSDL3
D5: Тиражирование практик безопасной разработки | E5: SSDL4
D6: Корректировка стратегии SSDL | E6: SSDL5
C7: Организационно-распорядительная документация | D7: Политика безопасной разработки | E7: OAD1
D8: Категоризация ИС | E8: OAD2 | F8: P-REQ-TM-1-2 | G8: =Практики!F308 -> Не заполнено | H8: 0 | I8: =Практики!Q308 -> 0
F9: P-REQ-TM-2-3 | G9: =Практики!F312 -> Не заполнено | I9: =Практики!Q312 -> 0
D10: Регламент безопасной разработки | E10: OAD3 | F10: P-ROLE-RESP-2-3 | G10: =Практики!F399 -> Не заполнено | H10: 0 | I10: =Практики!Q399 -> 0
D11: Документирование процесса | E11: OAD4
D12: Контроль соблюдения правил ОРД | E12: OAD5 | F12: P-MET-EX-3-2 | G12: =Практики!F377 -> Не заполнено | H12: 0 | I12: =Практики!Q377 -> 0
B13: Проектирование архитектуры | C13: Модель угроз и требования | D13: Общая модель угроз | E13: TMR1 | F13: P-REQ-TM-0-1 | G13: =Практики!F306 -> Не заполнено | H13: 0 | I13: =Практики!Q306 -> 0
D14: Моделирование угроз в ЖЦ ПО | E14: TMR2 | F14: P-REQ-TM-0-1 | G14: =Практики!F306 -> Не заполнено | H14: 0 | I14: =Практики!Q306 -> 0
F15: P-REQ-TM-1-3 | G15: =Практики!F309 -> Не заполнено | I15: =Практики!Q309 -> 0
F16: P-REQ-TM-2-1 | G16: =Практики!F310 -> Не заполнено | I16: =Практики!Q310 -> 0
F17: P-REQ-TM-2-2 | G17: =Практики!F311 -> Не заполнено | I17: =Практики!Q311 -> 0
F18: P-REQ-TM-3-3 | G18: =Практики!F315 -> Не заполнено | I18: =Практики!Q315 -> 0
D19: Чек-лист внешних регуляторных требований | E19: TMR3 | F19: P-REQ-TM-1-1 | G19: =Практики!F307 -> Не заполнено | H19: 0 | I19: =Практики!Q307 -> 0
D20: Требования к инфраструктуре и ПО | E20: TMR4 | F20: P-REQ-RD-1-1 | G20: =Практики!F318 -> Не заполнено | H20: 0 | I20: =Практики!Q318 -> 0
F21: P-REQ-RD-2-2 | G21: =Практики!F321 -> Не заполнено | I21: =Практики!Q321 -> 0
D22: Меры митигации | E22: TMR5 | F22: P-REQ-RD-3-2 | G22: =Практики!F324 -> Не заполнено | H22: 0 | I22: =Практики!Q324 -> 0
D23: Периодический пересмотр требований | E23: TMR6 | F23: P-REQ-RD-2-1 | G23: =Практики!F320 -> Не заполнено | H23: 0 | I23: =Практики!Q320 -> 0
C24: Риски и метрики | D24: Выбор метрик | E24: RM1 | F24: P-MET-SET-0-1 | G24: =Практики!F368 -> Не заполнено | H24: 0 | I24: =Практики!Q368 -> 0
D25: Оценка рисков | E25: RM2 | F25: P-REQ-RD-3-2 | G25: =Практики!F324 -> Не заполнено | H25: 0 | I25: =Практики!Q324 -> 0
D26: Определение подходов к сбору метрик | E26: RM3 | F26: P-MET-SET-2-1 | G26: =Практики!F369 -> Не заполнено | H26: 0 | I26: =Практики!Q369 -> 0
F27: P-MET-SET-2-2 | G27: =Практики!F370 -> Не заполнено | I27: =Практики!Q370 -> 0
D28: Анализ метрик | E28: RM4 | F28: P-MET-SET-3-1 | G28: =Практики!F371 -> Не заполнено | H28: 0 | I28: =Практики!Q371 -> 0
C29: Технический проект | D29: Определение технологического стека | E29: TP1
D30: Порядок контроля используемого ПО | E30: TP2 | F30: T-ADI-DEP-1-1 | G30: =Практики!F4 -> Не заполнено | H30: 0 | I30: =Практики!Q4 -> 0
D31: Определение CI/CD-конвейера | E31: TP3 | F31: T-DEV-BLD-3-1 | G31: =Практики!F50 -> Не заполнено | H31: 0 | I31: =Практики!Q50 -> 0
F32: T-DEV-CICD-4-1 | G32: =Практики!F103 -> Не заполнено | I32: =Практики!Q103 -> 0
D33: Формирование безопасной архитектуры | E33: TP4 | F33: P-REQ-RD-3-3 | G33: =Практики!F325 -> Не заполнено | H33: 0 | I33: =Практики!Q325 -> 0
B34: Безопасность инфраструктуры | C34: Разграничение доступа | D34: Сегментация сети | E34: AC1 | F34: T-DEV-BLD-1-3 | G34: =Практики!F47 -> Не заполнено | H34: 0 | I34: =Практики!Q47 -> 0
F35: T-DEV-SCM-3-4 | G35: =Практики!F71 -> Не заполнено | I35: =Практики!Q71 -> 0
F36: T-PROD-NETWORK-0-1 | G36: =Практики!F258 -> Не заполнено | I36: =Практики!Q258 -> 0
F37: T-PROD-NETWORK-1-1 | G37: =Практики!F259 -> Не заполнено | I37: =Практики!Q259 -> 0
F38: T-PROD-NETWORK-1-2 | G38: =Практики!F260 -> Не заполнено | I38: =Практики!Q260 -> 0
D39: Ролевая модель | E39: AC2 | F39: T-ADI-ART-1-2 | G39: =Практики!F18 -> Не заполнено | H39: 0 | I39: =Практики!Q18 -> 0
F40: T-ADI-ART-1-4 | G40: =Практики!F20 -> Не заполнено | I40: =Практики!Q20 -> 0
F41: T-DEV-COMP-1-2 | G41: =Практики!F34 -> Не заполнено | I41: =Практики!Q34 -> 0
F42: T-DEV-BLD-1-1 | G42: =Практики!F45 -> Не заполнено | I42: =Практики!Q45 -> 0
F43: T-DEV-SCM-1-1 | G43: =Практики!F55 -> Не заполнено | I43: =Практики!Q55 -> 0
F44: T-DEV-SCM-1-2 | G44: =Практики!F56 -> Не заполнено | I44: =Практики!Q56 -> 0
F45: T-DEV-SCM-1-3 | G45: =Практики!F57 -> Не заполнено | I45: =Практики!Q57 -> 0
F46: T-DEV-SCM-1-6 | G46: =Практики!F60 -> Не заполнено | I46: =Практики!Q60 -> 0
F47: T-DEV-SRC-1-3 | G47: =Практики!F78 -> Не заполнено | I47: =Практики!Q78 -> 0
F48: T-DEV-CICD-0-1 | G48: =Практики!F94 -> Не заполнено | I48: =Практики!Q94 -> 0
F49: T-PROD-ACCESS-1-4 | G49: =Практики!F252 -> Не заполнено | I49: =Практики!Q252 -> 0
F50: T-PROD-ACCESS-2-1 | G50: =Практики!F254 -> Не заполнено | I50: =Практики!Q254 -> 0
C51: Безопасность конфигураций | D51: Харденинг | E51: CNFG1 | F51: T-ADI-DEP-1-4 | G51: =Практики!F7 -> Не заполнено | H51: 0 | I51: =Практики!Q7 -> 0
F52: T-ADI-ART-1-4 | G52: =Практики!F20 -> Не заполнено | I52: =Практики!Q20 -> 0
F53: T-ADI-ART-1-5 | G53: =Практики!F21 -> Не заполнено | I53: =Практики!Q21 -> 0
F54: T-DEV-COMP-0-1 | G54: =Практики!F32 -> Не заполнено | I54: =Практики!Q32 -> 0
F55: T-DEV-BLD-0-1 | G55: =Практики!F44 -> Не заполнено | I55: =Практики!Q44 -> 0
F56: T-DEV-BLD-3-2 | G56: =Практики!F51 -> Не заполнено | I56: =Практики!Q51 -> 0
F57: T-PREPROD-VULN-1-2 | G57: =Практики!F199 -> Не заполнено | I57: =Практики!Q199 -> 0
F58: T-PREPROD-VULN-2-3 | G58: =Практики!F202 -> Не заполнено | I58: =Практики!Q202 -> 0
F59: T-PREPROD-VULN-3-2 | G59: =Практики!F204 -> Не заполнено | I59: =Практики!Q204 -> 0
F60: T-PROD-NETWORK-2-1 | G60: =Практики!F261 -> Не заполнено | I60: =Практики!Q261 -> 0
F61: T-PROD-VULN-2-3 | G61: =Практики!F273 -> Не заполнено | I61: =Практики!Q273 -> 0
F62: T-PROD-VULN-3-2 | G62: =Практики!F275 -> Не заполнено | I62: =Практики!Q275 -> 0
F63: P-REQ-STDR-App-2-1 | G63: =Практики!F335 -> Не заполнено | I63: =Практики!Q335 -> 0
F64: P-REQ-STDR-App-3-1 | G64: =Практики!F336 -> Не заполнено | I64: =Практики!Q336 -> 0
F65: P-REQ-STDR-Infr-2-1 | G65: =Практики!F342 -> Не заполнено | I65: =Практики!Q342 -> 0
F66: P-REQ-STDR-Infr-3-1 | G66: =Практики!F344 -> Не заполнено | I66: =Практики!Q344 -> 0
D67: Учёт рисков при настройке инфраструктуры | E67: CNFG2 | F67: P-REQ-STDR-App-4-1 | G67: =Практики!F338 -> Не заполнено | H67: 0 | I67: =Практики!Q338 -> 0
F68: P-REQ-STDR-Infr-4-1 | G68: =Практики!F347 -> Не заполнено | I68: =Практики!Q347 -> 0
F69: P-DEFECT-MNG-4-1 | G69: =Практики!F357 -> Не заполнено | I69: =Практики!Q357 -> 0
A70: MainStageSDL | B70: Разработка | C70: Безопасное программирование | D70: Контроль ТЗ | E70: SC1
D71: Регламент безопасного кодирования | E71: SC2 | F71: P-EDU-KB-0-1 | G71: =Практики!F295 -> Не заполнено | H71: 0 | I71: =Практики!Q295 -> 0
F72: P-EDU-KB-3-1 | G72: =Практики!F299 -> Не заполнено | I72: =Практики!Q299 -> 0
F73: P-ROLE-SC-2-2 | G73: =Практики!F385 -> Не заполнено | I73: =Практики!Q385 -> 0
F74: P-ROLE-SC-3-3 | G74: =Практики!F388 -> Не заполнено | I74: =Практики!Q388 -> 0
F75: P-ROLE-SC-4-1 | G75: =Практики!F390 -> Не заполнено | I75: =Практики!Q390 -> 0
F76: P-ROLE-SC-4-3 | G76: =Практики!F392 -> Не заполнено | I76: =Практики!Q392 -> 0
F77: P-ROLE-RESP-2-3 | G77: =Практики!F399 -> Не заполнено | I77: =Практики!Q399 -> 0
D78: Рефакторинг | E78: SC3
C79: Использование безопасных компонент | D79: Использование инструментов OSA | E79: OSS1 | F79: T-CODE-SC-0-1 | G79: =Практики!F131 -> Не заполнено | H79: 0 | I79: =Практики!Q131 -> 0
D80: Хранилище доверенных артефактов | E80: OSS2 | F80: T-ADI-ART-1-1 | G80: =Практики!F17 -> Не заполнено | H80: 0 | I80: =Практики!Q17 -> 0
D81: Анализ образов | E81: OSS3 | F81: T-CODE-IMG-1-2 | G81: =Практики!F146 -> Не заполнено | H81: 0 | I81: =Практики!Q146 -> 0
D82: Проверка лицензионной чистоты | E82: OSS4 | F82: T-CODE-SC-2-5 | G82: =Практики!F138 -> Не заполнено | H82: 0 | I82: =Практики!Q138 -> 0
C83: Статический анализ кода | D83: Линтеры | E83: SPA1 | F83: T-PREPROD-MANSEC-0-1 | G83: =Практики!F209 -> Не заполнено | H83: 0 | I83: =Практики!Q209 -> 0
F84: T-PREPROD-MANSEC-1-1 | G84: =Практики!F210 -> Не заполнено | I84: =Практики!Q210 -> 0
F85: T-PREPROD-MANSEC-2-1 | G85: =Практики!F211 -> Не заполнено | I85: =Практики!Q211 -> 0
D86: Код-ревью | E86: SPA2 | F86: P-ROLE-SC-4-3 | G86: =Практики!F392 -> Не заполнено | H86: 0 | I86: =Практики!Q392 -> 0
D87: Использование инструментов SAST | E87: SPA3 | F87: T-CODE-SST-0-1 | G87: =Практики!F119 -> Не заполнено | H87: 0 | I87: =Практики!Q119 -> 0
F88: T-CODE-SST-2-4 | G88: =Практики!F125 -> Не заполнено | I88: =Практики!Q125 -> 0
D89: Кастомные правила SAST | E89: SPA4 | F89: T-CODE-SST-2-2 | G89: =Практики!F123 -> Не заполнено | H89: 0 | I89: =Практики!Q123 -> 0
F90: T-CODE-SST-3-2 | G90: =Практики!F127 -> Не заполнено | I90: =Практики!Q127 -> 0
D91: SAST в пайплайне | E91: SPA5 | F91: T-CODE-SST-2-3 | G91: =Практики!F124 -> Не заполнено | H91: 0 | I91: =Практики!Q124 -> 0
F92: P-DEFECT-MNG-3-3 | G92: =Практики!F356 -> Не заполнено | I92: =Практики!Q356 -> 0
D93: Оркестрация SAST | E93: SPA6 | F93: P-DEFECT-CNS-1-2 | G93: =Практики!F360 -> Не заполнено | H93: 0 | I93: =Практики!Q360 -> 0
D94: Детектирование секретов | E94: SPA7 | F94: T-CODE-SECDN-0-1 | G94: =Практики!F154 -> Не заполнено | H94: 0 | I94: =Практики!Q154 -> 0
F95: T-CODE-SECDN-1-3 | G95: =Практики!F157 -> Не заполнено | I95: =Практики!Q157 -> 0
F96: T-CODE-SECDN-2-2 | G96: =Практики!F160 -> Не заполнено | I96: =Практики!Q160 -> 0
C97: Управление изменениями | D97: Система контроля версий | E97: GF1 | F97: T-DEV-SRC-1-1 | G97: =Практики!F76 -> Не заполнено | H97: 0 | I97: =Практики!Q76 -> 0
F98: T-DEV-SRC-1-2 | G98: =Практики!F77 -> Не заполнено | I98: =Практики!Q77 -> 0
D99: Организация распределенного рабочего процесса | E99: GF2
B100: Сборка | C100: Компонентный анализ | D100: Использование инструментов SCA | E100: SCA1 | F100: T-CODE-SC-0-1 | G100: =Практики!F130 -> Не заполнено | H100: 0 | I100: =Практики!Q130 -> 0
...

Sheet SAMM_mapping
C1: Level | D1: Требование | E1: ID | F1: Требования из DAF | G1: Выполнение по DAF | H1: Комментарий | I1: Подсчет требований | K1: Замаплено | L1: Всего требований | M1: % Маппинга на DAF
B2: Governance | K2: =COUNTA(I4:I178) -> 57 | L2: =COUNTA(E4:E10,E12:E17,E19:E31,E34:E41,E43:E51,E53:E58,E61:E77,E79:E90,E92:E102,E105:E110,E112:E121,E123:E145,E148:E154,E156:E167,E169:E178) -> 90 | M2: =(K2/L2)*100 -> 63.333333
B3: Strategy&Metrics
B4: Create and Promote | C4: 1 | D4: Do you understand the enterprise-wide risk appetite for your applications? | E4: SM-A-1 | F4: =Практики!C314 -> P-REQ-TM-3-2 | G4: =Практики!F314 -> Не заполнено | H4: =Практики!Q314 -> 0 | I4: 0
C5: 2 | D5: Do you have a strategic plan for application security and use it to make decisions? | E5: SM-A-2 | F5: =Практики!C400 -> P-ROLE-RESP-2-4 | G5: =Практики!F402 -> Не заполнено | H5: =Практики!Q402 -> 0 | I5: 0
C6: 3 | D6: Do you regularly review and update the Strategic Plan for Application Security? | E6: SM-A-3 | F6: =Практики!C402 -> P-ROLE-RESP-3-2 | G6: =Практики!F402 -> Не заполнено | H6: =Практики!Q403 -> 0 | I6: 0
B7: Measure and Improve | C7: 1 | D7: Do you use a set of metrics to measure the effectiveness and efficiency of the application security program across applications? | E7: SM-B-1 | F7: =Практики!C369 -> P-MET-SET-2-1 | G7: =Практики!F369 -> Не заполнено | H7: =Практики!Q369 -> 0 | I7: 0
C8: 2 | D8: Did you define Key Performance Indicators (KPI) from available application security metrics? | E8: SM-B-2 | F8: =Практики!C370 -> P-MET-SET-2-2 | G8: =Практики!F370 -> Не заполнено | H8: =Практики!Q370 -> 0 | I8: 0
C9: 3 | D9: Do you update the Application Security strategy and roadmap based on application security metrics and KPIs? | E9: SM-B-3 | F9: P-MET-SET-3-2 | G9: =Практики!F372 -> Не заполнено | H9: =Практики!Q372 -> 0 | I9: 0
F10: =Практики!C373 -> P-MET-EX-0-1 | G10: =Практики!F373 -> Не заполнено | H10: =Практики!Q373 -> 0
B11: Policy & Compliance
B12: Policy and Standards | C12: 1 | D12: Do you have and apply a common set of policies and standards throughout your organization? | E12: PC-A-1 | F12: =Практики!C399 -> P-ROLE-RESP-2-3 | G12: =Практики!F399 -> Не заполнено | H12: =Практики!Q399 -> 0 | I12: 0
C13: 2 | D13: Do you publish the organization's policies as test scripts or run-books for easy interpretation by development teams? | E13: PC-A-2 | F13: =Практики!C194 -> T-PREPROD-SECTEST-2-1 | G13: =Практики!F194 -> Не заполнено | H13: =Практики!Q194 -> 0 | I13: 0
C14: 3 | D14: Do you regularly report on policy and standard compliance, and use that information to guide compliance improvement efforts? | E14: PC-A-3 | F14: =Практики!C278 -> T-PROD-VULN-4-1 | G14: =Практики!F278 -> Не заполнено | H14: =Практики!Q278 -> 0 | I14: 0
B15: Compliance Management | C15: 1 | D15: Do you have a complete picture of your external compliance obligations? | E15: PC-B-1
C16: 2 | D16: Do you have a standard set of security requirements and verification procedures addressing the organization's external compliance obligations? | E16: PC-B-2
C17: 3 | D17: Do you regularly report on adherence to external compliance obligations and use that information to guide efforts to close compliance gaps? | E17: PC-B-3
B18: Education & Guidance
B19: Training and Awareness | C19: 1 | D19: Do you require employees involved with application development to take SDLC training? | E19: EG-A-1 | F19: =Практики!C285 -> P-EDU-AWR-0-1 | G19: =Практики!F285 -> Не заполнено | H19: =Практики!Q285 -> 0 | I19: 0
F20: =Практики!C286 -> P-EDU-AWR-1-1 | G20: =Практики!F286 -> Не заполнено | H20: =Практики!Q286 -> 0
C21: 2 | D21: Is training customized for individual roles such as developers, testers, or security champions? | E21: EG-A-2 | F21: =Практики!C232 -> T-PROD-PENTEST-4-2 | G21: =Практики!F232 -> Не заполнено | H21: =Практики!Q232 -> 0 | I21: 0
F22: =Практики!C290 -> P-EDU-AWR-2-3 | G22: =Практики!F290 -> Не заполнено | H22: =Практики!Q290 -> 0
F23: =Практики!C288 -> P-EDU-AWR-2-1 | G23: =Практики!F288 -> Не заполнено | H23: =Практики!Q288 -> 0
C24: 3 | D24: Have you implemented a Learning Management System or equivalent to track employee training and certification processes? | E24: EG-A-3 | F24: =Практики!C288 -> P-EDU-AWR-2-1 | G24: =Практики!F288 -> Не заполнено | H24: =Практики!Q288 -> 0 | I24: 0
F25: =Практики!C291 -> P-EDU-AWR-2-4 | G25: =Практики!F291 -> Не заполнено | H25: =Практики!Q291 -> 0
B26: Organization and Culture | C26: 1 | D26: Have you identified a Security Champion for each development team? | E26: EG-B-1 | F26: =Практики!C382 -> P-ROLE-SC-0-1 | G26: =Практики!F382 -> Не заполнено | H26: =Практики!Q382 -> 0 | I26: 0
F27: =Практики!C384 -> P-ROLE-SC-2-1 | G27: =Практики!F384 -> Не заполнено | H27: =Практики!Q384 -> 0
F28: =Практики!C388 -> P-ROLE-SC-3-3 | G28: =Практики!F388 -> Не заполнено | H28: =Практики!Q388 -> 0
C29: 2 | D29: Does the organization have a Secure Software Center of Excellence (SSCE)? | E29: EG-B-2 | F29: =Практики!C395 -> P-ROLE-RESP-1-1 | G29: =Практики!F395 -> Не заполнено | H29: =Практики!Q395 -> 0 | I29: 0
C30: 3 | D30: Is there a centralized portal where developers and application security professionals from different teams and business units are able to communicate and share information? | E30: EG-B-3 | F30: =Практики!C292 -> P-EDU-AWR-3-1 | G30: =Практики!F292 -> Не заполнено | H30: =Практики!Q292 -> 0 | I30: 0
F31: =Практики!C295 -> P-EDU-KB-0-1 | G31: =Практики!F295 -> Не заполнено | H31: =Практики!Q295 -> 0
B32: Design
B33: Threat Assessment
B34: Application Risk Profile | C34: 1 | D34: Do you classify applications according to business risk based on a simple and predefined set of questions? | E34: TA-A-1 | F34: =Практики!C308 -> P-REQ-TM-1-2 | G34: =Практики!F308 -> Не заполнено | H34: =Практики!Q308 -> 0 | I34: 0
F35: =Практики!C309 -> P-REQ-TM-1-3 | G35: =Практики!F309 -> Не заполнено | H35: =Практики!Q309 -> 0
C36: 2 | D36: Do you use centralized and quantified application risk profiles to evaluate business risk? | E36: TA-A-2 | F36: =Практики!C312 -> P-REQ-TM-2-3 | G36: =Практики!F312 -> Не заполнено | H36: =Практики!Q312 -> 0 | I36: 0
C37: 3 | D37: Do you regularly review and update the risk profiles for your applications? | E37: TA-A-3
B38: Threat Modeling | C38: 1 | D38: Do you identify and manage architectural design flaws with threat modeling? | E38: TA-B-1 | F38: =Практики!C306 -> P-REQ-TM-0-1 | G38: =Практики!F306 -> Не заполнено | H38: =Практики!Q306 -> 0 | I38: 0
C39: 2 | D39: Do you use a standard methodology, aligned with your application risk levels? | E39: TA-B-2 | F39: =Практики!C314 -> P-REQ-TM-3-2 | G39: =Практики!F314 -> Не заполнено | H39: =Практики!Q314 -> 0 | I39: 0
F40: =Практики!C323 -> P-REQ-RD-3-1 | G40: =Практики!F323 -> Не заполнено | H40: =Практики!Q323 -> 0
C41: 3 | D41: Do you regularly review and update the threat modeling methodology for your applications? | E41: TA-B-3 | F41: =Практики!C315 -> P-REQ-TM-3-3 | G41: =Практики!F315 -> Не заполнено | H41: =Практики!Q315 -> 0 | I41: 0
B42: Security Requirements
B43: Software Requirements | C43: 1 | D43: Do project teams specify security requirements during development? | E43: SR-A-1 | F43: =Практики!C317 -> P-REQ-RD-0-1 | G43: =Практики!F317 -> Не заполнено | H43: =Практики!Q317 -> 0 | I43: 0
C44: 2 | D44: Do you define, structure, and include prioritization in the artifacts of the security requirements gathering process? | E44: SR-A-2 | F44: =Практики!C318 -> P-REQ-RD-1-1 | G44: =Практики!F318 -> Не заполнено | H44: =Практики!Q318 -> 0 | I44: 0
F45: =Практики!C319 -> P-REQ-RD-1-2 | G45: =Практики!F319 -> Не заполнено | H45: =Практики!Q319 -> 0
F46: =Практики!C321 -> P-REQ-RD-2-2 | G46: =Практики!F321 -> Не заполнено | H46: =Практики!Q321 -> 0
F47: =Практики!C327 -> P-REQ-CR-0-1 | G47: =Практики!F327 -> Не заполнено | H47: =Практики!Q327 -> 0
C48: 3 | D48: Do you use a standard requirements framework to streamline the elicitation of security requirements? | E48: SR-A-3
B49: Supplier Security | C49: 1 | D49: Do stakeholders review vendor collaborations for security requirements and methodology? | E49: SR-B-1
C50: 2 | D50: Do vendors meet the security responsibilities and quality measures of service level agreements defined by the organization? | E50: SR-B-2
C51: 3 | D51: Are vendors aligned with standard security controls and software development tools and processes that the organization utilizes? | E51: SR-B-3
B52: Secure Architecture
B53: Architecture Design | C53: 1 | D53: Do teams use security principles during design? | E53: SA-A-1 | F53: =Практики!C66 -> T-DEV-SCM-2-5 | G53: =Практики!F66 -> Не заполнено | H53: =Практики!Q66 -> 0 | I53: 0
C54: 2 | D54: Do you use shared security services during design? | E54: SA-A-2
C55: 3 | D55: Do you base your design on available reference architectures? | E55: SA-A-3 | F55: =Практики!C325 -> P-REQ-RD-3-3 | G55: =Практики!F325 -> Не заполнено | H55: =Практики!Q325 -> 0 | I55: 0
B56: Technology Management | C56: 1 | D56: Do you evaluate the security quality of important technologies used for development? | E56: SA-B-1 | F56: =Практики!C8 -> T-ADI-DEP-1-5 | G56: =Практики!F8 -> Не заполнено | H56: =Практики!Q8 -> 0 | I56: 0
C57: 2 | D57: Do you have a list of recommended technologies for the organization? | E57: SA-B-2 | F57: =Практики!C16 -> T-ADI-ART-0-1 | G57: =Практики!F16 -> Не заполнено | H57: =Практики!Q16 -> 0 | I57: 0
C58: 3 | D58: Do you enforce the use of recommended technologies within the organization? | E58: SA-B-3
B59: Implementation
B60: Secure Build
C61: 1 | D61: Is your full build process formally described? | E61: SB-A-1 | F61: =Практики!C44 -> T-DEV-BLD-0-1 | G61: =Практики!F44 -> Не заполнено | H61: =Практики!Q44 -> 0 | I61: 0
F62: =Практики!C51 -> T-DEV-BLD-3-2 | G62: =Практики!F51 -> Не заполнено | H62: =Практики!Q51 -> 0
F63: =Практики!C94 -> T-DEV-CICD-0-1 | G63: =Практики!F94 -> Не заполнено | H63: =Практики!Q94 -> 0
F64: =Практики!C136 -> T-CODE-SC-2-3 | G64: =Практики!F136 -> Не заполнено | H64: =Практики!Q136 -> 0
C65: 2 | D65: Is the build process fully automated? | E65: SB-A-2 | F65: =Практики!C47 -> T-DEV-BLD-1-3 | G65: =Практики!F47 -> Не заполнено | H65: =Практики!Q47 -> 0 | I65: 0
F66: =Практики!C51 -> T-DEV-BLD-3-2 | G66: =Практики!F51 -> Не заполнено | H66: =Практики!Q51 -> 0
C67: 3 | D67: Do you enforce automated security checks in your build processes? | E67: SB-A-3 | F67: =Практики!C48 -> T-DEV-BLD-1-4 | G67: =Практики!F48 -> Не заполнено | H67: =Практики!Q48 -> 0 | I67: 0
F68: =Практики!C330 -> P-REQ-CR-3-1 | G68: =Практики!F330 -> Не заполнено | H68: =Практики!Q330 -> 0
F69: =Практики!C356 -> P-DEFECT-MNG-3-3 | G69: =Практики!F356 -> Не заполнено | H69: =Практики!Q356 -> 0
F70: =Практики!C328 -> P-REQ-CR-1-1 | G70: =Практики!F328 -> Не заполнено | H70: =Практики!Q328 -> 0
B71: Software Dependencies | C71: 1 | D71: Do you have solid knowledge about dependencies you're relying on? | E71: SB-B-1 | F71: =Практики!C3 -> T-ADI-DEP-0-1 | G71: =Практики!F3 -> Не заполнено | H71: =Практики!Q3 -> 0 | I71: 0
F72: =Практики!C11 -> T-ADI-DEP-3-1 | G72: =Практики!F11 -> Не заполнено | H72: =Практики!Q11 -> 0
C73: 2 | D73: Do you handle 3rd party dependency risk by a formal process? | E73: SB-B-2 | F73: =Практики!C4 -> T-ADI-DEP-1-1 | G73: =Практики!F4 -> Не заполнено | H73: =Практики!Q4 -> 0 | I73: 0
F74: =Практики!C5 -> T-ADI-DEP-1-2 | G74: =Практики!F5 -> Не заполнено | H74: =Практики!Q5 -> 0
F75: =Практики!C10 -> T-ADI-DEP-2-2 | G75: =Практики!F10 -> Не заполнено | H75: =Практики!Q10 -> 0
F76: =Практики!C138 -> T-CODE-SC-2-5 | G76: =Практики!F138 -> Не заполнено | H76: =Практики!Q138 -> 0
C77: 3 | D77: Do you prevent build of software if it's affected by vulnerabilities in dependencies? | E77: SB-B-3 | F77: =Практики!C129 -> T-CODE-SST-4-1 | G77: =Практики!F129 -> Не заполнено | H77: =Практики!Q129 -> 0 | I77: 0
B78: Secure Deployment
B79: Deployment Process | C79: 1 | D79: Do you use repeatable deployment processes? | E79: SD-A-1
C80: 2 | D80: Are deployment processes automated and employing security checks? | E80: SD-A-2 | F80: =Практики!C330 -> P-REQ-CR-3-1 | G80: =Практики!F330 -> Не заполнено | H80: =Практики!Q330 -> 0 | I80: 0
F81: =Практики!C353 -> P-DEFECT-MNG-2-2 | G81: =Практики!F353 -> Не заполнено | H81: =Практики!Q353 -> 0
C82: 3 | D82: Do you consistently validate the integrity of deployed artifacts? | E82: SD-A-3
B83: Secret Management | C83: 1 | D83: Do you limit access to application secrets according to the least privilege principle? | E83: SD-B-1 | F83: =Практики!C36 -> T-DEV-SM-0-1 | G83: =Практики!F36 -> Не заполнено | H83: =Практики!Q36 -> 0 | I83: 0
F84: =Практики!C37 -> T-DEV-SM-1-1 | G84: =Практики!F37 -> Не заполнено | H84: =Практики!Q37 -> 0
F85: =Практики!C41 -> T-DEV-SM-3-1 | G85: =Практики!F41 -> Не заполнено | H85: =Практики!Q41 -> 0
C86: 2 | D86: Do you inject production secrets into configuration files during deployment? | E86: SD-B-2 | F86: =Практики!C39 -> T-DEV-SM-2-1 | G86: =Практики!F39 -> Не заполнено | H86: =Практики!Q39 -> 0 | I86: 0
F87: =Практики!C40 -> T-DEV-SM-2-2 | G87: =Практики!F40 -> Не заполнено | H87: =Практики!Q40 -> 0
F88: =Практики!C130 -> T-CODE-SC-0-1 | G88: =Практики!F130 -> Не заполнено | H88: =Практики!Q130 -> 0
F89: =Практики!C165 -> T-CODE-SECDN-4-1 | G89: =Практики!F165 -> Не заполнено | H89: =Практики!Q165 -> 0
C90: 3 | D90: Do you practice proper lifecycle management for application secrets? | E90: SD-B-3 | F90: =Практики!C42 -> T-DEV-SM-3-2 | G90: =Практики!F42 -> Не заполнено | H90: =Практики!Q42 -> 0 | I90: 0
B91: Defect Management
B92: Defect Tracking | C92: 1 | D92: Do you track all known security defects in accessible locations? | E92: DM-A-1
C93: 2 | D93: Do you keep an overview of the state of security defects across the organization? | E93: DM-A-2 | F93: =Практики!C134 -> T-CODE-SC-2-1 | G93: =Практики!F134 -> Не заполнено | H93: =Практики!Q134 -> 0 | I93: 0
F94: =Практики!C351 -> P-DEFECT-MNG-1-1 | G94: =Практики!F351 -> Не заполнено | H94: =Практики!Q351 -> 0
F95: =Практики!C352 -> P-DEFECT-MNG-2-1 | G95: =Практики!F352 -> Не заполнено | H95: =Практики!Q352 -> 0
F96: =Практики!C354 -> P-DEFECT-MNG-3-1 | G96: =Практики!F354 -> Не заполнено | H96: =Практики!Q354 -> 0
F97: =Практики!C357 -> P-DEFECT-MNG-4-1 | G97: =Практики!F357 -> Не заполнено | H97: =Практики!Q357 -> 0
F98: =Практики!C358 -> P-DEFECT-CNS-0-1 | G98: =Практики!F358 -> Не заполнено | H98: =Практики!Q358 -> 0
C99: 3 | D99: Do you enforce SLAs for fixing security defects? | E99: DM-A-3 | F99: =Практики!C355 -> P-DEFECT-MNG-3-2 | G99: =Практики!F355 -> Не заполнено | H99: =Практики!Q355 -> 0 | I99: 0
B100: Metrics and Feedback | C100: 1 | D100: Do you use basic metrics about recorded security defects to carry out quick win improvement activities? | E100: DM-B-1
...

Sheet DSOMM_mapping
A1: ID | B1: Dimension | C1: Sub Dimension | D1: Activity | E1: UUID | F1: DAF | G1: Статус выполнения | H1: Комментарий | I1: Подсчет требований | K1: Замаплено | L1: Всего требований | M1: % Маппинга на DAF
A2: 1 | B2: Build and Deployment | C2: Build | D2: Building and testing of artifacts in virtual environments | E2: a340f46b-6360-4cb8-847b-a0d3483d09d3 | K2: =COUNTA(I2:I256) -> 68 | L2: =COUNTA(A2:A256) -> 185 | M2: =(K2/L2)*100 -> 36.756757
A3: 2 | B3: Build and Deployment | C3: Build | D3: Pinning of artifacts | E3: f3c4971e-9f4d-4e59-8ed0-f0bdb6262477
A4: 3 | B4: Build and Deployment | C4: Build | D4: Defined build process | E4: f6f7737f-25a9-4317-8de2-09bf59f29b5b | F4: =Практики!C50 -> T-DEV-BLD-3-1 | G4: =Практики!F50 -> Не заполнено | H4: =Практики!Q50 -> 0 | I4: 0
F5: =Практики!C53 -> T-DEV-BLD-4-1 | G5: =Практики!F53 -> Не заполнено | H5: =Практики!Q53 -> 0
A6: 4 | B6: Build and Deployment | C6: Build | D6: SBOM of components | E6: 2858ac12-0179-40d9-9acf-1b839c030473 | F6: =Практики!C3 -> T-ADI-DEP-0-1 | G6: =Практики!F3 -> Не заполнено | H6: =Практики!Q3 -> 0 | I6: 0
F7: =Практики!C24 -> T-ADI-ART-3-1 | G7: =Практики!F24 -> Не заполнено | H7: =Практики!Q24 -> 0
A8: 5 | B8: Build and Deployment | C8: Build | D8: Signing of artifacts | E8: 5786959d-0c6f-46a6-8e1c-a32ff1a50222
A9: 6 | B9: Build and Deployment | C9: Build | D9: Signing of code | E9: 9f107927-61e9-4574-85ad-3f2b4bca8665
A10: 7 | B10: Build and Deployment | C10: Deployment | D10: Environment depending configuration parameters (secrets) | E10: df428c9d-efa0-4226-9f47-a15bb53f822b | F10: =Практики!C36 -> T-DEV-SM-0-1 | G10: =Практики!F36 -> Не заполнено | H10: =Практики!Q36 -> 0 | I10: 0
F11: =Практики!C37 -> T-DEV-SM-1-1 | G11: =Практики!F37 -> Не заполнено | H11: =Практики!Q37 -> 0
F12: =Практики!C39 -> T-DEV-SM-2-1 | G12: =Практики!F39 -> Не заполнено | H12: =Практики!Q39 -> 0
F13: =Практики!C215 -> T-PROD-SM-1-1 | G13: =Практики!F215 -> Не заполнено | H13: =Практики!Q215 -> 0
F14: =Практики!C217 -> T-PROD-SM-2-1 | G14: =Практики!F217 -> Не заполнено | H14: =Практики!Q217 -> 0
F15: =Практики!C41 -> T-DEV-SM-3-1 | G15: =Практики!F41 -> Не заполнено | H15: =Практики!Q41 -> 0
A16: 8 | B16: Build and Deployment | C16: Deployment | D16: Evaluation of the trust of used components | E16: 0de465a6-55a7-4343-af79-948bb5ff10ba
A17: 9 | B17: Build and Deployment | C17: Patch Management | D17: A patch policy is defined | E17: 99415139-6b50-441b-89e1-0aa59accd43d | F17: =Практики!C5 -> T-ADI-DEP-1-2 | G17: =Практики!F5 -> Не заполнено | H17: =Практики!Q5 -> 0 | I17: 0
F18: =Практики!C270 -> T-PROD-VULN-1-2 | G18: =Практики!F270 -> Не заполнено | H18: =Практики!Q270 -> 0
F19: =Практики!C199 -> T-PREPROD-VULN-1-2 | G19: =Практики!F199 -> Не заполнено | H19: =Практики!Q199 -> 0
A20: 10 | B20: Build and Deployment | C20: Patch Management | D20: Automated PRs for patches | E20: 8ae0b92c-10e0-4602-ba22-7524d6aed488 | F20: =Практики!C13 -> T-ADI-DEP-3-3 | G20: =Практики!F13 -> Не заполнено | H20: =Практики!Q13 -> 0 | I20: 0
A21: 11 | B21: Build and Deployment | C21: Deployment | D21: Rolling update on deployment | E21: 85d52588-f542-4225-a338-20dc22a5508d
A22: 12 | B22: Build and Deployment | C22: Patch Management | D22: Reduction of the attack surface | E22: 16e39c8f-5336-4001-88ed-a552d2447531
A23: 13 | B23: Build and Deployment | C23: Deployment | D23: Handover of confidential parameters | E23: 94a96f79-8bd6-4904-97c0-994ff88f176a
A24: 14 | B24: Build and Deployment | C24: Patch Management | D24: Automated deployment of automated PRs | E24: 08f27c26-2c6a-47fe-9458-5e88f188085d
A25: 15 | B25: Build and Deployment | C25: Patch Management | D25: Automated merge of automated PRs | E25: f2594f8f-1cd6-45f9-af29-eaf3315698eb
A26: 16 | B26: Build and Deployment | C26: Patch Management | D26: Nightly build of images (base images) | E26: 34869eaf-f2e1-4926-b0bd-28c43402f057
A27: 17 | B27: Build and Deployment | C27: Patch Management | D27: Usage of a maximum lifetime for images | E27: 485a3383-7f2e-4dba-bb84-479377070904
A28: 18 | B28: Build and Deployment | C28: Patch Management | D28: Usage of a short maximum lifetime for images | E28: 6b96e5a0-ce34-4ea4-a88f-469d3b84546e
A29: 19 | B29: Build and Deployment | C29: Deployment | D29: Same artifact for environments | E29: a854b48d-83bd-4f8d-8621-a0bdd470837f
A30: 20 | B30: Build and Deployment | C30: Deployment | D30: Usage of feature toggles | E30: a511799b-045e-4b96-9843-7d63d8c1e2ad
A31: 21 | B31: Build and Deployment | C31: Deployment | D31: Blue/Green Deployment | E31: 0cb2626b-fb0d-4a0f-9688-57f787310d97
A32: 22 | B32: Build and Deployment | C32: Deployment | D32: Defined deployment process | E32: 74938a3f-1269-49b9-9d0f-c43a79a1985a
... A36: 26 | B36: Build and Deployment | C36: Deployment | D36: Inventory of production dependencies | E36: 13e9757e-58e2-4277-bc0f-eadc674891e6
A37: 27 | B37: Culture and Organization | C37: Design | D37: Conduction of simple threat modeling on technical level | E37: 47419324-e263-415b-815d-e7161b6b905e | F37: =Практики!C306 -> P-REQ-TM-0-1 | G37: =Практики!F306 -> Не заполнено | H37: =Практики!Q306 -> 0 | I37: 0
A38: 28 | B38: Culture and Organization | C38: Design | D38: Creation of advanced abuse stories | E38: 0a929c3e-ab9a-4206-8761-adf84b74622e | F38: =Практики!C316 -> P-REQ-TM-4-1 | G38: =Практики!F316 -> Не заполнено | H38: =Практики!Q316 -> 0 | I38: 0
A39: 29 | B39: Culture and Organization | C39: Design | D39: Creation of simple abuse stories | E39: bacf85b6-5bc0-405d-b5ba-a5d971467cc1 | F39: =Практики!C316 -> P-REQ-TM-4-1 | G39: =Практики!F316 -> Не заполнено | H39: =Практики!Q316 -> 0 | I39: 0
A40: 30 | B40: Culture and Organization | C40: Design | D40: Creation of threat modeling processes and standards | E40: dd5ed7c1-bdbf-400f-b75f-6d3953a1a04e | F40: =Практики!C306 -> P-REQ-TM-0-1 | G40: =Практики!F306 -> Не заполнено | H40: =Практики!Q306 -> 0 | I40: 0
F41: =Практики!C314 -> P-REQ-TM-3-2 | G41: =Практики!F314 -> Не заполнено | H41: =Практики!Q314 -> 0
A42: 31 | B42: Culture and Organization | C42: Education and Guidance | D42: Conduction of collaborative security checks with developers and system administrators | E42: 95caef96-36ed-458c-a087-5c35d4f9dec2
A43: 32 | B43: Culture and Organization | C43: Education and Guidance | D43: Security code review | E43: 7121b0c7-6ace-4d6b-95d0-94535dbccb57
A44: 33 | B44: Culture and Organization | C44: Education and Guidance | D44: Ad-Hoc Security trainings for software developers | E44: 12c90cc6-3d58-4d9b-82ff-d469d2a0c298 | F44: =Практики!C285 -> P-EDU-AWR-0-1 | G44: =Практики!F285 -> Не заполнено | H44: =Практики!Q285 -> 0 | I44: 0
A45: 34 | B45: Culture and Organization | C45: Education and Guidance | D45: Conduction of build-it, break-it, fix-it contests | E45: bfdb576e-a416-4ec6-96fe-a078d58b2ff8
A46: 35 | B46: Culture and Organization | C46: Education and Guidance | D46: Office Hours | E46: 185d5a74-19dc-4422-be07-44ea35226783
A47: 36 | B47: Culture and Organization | C47: Education and Guidance | D47: Regular security training for all | E47: 9768f154-357a-4c06-af6f-d66570677c9b | F47: =Практики!C286 -> P-EDU-AWR-1-1 | G47: =Практики!F286 -> Не заполнено | H47: =Практики!Q286 -> 0 | I47: 0
F48: =Практики!C289 -> P-EDU-AWR-2-2 | G48: =Практики!F289 -> Не заполнено | H48: =Практики!Q289 -> 0
A49: 37 | B49: Culture and Organization | C49: Education and Guidance | D49: Regular security training for externals | E49: 31833d56-35af-4ef3-9300-f23d27646ce7
A50: 38 | B50: Culture and Organization | C50: Design | D50: Information security targets are communicated | E50: 1b9281b9-48e2-4c01-9ac6-9db9931c4885
A51: 39 | B51: Culture and Organization | C51: Education and Guidance | D51: Aligning security in teams | E51: f994a55d-71bb-45a4-a887-0a213d72c504
A52: 40 | B52: Culture and Organization | C52: Design | D52: Conduction of simple threat modeling on business level | E52: 48f97f31-931c-46eb-9b3e-e2fec0cd0426 | F52: =Практики!C306 -> P-REQ-TM-0-1 | G52: =Практики!F306 -> Не заполнено | H52: =Практики!Q306 -> 0 | I52: 0
F53: =Практики!C313 -> P-REQ-TM-3-1 | G53: =Практики!F313 -> Не заполнено | H53: =Практики!Q313 -> 0
A54: 41 | B54: Culture and Organization | C54: Design | D54: Conduction of advanced threat modeling | E54: ae22dafd-bcd6-41ee-ba01-8b7fe6fc1ad9 | F54: =Практики!C310 -> P-REQ-TM-2-1 | G54: =Практики!F310 -> Не заполнено | H54: =Практики!Q310 -> 0 | I54: 0
F55: =Практики!C315 -> P-REQ-TM-3-3 | G55: =Практики!F315 -> Не заполнено | H55: =Практики!Q315 -> 0
A56: 42 | B56: Culture and Organization | C56: Education and Guidance | D56: Simple mob hacking | E56: 535f301a-e8e8-4eda-ad77-a08b035c92de
A57: 43 | B57: Culture and Organization | C57: Education and Guidance | D57: Security Coaching | E57: f7b215dc-73a4-4c61-9e49-b3a3af1c9ac3 | F57: =Практики!C385 -> P-ROLE-SC-2-2 | G57: =Практики!F385 -> Не заполнено | H57: =Практики!Q385 -> 0 | I57: 0
A58: 44 | B58: Culture and Organization | C58: Process | D58: Definition of simple BCDR practices for critical components | E58: c72da779-86cc-45b1-a339-190ce5093171
A59: 45 | B59: Culture and Organization | C59: Education and Guidance | D59: Security-Lessoned-Learned | E59: 58c46807-fee9-448b-b6dd-8050c464ab52
A60: 46 | B60: Culture and Organization | C60: Process | D60: Definition of a change management process | E60: b4193d32-3948-47e2-a326-3748c48019a1
A61: 47 | B61: Culture and Organization | C61: Education and Guidance | D61: Conduction of collaborative team security checks | E61: 35446784-7610-40d9-af9e-d43f3173bf8c
A62: 48 | B62: Culture and Organization | C62: Education and Guidance | D62: Conduction of war games | E62: 534f60bf-0995-4314-bb9c-f0f2bf204694
A63: 49 | B63: Culture and Organization | C63: Education and Guidance | D63: Reward of good communication | E63: 91b6f75b-9f4a-4d77-95a2-af7ad3222c7c | F63: =Практики!C292 -> P-EDU-AWR-3-1 | G63: =Практики!F292 -> Не заполнено | H63: =Практики!Q292 -> 0 | I63: 0
A64: 50 | B64: Culture and Organization | C64: Education and Guidance | D64: Each team has a security champion | E64: 6217fe11-5ed7-4cf4-9de4-555bcfa6fe87 | F64: =Практики!C382 -> P-ROLE-SC-0-1 | G64: =Практики!F382 -> Не заполнено | H64: =Практики!Q382 -> 0 | I64: 0
F65: =Практики!C384 -> P-ROLE-SC-2-1 | G65: =Практики!F384 -> Не заполнено | H65: =Практики!Q384 -> 0
A66: 51 | B66: Culture and Organization | C66: Education and Guidance | D66: Regular security training of security champions | E66: f88d1b17-3d7d-4c3d-8139-ad44fc4942d4 | F66: =Практики!C290 -> P-EDU-AWR-2-3 | G66: =Практики!F290 -> Не заполнено | H66: =Практики!Q290 -> 0 | I66: 0
A67: 52 | B67: Culture and Organization | C67: Process | D67: Approval by reviewing any new version | E67: 3f63bdbc-c75f-4780-a941-e6ad42e894e1
A68: 53 | B68: Culture and Organization | C68: Education and Guidance | D68: Security consulting on request | E68: 0b28367b-75a0-4bae-a926-3725c1bf9bb0 | F68: =Практики!C287 -> P-EDU-AWR-1-2 | G68: =Практики!F287 -> Не заполнено | H68: =Практики!Q287 -> 0 | I68: 0
A69: 54 | B69: Implementation | C69: Infrastructure Hardening | D69: Limitation of system events | E69: e5386abf-9154-4752-a1a8-c3a8900f732d
A70: 55 | B70: Implementation | C70: Infrastructure Hardening | D70: Microservice-architecture | E70: 118b869b-3850-456e-98d9-1abdb85cbc5a
A71: 56 | B71: Implementation | C71: Infrastructure Hardening | D71: Hardening of the Environment | E71: dcf9601b-b4f2-4e25-9143-e39af75f7c33 | F71: =Практики!C7 -> T-ADI-DEP-1-4 | G71: =Практики!F7 -> Не заполнено | H71: =Практики!Q7 -> 0 | I71: 0
F72: =Практики!C51 -> T-DEV-BLD-3-2 | G72: =Практики!F51 -> Не заполнено | H72: =Практики!Q51 -> 0
F73: =Практики!C44 -> T-DEV-BLD-0-1 | G73: =Практики!F44 -> Не заполнено | H73: =Практики!Q44 -> 0
F74: =Практики!C94 -> T-DEV-CICD-0-1 | G74: =Практики!F94 -> Не заполнено | H74: =Практики!Q94 -> 0
A75: 57 | B75: Implementation | C75: Infrastructure Hardening | D75: Role based authentication and authorization | E75: 070bb14b-e04a-4f3d-896a-a08eba7a35f9 | F75: =Практики!C18 -> T-ADI-ART-1-2 | G75: =Практики!F18 -> Не заполнено | H75: =Практики!Q18 -> 0 | I75: 0
F76: =Практики!C54 -> T-DEV-SCM-0-1 | G76: =Практики!F54 -> Не заполнено | H76: =Практики!Q54 -> 0
F77: =Практики!C55 -> T-DEV-SCM-1-1 | G77: =Практики!F55 -> Не заполнено | H77: =Практики!Q55 -> 0
F78: =Практики!C45 -> T-DEV-BLD-1-1 | G78: =Практики!F45 -> Не заполнено | H78: =Практики!Q45 -> 0
A79: 58 | B79: Implementation | C79: Infrastructure Hardening | D79: Simple access control for systems | E79: 82e499d1-f463-4a4b-be90-68812a874af6 | F79: =Практики!C18 -> T-ADI-ART-1-2 | G79: =Практики!F18 -> Не заполнено | H79: =Практики!Q18 -> 0 | I79: 0
F80: =Практики!C45 -> T-DEV-BLD-1-1 | G80: =Практики!F45 -> Не заполнено | H80: =Практики!Q45 -> 0
A81: 59 | B81: Implementation | C81: Infrastructure Hardening | D81: MFA | E81: 598e9f13-1ac8-4a01-b85e-8fab93ee81de | F81: =Практики!C19 -> T-ADI-ART-1-3 | G81: =Практики!F19 -> Не заполнено | H81: =Практики!Q19 -> 0 | I81: 0
F82: =Практики!C70 -> T-DEV-SCM-3-3 | G82: =Практики!F70 -> Не заполнено | H82: =Практики!Q70 -> 0
F83: =Практики!C25 -> T-ADI-ART-3-2 | G83: =Практики!F25 -> Не заполнено | H83: =Практики!Q25 -> 0
A84: 60 | B84: Implementation | C84: Infrastructure Hardening | D84: MFA for admins | E84: 8098e416-e1ed-4ae4-a561-83efbe76bf57 | F84: =Практики!C18 -> T-ADI-ART-1-2 | G84: =Практики!F18 -> Не заполнено | H84: =Практики!Q18 -> 0 | I84: 0
F85: =Практики!C70 -> T-DEV-SCM-3-3 | G85: =Практики!F70 -> Не заполнено | H85: =Практики!Q70 -> 0
F86: =Практики!C25 -> T-ADI-ART-3-2 | G86: =Практики!F25 -> Не заполнено | H86: =Практики!Q25 -> 0
F87: =Практики!C19 -> T-ADI-ART-1-3 | G87: =Практики!F19 -> Не заполнено | H87: =Практики!Q19 -> 0
A88: 61 | B88: Implementation | C88: Development and Source Control | D88: Local development linting & style checks performed | E88: 517b0957-4981-4ac0-b4c7-0d8d1934c474
A89: 62 | B89: Implementation | C89: Infrastructure Hardening | D89: WAF Advanced | E89: f0e01814-3b88-4bd0-a3a9-f91db001d20b-advanced
A90: 63 | B90: Implementation | C90: Development and Source Control | D90: Block force pushes | E90: c7d99b18-c3e1-4d22-b2e3-9aa9146c0b17 | F90: =Практики!C93 -> T-DEV-SRC-4-1 | G90: =Практики!F93 -> Не заполнено | H90: =Практики!Q93 -> 0 | I90: 0
A91: 64 | B91: Implementation | C91: Development and Source Control | D91: Dismiss stale PR approvals | E91: ea6f69f7-54a5-4922-ac15-a77ff0c16162
A92: 65 | B92: Implementation | C92: Development and Source Control | D92: Require a PR before merging | E92: e7598ac4-b082-4e56-b7df-e2c6b426a5e2 | F92: =Практики!C86 -> T-DEV-SRC-2-6 | G92: =Практики!F86 -> Не заполнено | H92: =Практики!Q86 -> 0 | I92: 0
A93: 66 | B93: Implementation | C93: Infrastructure Hardening | D93: Production near environments are used by developers | E93: e14de741-94b3-447c-8b07-eea947d82e61
A94: 67 | B94: Implementation | C94: Development and Source Control | D94: .gitignore | E94: 363a3eea-baf9-4010-88ca-bb8186a2989d
A95: 68 | B95: Implementation | C95: Development and Source Control | D95: Require status checks to pass | E95: ac8730a2-ccc0-465c-9550-d91edae9d5ee | F95: =Практики!C82 -> T-DEV-SRC-2-2 | G95: =Практики!F82 -> Не заполнено | H95: =Практики!Q82 -> 0 | I95: 0
F96: =Практики!C92 -> T-DEV-SRC-3-6 | G96: =Практики!F92 -> Не заполнено | H96: =Практики!Q92 -> 0 | I96: 0
A97: 69 | B97: Implementation | C97: Application Hardening | D97: App. Hardening Level 1 | E97: cf819225-30cb-4702-8e32-60225eedc33d
A98: 70 | B98: Implementation | C98: Application Hardening | D98: App. Hardening Level 1 (50%) | E98: b597928e-54d6-48a5-a806-8003dcd56aab
A99: 71 | B99: Implementation | C99: Application Hardening | D99: App. Hardening Level 2 | E99: ffe86caf-2fec-4630-b514-2db83983984d
A100: 72 | B100: Implementation | C100: Application Hardening | D100: App. Hardening Level 2 (75%) | E100: 03643ca2-03c2-472b-8e19-956bf02fe9b7
A101: 73 | B101: Implementation | C101: Application Hardening | D101: App. Hardening Level 3 | E101: 4cae98c2-4163-44ed-bb88-3c67c569533a
A102: 74 | B102: Implementation | C102: Application Hardening | D102: Containers are running as non-root | E102: a86c1fbc-28fd-4610-89a3-a7f73acfe45f
A103: 75 | B103: Implementation | C103: Application Hardening | D103: Context-aware output encoding | E103: e1f37abb-d848-4a3a-b3df-65e91a89dcb7
...

Sheet ГОСТ56939_mapping
A1: ID | B1: Является требованием? | C1: Маппинг? | D1: ID_требования | E1: Требование ГОСТ 56939-2024 | F1: Практика DAF | G1: Выполнение практики DAF | H1: Комментарий | J1: Замаплено | K1: Всего требований | L1: % Маппинга на DAF
A2: 5.1 | C2: =IF(F2<>"",1,"") | E2: Планирование процессов разработки безопасного программного обеспечения | J2: =COUNT(C2:C429) -> 57 | K2: =COUNTA(B2:B429) -> 118 | L2: =(J2/K2)*100 -> 48.305085
A3: 5.1.1 | C3: =IF(F3<>"",1,"") | E3: Цели
C4: =IF(F4<>"",1,"") | D4: 5.1.1.1 | E4: Обеспечение потребностей в ресурсах, необходимых для реализации процессов разработки безопасного ПО.
C5: =IF(F5<>"",1,"") | D5: 5.1.1.2 | E5: Подготовка и планирование внедрения и улучшения процессов разработки безопасного ПО.
C6: =IF(F6<>"",1,"") | D6: 5.1.1.3 | E6: Определение области применения процессов разработки безопасного ПО.
A7: 5.1.2 | C7: =IF(F7<>"",1,"") | E7: Требования к реализации
B8: Требование | C8: =IF(F8<>"",1,"") -> 1 | D8: 5.1.2.1 | E8: Выполнять периодический анализ текущего статуса реализации процессов разработки безопасного ПО. | F8: =Практики!C402 -> P-ROLE-RESP-3-2 | G8: =Практики!F402 -> Не заполнено | H8: =Практики!Q402 -> 0
B9: Требование | C9: =IF(F9<>"",1,"") | D9: 5.1.2.2 | E9: Выполнять периодический анализ потребностей в ресурсах, необходимых для реализации процессов разработки безопасного ПО.
B10: Требование | C10: =IF(F10<>"",1,"") -> 1 | D10: 5.1.2.3 | E10: Разрабатывать план развития процессов разработки безопасного ПО. Артефакты реализации требований, учитываемые при выполнении требования, представлены в 5.1.3.1, 5.1.3.2. | F10: =Практики!C400 -> P-ROLE-RESP-2-4 | G10: =Практики!F400 -> Не заполнено | H10: =Практики!Q400 -> 0
B11: Требование | C11: =IF(F11<>"",1,"") -> 1 | D11: 5.1.2.4 | E11: Разрабатывать план реализации процессов разработки безопасного ПО. Артефакты реализации требований, учитываемые при выполнении требования, представлены в 5.1.3.1, 5.1.3.2. | F11: =Практики!C400 -> P-ROLE-RESP-2-4 | G11: =Практики!F400 -> Не заполнено | H11: =Практики!Q400 -> 0
B12: Требование | C12: =IF(F12<>"",1,"") | D12: 5.1.2.5 | E12: Определять область применения процессов разработки безопасного ПО.
A13: 5.1.3 | C13: =IF(F13<>"",1,"") | E13: Артефакты реализации требований
C14: =IF(F14<>"",1,"") | D14: 5.1.3.1 | E14: Результаты анализа текущего статуса реализации процессов разработки безопасного ПО должны содержать следующие сведения: - перечень процессов разработки безопасного ПО, реализованных и не реализованных разработчиком; - результаты определения достаточности и соответствия процессов разработки безопасного ПО, реализованных разработчиком, положениям настоящего стандарта и иным стандартам, содержащим требования к разработке безопасного ПО, используемым инструментам и технологиям.
C15: =IF(F15<>"",1,"") | D15: 5.1.3.2 | E15: Результаты анализа потребностей в ресурсах, необходимых для реализации процессов разработки безопасного ПО, могут содержать оценочные показатели в материальных и людских ресурсах для каждого реализуемого или планируемого к реализации процесса разработки безопасного ПО.
C16: =IF(F16<>"",1,"") | D16: 5.1.3.3 | E16: План развития процессов разработки безопасного ПО должен содержать порядок (очередность) внедрения процессов разработки безопасного ПО с учетом приоритетов разработчика и имеющихся ресурсов, планируемые изменения в организационно-штатной структуре разработчика, планируемые закупки необходимых инструментов, затраты на обучение и др.
C17: =IF(F17<>"",1,"") | D17: 5.1.3.4 | E17: План реализации процессов разработки безопасного ПО должен содержать цели, сроки и этапы внедрения процессов разработки безопасного ПО; перечень необходимых ресурсов; информацию об ответственных за внедрение процессов сотрудниках.
C18: =IF(F18<>"",1,"") | D18: 5.1.3.5 | E18: Описание области применения процессов разработки безопасного ПО должно содержать состав ПО (версии, модули, компоненты, функциональные подсистемы и т. п.), в отношении которого должны быть реализованы процессы разработки безопасного ПО, с обоснованием выбора указанного состава ПО.
A19: 5.2 | C19: =IF(F19<>"",1,"") | E19: Обучение сотрудников
A20: 5.2.1 | C20: =IF(F20<>"",1,"") | E20: Цели
C21: =IF(F21<>"",1,"") | D21: 5.2.1.1 | E21: Получение актуальной информации о существующих (доступных для анализа) практиках, документах, обучающих курсах и тренингах по разработке безопасного ПО.
C22: =IF(F22<>"",1,"") | D22: 5.2.1.2 | E22: Организация обучения сотрудников типовым практикам разработки безопасного ПО с учетом актуальных потребностей.
C23: =IF(F23<>"",1,"") | D23: 5.2.1.3 | E23: Создание условий для снижения количества возможных типовых ошибок и уязвимостей в разрабатываемом ПО.
A24: 5.2.2 | C24: =IF(F24<>"",1,"") | E24: Требования к реализации
B25: Требование | C25: =IF(F25<>"",1,"") -> 1 | D25: 5.2.2.1 | E25: Проводить анализ существующих (доступных для анализа) практик, документов, обучающих курсов и тренингов по разработке безопасного ПО. Входными данными требования к реализации являются существующие (доступные для анализа) практики, документы, обучающие курсы и тренинги по разработке безопасного ПО. | F25: =Практики!C300 -> P-EDU-KB-3-2 | G25: =Практики!F300 -> Не заполнено | H25: =Практики!Q300 -> 0
B26: Требование | C26: =IF(F26<>"",1,"") | D26: 5.2.2.2 | E26: Разрабатывать план обучения с учетом потребностей разработчика в части используемых средств и технологий разработки. Артефакты реализации требований, учитываемые при выполнении требования, представлены в 5.2.3.1.
B27: Требование | C27: =IF(F27<>"",1,"") -> 1 | D27: 5.2.2.3 | E27: Проводить обучение сотрудников. Артефакты реализации требований, учитываемые при выполнении требования, представлены в 5.2.3.2. | F27: =Практики!C285 -> P-EDU-AWR-0-1 | G27: =Практики!F285 -> Не заполнено | H27: =Практики!Q285 -> 0
F28: =Практики!C287 -> P-EDU-AWR-1-2 | G28: =Практики!F287 -> Не заполнено | H28: =Практики!Q287 -> 0
F29: =Практики!C288 -> P-EDU-AWR-2-1 | G29: =Практики!F288 -> Не заполнено | H29: =Практики!Q288 -> 0
B30: Требование | C30: =IF(F30<>"",1,"") | D30: 5.2.2.4 | E30: Вести учет обучения сотрудников. Артефакты реализации требований, учитываемые при выполнении требования, представлены в 5.2.3.2. 5.2.3.3, 5.2.3.6.
B31: Требование | C31: =IF(F31<>"",1,"") | D31: 5.2.2.5 | E31: Определить критерии пересмотра программ обучения (курсов, тренингов и т. п.).
B32: Требование | C32: =IF(F32<>"",1,"") -> 1 | D32: 5.2.2.6 | E32: Повышать осведомленность сотрудников разработчика о возможных типовых угрозах, ошибках и уязвимостях в разрабатываемом ПО, механизмах их недопущения или минимизации вероятности их возникновения, порядке сопровождения ПО и управления жизненным циклом. Артефакты реализации требований, учитываемые при выполнении требования, представлены в 5.2.3.1. | F32: =Практики!C287 -> P-EDU-AWR-1-2 | G32: =Практики!F287 -> Не заполнено | H32: =Практики!Q287 -> 0
F33: =Практики!C288 -> P-EDU-AWR-2-1 | G33: =Практики!F288 -> Не заполнено | H33: =Практики!Q288 -> 0
A34: 5.2.3 | C34: =IF(F34<>"",1,"") | E34: Артефакты реализации требований
C35: =IF(F35<>"",1,"") | D35: 5.2.3.1 | E35: Результаты анализа существующих (доступных для анализа) практик, документов, обучающих курсов и тренингов по разработке безопасного ПО с точки зрения их применимости для обучения сотрудников разработчика.
C36: =IF(F36<>"",1,"") | D36: 5.2.3.2 | E36: План обучения, включающий: - список сотрудников, направляемых на обучение; - сроки прохождения обучения; - наименование программы (курса, тренинга) обучения; - ожидаемый результат обучения.
C37: =IF(F37<>"",1,"") | D37: 5.2.3.3 | E37: Артефакты реализации требований, подтверждающие прохождение обучения, включают (в зависимости от учебной программы, курса) свидетельства, дипломы, отчеты обучающих платформ и иные документы и материалы, подтверждающие прохождение сотрудником обучения.
C38: =IF(F38<>"",1,"") | D38: 5.2.3.4 | E38: Артефакты реализации требований, подтверждающие осуществление учета обучения сотрудников, должны содержать информацию о сотрудниках, прошедших обучение, пройденных программах (курсах) и результатах прохождения обучения.
C39: =IF(F39<>"",1,"") | D39: 5.2.3.5 | E39: Критерии необходимости пересмотра программ обучения (курсов, тренингов и т. п.) должны содержать информацию о периодичности пересмотра (уточнения) программ обучения (курсов, тренингов и т. п.) или о событиях, при наступлении которых необходимо изменение программ обучения (курсов, тренингов и т. п.).
C40: =IF(F40<>"",1,"") | D40: 5.2.3.6 | E40: Артефакты реализации требований, подтверждающие осуществление повышения осведомленности сотрудников, должны содержать информацию о проведенных мероприятиях по повышению осведомленности сотрудников о возможных типовых угрозах, ошибках и уязвимостях в разрабатываемом ПО, механизмах их недопущения или минимизации вероятности их возникновения, порядке сопровождения ПО и управления жизненным циклом, а также о сотрудниках (подразделениях), для которых проводились мероприятия по повышению осведомленности.
A41: 5.3 | C41: =IF(F41<>"",1,"") | E41: Формирование и предъявление требований безопасности к программному обеспечению
A42: 5.3.1 | C42: =IF(F42<>"",1,"") | E42: Цели
C43: =IF(F43<>"",1,"") | D43: 5.3.1.1 | E43: Обеспечение безопасности ПО посредством предъявления к нему требований и управления требованиями в процессе изменения (разработки) ПО.
A44: 5.3.2 | C44: =IF(F44<>"",1,"") -> 1 | E44: Требования к реализации | F44: =Практики!C327 -> P-REQ-CR-0-1 | G44: =Практики!F327 -> Не заполнено | H44: =Практики!Q327 -> 0
B45: Требование | C45: =IF(F45<>"",1,"") -> 1 | D45: 5.3.2.1 | E45: Разработать регламент управления требованиями безопасности ПО. | F45: =Практики!C321 -> P-REQ-RD-2-2 | G45: =Практики!F321 -> Не заполнено | H45: =Практики!Q321 -> 0
B46: Требование | C46: =IF(F46<>"",1,"") -> 1 | D46: 5.3.2.2 | E46: Предъявлять к ПО требования безопасности. Артефакты реализации требований, учитываемые при выполнении требования, представлены в 5.3.3.1. | F46: =Практики!C317 -> P-REQ-RD-0-1 | G46: =Практики!F317 -> Не заполнено | H46: =Практики!Q317 -> 0
F47: =Практики!C318 -> P-REQ-RD-1-1 | G47: =Практики!F318 -> Не заполнено | H47: =Практики!Q318 -> 0
B48: Требование | C48: =IF(F48<>"",1,"") | D48: 5.3.2.3 | E48: Вести учет предъявленных требований безопасности и контроль однозначности трактования и непротиворечивости набора требований безопасности ПО. Артефакты реализации требований, учитываемые при выполнении требования, представлены в 5.3.3.2.
B49: Требование | C49: =IF(F49<>"",1,"") | D49: 5.3.2.4 | E49: Осуществлять пересмотр набора требований безопасности на основе выполнения критериев пересмотра — с установленной периодичностью или при наступлении определенных событий. Артефакты реализации требований, учитываемые при выполнении требования, представлены в 5.3.3.1, 5.3.3.2.
A50: 5.3.3 | C50: =IF(F50<>"",1,"") | E50: Артефакты реализации требований
C51: =IF(F51<>"",1,"") | D51: 5.3.3.1 | E51: Регламент управления требованиями безопасности ПО должен включать следующие положения: - порядок предъявления требований безопасности ПО; - порядок предоставления требований безопасности ПО исполнителям; - порядок отслеживания процесса предоставления, получения и выполнения требований безопасности ПО; - критерии пересмотра требований безопасности ПО (периодически, при наступлении определенных событий).
C52: =IF(F52<>"",1,"") | D52: 5.3.3.2 | E52: Набор требований безопасности ПО должен содержать следующую информацию: - идентификатор требования безопасности ПО; - формулировку требования безопасности ПО; - дату предъявления требований безопасности ПО; - приоритет/важность требования безопасности ПО; - предполагаемые сроки реализации; - сведения о сотрудниках (подразделениях), предъявивших требования; - сведения о сотрудниках (подразделениях), принявших требования к реализации.
C53: =IF(F53<>"",1,"") | D53: 5.3.3.3 | E53: Артефакты реализации требований, подтверждающие осуществление учета предъявленных требований безопасности ПО, должны включать, как минимум, следующую информацию: - сведения о принятии требований к реализации, подтверждающие однозначность трактования и непротиворечивость набора требований безопасности ПО; - текущий статус реализации требований; - сведения об изменениях статуса реализации предъявленных требований безопасности ПО; - сведения об изменениях предъявленных требований безопасности ПО.
C54: =IF(F54<>"",1,"") | D54: 5.3.3.4 | E54: Набор требований безопасности ПО, уточненный по результатам выполнения требований 5.3.2.4, должен содержать информацию об особенностях реализации требований безопасности ПО в процессе разработки ПО, принятых решениях по корректировкам требований безопасности ПО в процессе разработки.
A55: 5.4 | C55: =IF(F55<>"",1,"") | E55: Управление конфигурацией программного обеспечения
A56: 5.4.1 | C56: =IF(F56<>"",1,"") | E56: Цели
C57: =IF(F57<>"",1,"") | D57: 5.4.1.1 | E57: Осуществление уникальной идентификации ПО, документации на ПО, других элементов, подлежащих отслеживанию в рамках управления конфигурацией ПО (элементов конфигурации).
C58: =IF(F58<>"",1,"") | D58: 5.4.1.2 | E58: Контроль реализации изменений ПО, документации на ПО, других элементов, подлежащих отслеживанию в рамках управления конфигурацией ПО (элементов конфигурации).
A59: 5.4.2 | C59: =IF(F59<>"",1,"") | E59: Требования к реализации
B60: Требование | C60: =IF(F61<>"",1,"") -> 1 | D60: 5.4.2.1 | E60: Разработать регламент управления конфигурацией в рамках жизненного цикла ПО. | F60: =Практики!C335 -> P-REQ-STDR-App-2-1 | G60: =Практики!F335 -> Не заполнено | H60: =Практики!Q335 -> 0
F61: =Практики!C336 -> P-REQ-STDR-App-3-1 | G61: =Практики!F336 -> Не заполнено | H61: =Практики!Q336 -> 0
B62: Требование | C62: =IF(F62<>"",1,"") | D62: 5.4.2.2 | E62: Определить перечень элементов конфигурации, подлежащих отслеживанию в рамках управления конфигурацией ПО.
B63: Требование | C63: =IF(F63<>"",1,"") -> 1 | D63: 5.4.2.3 | E63: Контролировать реализацию изменений ПО, документации на ПО, других элементов, подлежащих отслеживанию в рамках управления конфигурацией ПО (элементов конфигурации). | F63: =Практики!C251 -> T-PROD-ACCESS-1-3 | G63: =Практики!F251 -> Не заполнено | H63: =Практики!Q251 -> 0
A64: 5.4.3 | C64: =IF(F64<>"",1,"") | E64: Артефакты реализации требований
C65: =IF(F65<>"",1,"") | D65: 5.4.3.1 | E65: Регламент управления конфигурацией ПО должен содержать: - порядок формирования перечня элементов ПО (компонентов, модулей и т. п.), документации на ПО, подлежащих отслеживанию в рамках жизненного цикла ПО; - порядок идентификации ПО (версий ПО, модулей ПО), документации для отслеживаемых элементов.
C66: =IF(F66<>"",1,"") | D66: 5.4.3.2 | E66: Перечень элементов конфигурации, подлежащих отслеживанию в рамках управления конфигурацией ПО.
C67: =IF(F67<>"",1,"") | D67: 5.4.3.3 | E67: Артефакты реализации требований, подтверждающие реализацию управления изменениями ПО, документации на ПО в рамках управления конфигурацией ПО, должны отображать факты изменения ПО (модулей ПО), документации на ПО.
A68: 5.5 | C68: =IF(F68<>"",1,"") | E68: Управление недостатками и запросами на изменение программного обеспечения
A69: 5.5.1 | C69: =IF(F69<>"",1,"") | E69: Цели
C70: =IF(F70<>"",1,"") | D70: 5.5.1.1 | E70: Обеспечение управления недостатками ПО.
C71: =IF(F71<>"",1,"") | D71: 5.5.1.2 | E71: Обеспечение управления запросами на изменение ПО. Примечание — Управление недостатками и запросами на изменение ПО способствует систематическому устранению ошибок программирования, отклонений от заданных требований и корректировке требований в необходимых случаях путем осуществления запросов на изменение ПО — предложений о добавлении, модификации или удалении каких-либо элементов (модулей, компонентов, функциональных возможностей) ПО.
A72: 5.5.2 | C72: =IF(F72<>"",1,"") | E72: Требования к реализации
B73: Требование | C73: =IF(F73<>"",1,"") | D73: 5.5.2.1 | E73: Разработать регламент управления недостатками ПО.
B74: Требование | C74: =IF(F74<>"",1,"") | D74: 5.5.2.2 | E74: Разработать регламент управления запросами на изменение ПО.
B75: Требование | C75: =IF(F75<>"",1,"") -> 1 | D75: 5.5.2.3 | E75: Контролировать реализацию изменений, связанных с недостатками ПО. | F75: =Практики!C75 -> T-DEV-SRC-0-1 | G75: =Практики!F75 -> Не заполнено | H75: =Практики!Q75 -> 0
F76: =Практики!C76 -> T-DEV-SRC-1-1 | G76: =Практики!F76 -> Не заполнено | H76: =Практики!Q76 -> 0
F77: =Практики!C350 -> P-DEFECT-MNG-0-1 | G77: =Практики!F350 -> Не заполнено | H77: =Практики!Q350 -> 0
B78: Требование | C78: =IF(F78<>"",1,"") | D78: 5.5.2.4 | E78: Контролировать реализацию запросов на изменение в рамках жизненного цикла ПО.
B79: Требование | C79: =IF(F79<>"",1,"") -> 1 | D79: 5.5.2.5 | E79: Использовать средства автоматизации для управления недостатками и запросами на изменение разрабатываемого ПО. | F79: =Практики!C76 -> T-DEV-SRC-1-1 | G79: =Практики!F76 -> Не заполнено | H79: =Практики!Q76 -> 0
F80: =Практики!C150 -> T-CODE-IMG-2-3 | G80: =Практики!F150 -> Не заполнено | H80: =Практики!Q150 -> 0
F81: =Практики!C354 -> P-DEFECT-MNG-3-1 | G81: =Практики!F354 -> Не заполнено | H81: =Практики!Q354 -> 0
A82: 5.5.3 | C82: =IF(F82<>"",1,"") | E82: Артефакты реализации требований
C83: =IF(F83<>"",1,"") | D83: 5.5.3.1 | E83: Регламент управления недостатками ПО должен содержать: - порядок идентификации недостатков ПО; - порядок управления недостатками ПО, включающий сведения о действиях, выполняемых при выявлении, устранении, тестировании, принятии решения об окончании работы с недостатком (закрытии недостатка).
C84: =IF(F84<>"",1,"") | D84: 5.5.3.2 | E84: Регламент управления запросами на изменение ПО должен содержать: - порядок идентификации запросов на изменение ПО; - порядок управления запросами на изменение ПО, включающий сведения о действиях, выполняемых при осуществлении запроса на изменение, тестировании, принятии решения о закрытии запроса на изменение.
C85: =IF(F85<>"",1,"") | D85: 5.5.3.3 | E85: Артефакты реализации требований, подтверждающие реализацию управления недостатками ПО, должны содержать зафиксированные факты изменений, связанных с недостатками, включающие следующую информацию: - уникальный идентификатор недостатка ПО; - описание недостатка ПО; - версию ПО (модуля ПО, компонента ПО), к которому относится недостаток ПО; - приоритет выполнения действий с недостатком ПО; - текущий статус обработки изменений, связанных с недостатками ПО.
C86: =IF(F86<>"",1,"") | D86: 5.5.3.4 | E86: Артефакты реализации требований, подтверждающие реализации управления запросами на изменение ПО, должны содержать следующую информацию: - уникальный идентификатор запроса на изменение ПО; - краткую характеристику запроса на изменение ПО; - версию ПО (модуля ПО, компонента ПО), к которому относится запрос на изменение; - приоритет выполнения действий с запросом на изменение ПО; - текущий статус обработки запроса на изменение ПО.
A87: 5.6 | C87: =IF(F87<>"",1,"") | E87: Разработка, уточнение и анализ архитектуры программного обеспечения
A88: 5.6.1 | C88: =IF(F88<>"",1,"") | E88: Цели
C89: =IF(F89<>"",1,"") | D89: 5.6.1.1 | E89: Создание условий для снижения количества возможных недостатков при разработке архитектуры ПО.
C90: =IF(F90<>"",1,"") | D90: 5.6.1.2 | E90: Уточнение архитектуры ПО в процессе разработки кода.
A91: 5.6.2 | C91: =IF(F91<>"",1,"") | E91: Требования к реализации
B92: Требование | C92: =IF(F92<>"",1,"") -> 1 | D92: 5.6.2.1 | E92: Определить требования безопасности к принципам проектирования архитектуры ПО, направленным на снижение количества возможных недостатков в разрабатываемом ПО. Артефакты реализации требований, учитываемые при выполнении требования, представлены в 5.3.3.2. | F92: =Практики!C322 -> P-REQ-RD-2-3 | G92: =Практики!F322 -> Не заполнено | H92: =Практики!Q322 -> 0
B93: Требование | C93: =IF(F93<>"",1,"") | D93: 5.6.2.2 | E93: Выполнить первичное проектирование архитектуры ПО. Артефакты реализации требований, учитываемые при выполнении требования, представлены в 5.3.3.1, 5.6.3.1.
B94: Требование | C94: =IF(F94<>"",1,"") | D94: 5.6.2.3 | E94: Установить критерии необходимости уточнения архитектуры ПО. Артефакты реализации требований, учитываемые при выполнении требования, представлены в 5.6.3.2.
B95: Требование | C95: =IF(F95<>"",1,"") | D95: 5.6.2.4 | E95: Выполнять уточнение архитектуры ПО в процессе разработки кода и его изменений с установленной периодичностью или при наступлении определенных событий. Артефакты реализации требований, учитываемые при выполнении требования, представлены в 5.6.3.2, 5.6.3.3.
A96: 5.6.3 | C96: =IF(F96<>"",1,"") | E96: Артефакты реализации требований
C97: =IF(F97<>"",1,"") | D97: 5.6.3.1 | E97: Требования к принципам проектирования архитектуры ПО должны содержать информацию, позволяющую на начальном этапе проектирования ПО получить представление о принятых подходах и принципах проектирования архитектуры ПО (например, инкапсуляция, уникальность, разделение задач, применение заимствованных компонентов и т. п.), в том числе с точки зрения безопасности («нулевое доверие», «протоколирование событий», «резервное копирование», «формирование перечня недопустимых событий», «приоритетное использование языков с безопасной моделью памяти» и т. п.).
C98: =IF(F98<>"",1,"") | D98: 5.6.3.2 | E98: Описание архитектуры ПО должно включать, как минимум, следующую информацию: - назначение ПО и сценарии его использования; - описание среды функционирования; - ограничения и указания по применению; - проект ПО на уровне подсистем (модулей), включающий описание их назначения, структуры, особенностей реализации, применяемых языков программирования, взаимодействия друг с другом и другим ПО с указанием соответствующих интерфейсов, сетевых портов, протоколов.
C99: =IF(F99<>"",1,"") | D99: 5.6.3.3 | E99: Критерии необходимости уточнения архитектуры ПО должны содержать информацию о периодичности пересмотра (уточнения) архитектуры ПО в процессе разработки ПО или о событиях, при наступлении которых необходимо уточнять архитектуры ПО.
C100: =IF(F100<>"",1,"") | D100: 5.6.3.4 | E100: Архитектура ПО, уточненная по результатам выполнения требований 5.6.2.4, должна содержать информацию об особенностях реализации ПО в процессе разработки ПО, принятых решениях по корректировкам архитектурных решений в процессе разработки, в том числе связанных с безопасностью, и причинах, их вызвавших.
...

Sheet BSIMM14_mapping
A1: ID | B1: Требование | C1: ID-DAF | D1: Маппинг DAF | E1: Комментарий | F1: Подсчет требований DAF | G1: Подсчет требований BSIMM | I1: Замаплено | J1: Всего требований BSIMM | K1: % Маппинга на DAF
A2: GOVERNANCE | I2: =COUNTA(F2:F256) -> 62 | J2: =COUNTA(G2:G194) -> 126 | K2: =(I2/J2)*100 -> 49.206349
A3: Strategy & Metrics (SM)
A4: SM1.1 | B4: Publish process and evolve as necessary. | C4: =Практики!C297 -> P-EDU-KB-2-1 | D4: =Практики!F297 -> Не заполнено | E4: =Практики!Q297 -> 0 | F4: 0 | G4: 0
A5: SM1.3 | B5: Educate executives on software security. | G5: 0
A6: SM1.4 | B6: Implement security checkpoints and associated governance. | C6: =Практики!C328 -> P-REQ-CR-1-1 | D6: =Практики!F328 -> Не заполнено | E6: =Практики!Q328 -> 0 | F6: 0 | G6: 0
C7: =Практики!C329 -> P-REQ-CR-2-1 | D7: =Практики!F329 -> Не заполнено | E7: =Практики!Q329 -> 0
C8: =Практики!C330 -> P-REQ-CR-3-1 | D8: =Практики!F330 -> Не заполнено | E8: =Практики!Q330 -> 0
C9: =Практики!C331 -> P-REQ-CR-4-1 | D9: =Практики!F331 -> Не заполнено | E9: =Практики!Q331 -> 0
A10: SM2.1 | B10: Publish data about software security internally and use it to drive change. | C10: =Практики!C378 -> P-MET-EX-3-3 | D10: =Практики!F378 -> Не заполнено | E10: =Практики!Q378 -> 0 | F10: 0 | G10: 0
A11: SM2.2 | B11: Enforce security checkpoints and track exceptions. | C11: =Практики!C330 -> P-REQ-CR-3-1 | D11: =Практики!F330 -> Не заполнено | E11: =Практики!Q330 -> 0 | F11: 0 | G11: 0
C12: =Практики!C356 -> P-DEFECT-MNG-3-3 | D12: =Практики!F356 -> Не заполнено | E12: =Практики!Q356 -> 0
A13: SM2.3 | B13: Create or grow a satellite (security champions). | C13: =Практики!C382 -> P-ROLE-SC-0-1 | D13: =Практики!F382 -> Не заполнено | E13: =Практики!Q382 -> 0 | F13: 0 | G13: 0
A14: SM2.6 | B14: Require security sign-off prior to software release | G14: 0
A15: SM2.7 | B15: Create evangelism role and perform internal marketing. | G15: 0
A16: SM3.1 | B16: Use a software asset tracking application with portfolio view. | C16: =Практики!C201 -> T-PREPROD-VULN-2-2 | D16: =Практики!F201 -> Не заполнено | E16: =Практики!Q201 -> 0 | F16: 0 | G16: 0
C17: =Практики!C272 -> T-PROD-VULN-2-2 | D17: =Практики!F272 -> Не заполнено | E17: =Практики!Q272 -> 0
C18: =Практики!C362 -> P-DEFECT-CNS-3-1 | D18: =Практики!F362 -> Не заполнено | E18: =Практики!Q362 -> 0
C19: =Практики!C363 -> P-DEFECT-CNS-3-2 | D19: =Практики!F363 -> Не заполнено | E19: =Практики!Q363 -> 0
C20: =Практики!C364 -> P-DEFECT-CNS-4-1 | D20: =Практики!F364 -> Не заполнено | E20: =Практики!Q364 -> 0
A21: SM3.2 | B21: Make SSI efforts part of external marketing. | G21: 0
A22: SM3.3 | B22: Identify metrics and use them to drive resourcing. | C22: =Практики!C369 -> P-MET-SET-2-1 | D22: =Практики!F369 -> Не заполнено | E22: =Практики!Q369 -> 0 | F22: 0 | G22: 0
C23: =Практики!C371 -> P-MET-SET-3-1 | D23: =Практики!F371 -> Не заполнено | E23: =Практики!Q371 -> 0
C24: =Практики!C374 -> P-MET-EX-2-1 | D24: =Практики!F374 -> Не заполнено | E24: =Практики!Q374 -> 0
A25: SM3.4 | B25: Integrate software-defined lifecycle governance. | C25: =Практики!C97 -> T-DEV-CICD-1-3 | D25: =Практики!F97 -> Не заполнено | E25: =Практики!Q97 -> 0 | F25: 0 | G25: 0
C26: =Практики!C124 -> T-CODE-SST-2-3 | D26: =Практики!F124 -> Не заполнено | E26: =Практики!Q124 -> 0
C27: =Практики!C137 -> T-CODE-SC-2-4 | D27: =Практики!F137 -> Не заполнено | E27: =Практики!Q137 -> 0
C28: =Практики!C148 -> T-CODE-IMG-2-1 | D28: =Практики!F148 -> Не заполнено | E28: =Практики!Q148 -> 0
C29: =Практики!C353 -> P-DEFECT-MNG-2-2 | D29: =Практики!F353 -> Не заполнено | E29: =Практики!Q353 -> 0
A30: SM3.5 | B30: Integrate software supply chain risk management. | C30: =Практики!C130 -> T-CODE-SC-0-1 | D30: =Практики!F130 -> Не заполнено | E30: =Практики!Q130 -> 0 | F30: 0 | G30: 0
A31: Compliance & Policy (CP)
A32: CP1.1 | B32: Unify regulatory pressures. | G32: 0
A33: CP1.2 | B33: Identify privacy obligations. | G33: 0
A34: CP1.3 | B34: Create policy. | G34: 0
A35: CP2.1 | B35: Build a PII inventry. | G35: 0
A36: CP2.2 | B36: Require security sign-off for compliance-related risk. | G36: 0
A37: CP2.3 | B37: Implement and track controls for compliance. | C37: =Практики!C327 -> P-REQ-CR-0-1 | D37: =Практики!F327 -> Не заполнено | E37: =Практики!Q327 -> 0 | F37: 0 | G37: 0
C38: =Практики!C328 -> P-REQ-CR-1-1 | D38: =Практики!F328 -> Не заполнено | E38: =Практики!Q328 -> 0
C39: =Практики!C329 -> P-REQ-CR-2-1 | D39: =Практики!F329 -> Не заполнено | E39: =Практики!Q329 -> 0
A40: CP2.4 | B40: Include software security SLAs in all vendor contracts. | G40: 0
A41: CP2.5 | B41: Ensure executive awareness of compliance and privacy obligations. | G41: 0
A42: CP3.1 | B42: Document a software compliance story. | G42: 0
A43: CP3.2 | B43: Drive feedback from software lifecycle data back to policy. | G43: 0
A44: CP3.3 | B44: Ensure compatible vendor policies. | C44: =Практики!C379 -> P-MET-EX-4-1 | D44: =Практики!F379 -> Не заполнено | E44: =Практики!Q379 -> 0 | F44: 0 | G44: 0
A45: Training (T)
A46: T1.1 | B46: Conduct software security awareness training. | C46: =Практики!C288 -> P-EDU-AWR-2-1 | D46: =Практики!F288 -> Не заполнено | E46: =Практики!Q288 -> 0 | F46: 0 | G46: 0
A47: T1.7 | B47: Deliver on-demand individual training | G47: 0
A48: T1.8 | B48: Include security resources in onboarding. | C48: =Практики!C390 -> P-ROLE-SC-4-1 | D48: =Практики!F390 -> Не заполнено | E48: =Практики!Q390 -> 0 | F48: 0 | G48: 0
A49: T2.5 | B49: Enhance satellite (security champions) through training and events. | C49: =Практики!C290 -> P-EDU-AWR-2-3 | D49: =Практики!F290 -> Не заполнено | E49: =Практики!Q290 -> 0 | F49: 0 | G49: 0
A50: T2.8 | B50: Create and use material specific to company history. | G50: 0
A51: T2.9 | B51: Deliver role-specific advanced curriculum. | C51: =Практики!C288 -> P-EDU-AWR-2-1 | D51: =Практики!F288 -> Не заполнено | E51: =Практики!Q288 -> 0 | F51: 0 | G51: 0
C52: =Практики!C290 -> P-EDU-AWR-2-3 | D52: =Практики!F290 -> Не заполнено | E52: =Практики!Q290 -> 0
A53: T2.10 | B53: Host software security events | G53: 0
A54: T2.11 | B54: Require an annual refresher. | G54: 0
A55: T2.12 | B55: Provide expertise via open collaboration channels. | C55: =Практики!C292 -> P-EDU-AWR-3-1 | D55: =Практики!F292 -> Не заполнено | E55: =Практики!Q292 -> 0 | F55: 0 | G55: 0
A56: T3.1 | B56: Reward progression through curriculum. | C56: =Практики!C293 -> P-EDU-AWR-3-2 | D56: =Практики!F293 -> Не заполнено | E56: =Практики!Q293 -> 0 | F56: 0 | G56: 0
A57: T3.2 | B57: Trovide training for vendors and outsourced workers. | G57: 0
A58: T3.6 | B58: Identify new satellite members (security champions) through observation. | G58: 0
A59: INTELLIGENCE
A60: Attack Models (AM)
A61: AM1.2 | B61: Use a data classification scheme for software inventory. | G61: 0
A62: AM1.3 | B62: Identify potential attackers. | C62: =Практики!C314 -> P-REQ-TM-3-2 | D62: =Практики!F314 -> Не заполнено | E62: =Практики!Q314 -> 0 | F62: 0 | G62: 0
A63: AM1.5 | B63: Gather and use attack intelligence. | G63: 0
A64: AM2.1 | B64: Build attack patterns and abuse cases tied to potential attackers. | C64: =Практики!C316 -> P-REQ-TM-4-1 | D64: =Практики!F316 -> Не заполнено | E64: =Практики!Q316 -> 0 | F64: 0 | G64: 0
A65: AM2.6 | B65: Collect and publish attack stories | G65: 0
A66: AM2.7 | B66: Build an internal forum to discuss attacks. | G66: 0
A67: AM2.8 | B67: Have a research group that develops new attack methods. | G67: 0
A68: AM2.9 | B68: Monitor automated asset creation | C68: =Практики!C201 -> T-PREPROD-VULN-2-2 | D68: =Практики!F201 -> Не заполнено | E68: =Практики!Q201 -> 0 | F68: 0 | G68: 0
C69: =Практики!C272 -> T-PROD-VULN-2-2 | D69: =Практики!F272 -> Не заполнено | E69: =Практики!Q272 -> 0
A70: AM3.2 | B70: Create and use automation to mimic attackers. | G70: 0
A71: AM3.4 | B71: Create technology-specific attack patterns. | G71: 0
A72: AM3.5 | B72: Maintain and use a top N possible attacks list | G72: 0
A73: Security Features & Design (SFD)
A74: SFD1.1 | B74: Integrate and deliver security features | G74: 0
A75: SFD1.2 | B75: Application architecture teams engage with the SSG. | C75: =Практики!C322 -> P-REQ-RD-2-3 | D75: =Практики!F322 -> Не заполнено | E75: =Практики!Q322 -> 0 | F75: 0 | G75: 0
A76: SFD2.1 | B76: Leverage secure-by-design components and services | G76: 0
A77: SFD2.2 | B77: Create capability to solve difficult design problems | G77: 0
A78: SFD3.1 | B78: Form a review board to approve and maintain secure design patterns. | G78: 0
A79: SFD3.2 | B79: Require use of approved security features and frameworks. | G79: 0
A80: SFD3.3 | B80: Find and publish secure design patterns from the organization. | G80: 0
A81: Standards & Requirements (SR)
A82: SR1.1 | B82: Create security standards. | C82: =Практики!C297 -> P-EDU-KB-2-1 | D82: =Практики!F297 -> Не заполнено | E82: =Практики!Q297 -> 0 | F82: 0 | G82: 0
C83: =Практики!C298 -> P-EDU-KB-2-3 | D83: =Практики!F298 -> Не заполнено | E83: =Практики!Q298 -> 0
A84: SR1.2 | B84: Create a security portal. | C84: =Практики!C297 -> P-EDU-KB-2-1 | D84: =Практики!F297 -> Не заполнено | E84: =Практики!Q297 -> 0 | F84: 0 | G84: 0
C85: =Практики!C298 -> P-EDU-KB-2-3 | D85: =Практики!F298 -> Не заполнено | E85: =Практики!Q298 -> 0
C86: =Практики!C299 -> P-EDU-KB-3-1 | D86: =Практики!F299 -> Не заполнено | E86: =Практики!Q299 -> 0
C87: =Практики!C300 -> P-EDU-KB-3-2 | D87: =Практики!F300 -> Не заполнено | E87: =Практики!Q300 -> 0
A88: SR1.5 | B88: Translate compliance constraints to requirements. | C88: =Практики!C11 -> T-ADI-DEP-3-1 | D88: =Практики!F11 -> Не заполнено | E88: =Практики!Q11 -> 0 | F88: 0 | G88: 0
C89: =Практики!C24 -> T-ADI-ART-3-1 | D89: =Практики!F24 -> Не заполнено | E89: =Практики!Q24 -> 0
C90: =Практики!C133 -> T-CODE-SC-1-3 | D90: =Практики!F133 -> Не заполнено | E90: =Практики!Q133 -> 0
A91: SR1.3 | B91: Identify open source. | G91: 0
A92: SR2.2 | B92: Create a standards review process. | C92: =Практики!C300 -> P-EDU-KB-3-2 | D92: =Практики!F300 -> Не заполнено | E92: =Практики!Q300 -> 0 | F92: 0 | G92: 0
A93: SR2.5 | B93: Create SLA boilerplate | G93: 0
A94: SR2.7 | B94: Control open source risk. | C94: =Практики!C6 -> T-ADI-DEP-1-3 | D94: =Практики!F6 -> Не заполнено | E94: =Практики!Q6 -> 0 | F94: 0 | G94: 0
C95: =Практики!C9 -> T-ADI-DEP-2-1 | D95: =Практики!F9 -> Не заполнено | E95: =Практики!Q9 -> 0
C96: =Практики!C138 -> T-CODE-SC-2-5 | D96: =Практики!F138 -> Не заполнено | E96: =Практики!Q138 -> 0
A97: SR3.2 | B97: Communicate standards to vendors | G97: 0
A98: SR3.3 | B98: Use secure coding standards. | C98: =Практики!C299 -> P-EDU-KB-3-1 | D98: =Практики!F299 -> Не заполнено | E98: =Практики!Q299 -> 0 | F98: 0 | G98: 0
A99: SR3.4 | B99: Create standards for technology stacks. | C99: =Практики!C342 -> P-REQ-STDR-Infr-2-1 | D99: =Практики!F342 -> Не заполнено | E99: =Практики!Q342 -> 0 | F99: 0 | G99: 0
C100: =Практики!C344 -> P-REQ-STDR-Infr-3-1 | D100: =Практики!F344 -> Не заполнено | E100: =Практики!Q344 -> 0
...
